Workbook
Name AGROCHEMICAL: #REF!
Name Base_year: #REF!
Name BAU_Absolute: OFFSET(#REF!,0,0,DCOUNTA(#REF!,"BAU Absolute",#REF!))
Name BAU_Absolute_S3: OFFSET(#REF!,0,0,DCOUNTA(#REF!,"BAU Absolute S3",#REF!))
Name BAU_Intensity: OFFSET(#REF!,0,0, DCOUNTA(#REF!,"BAU Intensity",#REF!))
Name BAU_Intensity_S3: OFFSET(#REF!,0,0,DCOUNTA(#REF!,"BAU Intensity S3",#REF!))
Name Col_Abs_Emissions: #REF!
Name Col_activity: #REF!
Name Col_activity_target: #REF!
Name Col_Company_Intensity: #REF!
Name Col_IEA_Conv: #REF!
Name Col_IEA_data: #REF!
Name Col_index: #REF!
Name Col_input_data: #REF!
Name Col_My: #REF!
Name Col_Sect_Intens: #REF!
Name CommentsRequired: #REF!
Name COUNTRY: #REF!
Name Date: OFFSET(#REF!,0,0, DCOUNTA(#REF!,"Date",#REF!))
Name dererere: #REF!
Name Distance: #REF!
Name DistanceType: #REF!
Name edgeCAT: #REF!
Name EmissionsFactor: #REF!
Name EmissionsFactorRegion: #REF!
Name EmissionsFactorType: #REF!
Name FUEL: #REF!
Name Fuels: #REF!
Name FUELSOURCE: #REF!
Name Land: #REF!
Name Lst_activity_corporate: #REF!
Name Lst_activity_fleet: #REF!
Name Lst_activity_mobile_network: #REF!
Name Lst_activity_total: #REF!
Name Lst_geos: #REF!
Name Lst_Scope_fleet: #REF!
Name Lst_scope1: #REF!
Name Lst_Scope1_2: #REF!
Name Lst_Scope1_2_3: #REF!
Name Lst_scope2: #REF!
Name Lst_Scope3: #REF!
Name Lst_SDA_mapping: #REF!
Name Lst_SDA_sectors: #REF!
Name Lst_sectors: #REF!
Name MinD: #REF!
Name MinF: #REF!
Name MinM: #REF!
Name noABN: #REF!
Name PJ_to_TWh: #REF!
Name Renewable_energy: #REF!
Name Row_Abs_Emissions: #REF!
Name Row_activity: #REF!
Name Row_activity_target: #REF!
Name Row_Company_Intensity: #REF!
Name Row_IEA_conv: #REF!
Name Row_IEA_data: #REF!
Name Row_index: #REF!
Name Row_input_data: #REF!
Name Row_My: #REF!
Name Row_Sect_Intens: #REF!

Sheet 2022 Estimado
G1: 2022 | H1: 2022
B2: VISTA 1: 2022 ESTIMADO | G2: Estimado | H2: Real
B3: Categorias segun impacto en toneladas | C3: 2021 | D3: 2022 estimado | E3: 2022 real | F3: Dif 2022 estimado | G3: kgCO2/pieza | H3: kgCO2/pieza | I3: Dif | K3: Explicación
A4: 1 | B4: Cat 1: Transporte aéreo | C4: 10258.876 | D4: 7308 | E4: 6789 | F4: =+E4-D4 -> -519 | G4: =+D4*1000/$D$23 -> 0.38250097 | H4: =+E4*1000/$D$23 -> 0.35533649 | I4: =+H4-G4 -> -0.027164478 | J4: =+H4/G4-1 -> -0.071018062 | K4: Modifiación en la metodología para las emisiones generadas por LATAM Airlines
A5: 2 | B5: Cat 1: Distribución | C5: 10099.541 | D5: 6681 | E5: 6937 | F5: =+E5-D5 -> 256 | G5: =+D5*1000/$D$23 -> 0.34968377 | H5: =+E5*1000/$D$23 -> 0.36308282 | I5: =+H5-G5 -> 0.013399049 | J5: =+H5/G5-1 -> 0.038317617 | K5: Cambio metodologico, se incluye distribución realizada por flota propia
A6: 3 | B6: Cat 1: Bienes y servicios - Compra de servicios e insumos | C6: 6615.4766 | D6: 5236 | E6: ='5. Bienes y servicios'!$O$35 -> 4140.204 | F6: =+E6-D6 -> -1095.796 | G6: =+D6*1000/$D$23 -> 0.27405242 | H6: =+E6*1000/$D$23 -> 0.21669842 | I6: =+H6-G6 -> -0.057353998 | J6: =+H6/G6-1 -> -0.20928112 | K6: Cambio metodologico, se recategorizan cuentas con equipo de finanzas
A7: 4 | B7: Cat 1: Transporte terrestre terceros - troncal | C7: 11041.988 | D7: 9671 | E7: 4359 | F7: =+E7-D7 -> -5312 | G7: =+D7*1000/$D$23 -> 0.50618047 | H7: =+E7*1000/$D$23 -> 0.22815021 | I7: =+H7-G7 -> -0.27803026 | J7: =+H7/G7-1 -> -0.54927102 | K7: Cambio metodologico,se incluye flota troncal propia y se calculan las emisiones con fuente de información distinta (reporte área de transporte)
A8: 5 | B8: Cat 7: Traslado de trabajadores | C8: 4424.3687 | D8: 3221 | E8: ='6. Traslado colaboradores'!$L$12 -> 3248 | F8: =+E8-D8 -> 27 | G8: =+D8*1000/$D$23 -> 0.16858725 | H8: =+E8*1000/$D$23 -> 0.17000043 | I8: =+H8-G8 -> 0.0014131809 | J8: =+H8/G8-1 -> 0.0083824899 | K8: Cambio metodologico, estimación realizada en basea emisión por colaborador 2021, 2022 en basea encuesta fe hábitos de transporte pa el año de calculo
A9: 6 | B9: Transporte propio | C9: 0 | D9: 0 | E9: 0 | F9: =+E9-D9 -> 0 | G9: =+D9*1000/$D$23 -> 0 | H9: =+E9*1000/$D$23 -> 0 | I9: =+H9-G9 -> 0 | J9: 0 | K9: Desaparece esta categoría y su impacto se refleja en las categorías de distribución y transporte troncal
A10: 7 | B10: Cat 1: Bienes y servicios - Insumos operacionales | C10: 2246.5409 | D10: 850 | E10: ='8. Insumos y Empaque'!$J$29 -> 789.24863 | F10: =+E10-D10 -> -60.751367 | G10: =+D10*1000/$D$23 -> 0.044489029 | H10: =+E10*1000/$D$23 -> 0.0413093 | I10: =+H10-G10 -> -0.0031797286 | J10: =+H10/G10-1 -> -0.071472197 | K10: Estimación en base a proyección de demanda, desviación en base a compra real de noviembre y diciembre
A11: 8 | B11: Cat 12: Fin de vida de productos vendidos | C11: 1534.3592 | D11: 528 | E11: ='8. Insumos y Empaque'!$K$28 -> 539.38539 | F11: =+E11-D11 -> 11.385391 | G11: =+D11*1000/$D$23 -> 0.027635538 | H11: =+E11*1000/$D$23 -> 0.02823145 | I11: =+H11-G11 -> 0.00059591174 | J11: =+H11/G11-1 -> 0.02156324 | K11: Estimación en base a proyección de demanda, desviación en base a compra real de noviembre y diciembre
A12: 9 | B12: Compra de electricidad | C12: 1591.1647 | D12: 1182 | E12: ='7. Energia Electrica'!$X$16 -> 1073.2022 | F12: =+E12-D12 -> -108.79783 | G12: =+D12*1000/$D$23 -> 0.06186592 | H12: =+E12*1000/$D$23 -> 0.056171438 | I12: =+H12-G12 -> -0.005694482 | J12: =+H12/G12-1 -> -0.092045539 | K12: Cambio de metodología, cálculo 2022 considera vigencia mensual de cada instalación y nuevos criterios de estimiación
A13: 10 | B13: Cat 2: Bienes de capital | C13: 1046.8453 | D13: 607 | E13: ='10. Bienes de capital'!$J$15 -> 114.62357 | F13: =+E13-D13 -> -492.37643 | G13: =+D13*1000/$D$23 -> 0.031770401 | H13: =+E13*1000/$D$23 -> 0.0059994015 | I13: =+H13-G13 -> -0.025770999 | J13: =+H13/G13-1 -> -0.81116381
A14: 11 | B14: Cat 1: Empaque | C14: 438.6238 | D14: 204 | E14: =+'8. Insumos y Empaque'!$J$28 -> 190.49121 | F14: =+E14-D14 -> -13.508789 | G14: =+D14*1000/$D$23 -> 0.010677367 | H14: =+E14*1000/$D$23 -> 0.0099703164 | I14: =+H14-G14 -> -0.0007070505 | J14: =+H14/G14-1 -> -0.066219556 | K14: Estimación en base a proyección de demanda, desviació en base a compra real de noviembre y diciembre
A15: 12 | B15: Cat 5: Residuos generados en las operaciones | C15: 544.40704 | D15: 297 | E15: =+'9. Residuos'!$N$33 -> 0 | F15: =+E15-D15 -> -297 | G15: =+D15*1000/$D$23 -> 0.01554499 | H15: =+E15*1000/$D$23 -> 0 | I15: =+H15-G15 -> -0.01554499 | J15: =+H15/G15-1 -> -1 | K15: Estimación en base a proyección de demanda, desviación en base a generación real de noviembre y diciembre (incorporación de factor de emisión de residuos peligrosos)
A16: 14 | B16: Cat 3: Otras Emisiones energía | C16: 302.51454 | D16: 97 | E16: ='7. Energia Electrica'!$Y$16 -> 270.57411 | F16: =+E16-D16 -> 173.57411 | G16: =+D16*1000/$D$23 -> 0.0050769833 | H16: =+E16*1000/$D$23 -> 0.014161858 | I16: =+H16-G16 -> 0.0090848751 | J16: =+H16/G16-1 -> 1.7894239 | K16: Cambio de metodología, cálculo 2022 considera vigencia mensual de cada instalación y nuevos criterios de estimiación
A17: 15 | B17: Cat 3: Otras Emisiones combustibles (Transporte propio) | C17: 0 | D17: 0 | E17: 0 | F17: =+E17-D17 -> 0 | G17: =+D17*1000/$D$23 -> 0 | H17: =+E17*1000/$D$23 -> 0 | I17: =+H17-G17 -> 0 | J17: 0 | K17: Desaparece esta categoría y su impacto se refleja en las categorías de distribución y transporte troncal
A18: 16 | B18: Cat 6: Viajes de negocio | C18: 107.5348 | D18: 22 | E18: ='12. Viajes de Negocio'!$G$37 -> 66.055034 | F18: =+E18-D18 -> 44.055034 | G18: =+D18*1000/$D$23 -> 0.0011514807 | H18: =+E18*1000/$D$23 -> 0.0034573227 | I18: =+H18-G18 -> 0.002305842 | J18: =+H18/G18-1 -> 2.0025015 | K18: Cambio metodologico, estimación en base a proyección de demanda, real calculado en base a registros internos
A19: 17 | B19: Emisiones fugitivas | C19: 27.706 | D19: 19 | E19: ='11. Refrigerantes'!$J$37 -> 263.2324 | F19: =+E19-D19 -> 244.2324 | G19: =+D19*1000/$D$23 -> 0.00099446064 | H19: =+E19*1000/$D$23 -> 0.013777593 | I19: =+H19-G19 -> 0.012783132 | J19: =+H19/G19-1 -> 12.854337 | K19: Cambio metodologico, estimación en base a proyección de demanda, real calculado en base a registros internos
A20: 18 | B20: Combustión- fuentes fijas | C20: 4.0750041 | D20: 0.078 | E20: =SUM('13. Combustible Fuentes fijas'!$K$37:$L$37) -> 11.96079 | F20: =+E20-D20 -> 11.88279 | G20: =+D20*1000/$D$23 -> 4.0825226e-06 | H20: =+E20*1000/$D$23 -> 0.00062602816 | I20: =+H20-G20 -> 0.00062194563 | J20: =+H20/G20-1 -> 152.34346 | K20: Se declara una mayor cantidad de generadores y calefactores en centros de distribución a nivel nacional
B21: TOTAL | C21: =+SUM(C4:C20) -> 50284.021 | D21: =+SUM(D4:D20) -> 35923.078 | E21: =+SUM(E4:E20) -> 28791.977 | F21: =+SUM(F4:F20) -> -7131.1007 | G21: =+SUM(G4:G20) -> 1.8802151 | H21: =+SUM(H4:H20) -> 1.5069731 | I21: =+H21-G21 -> -0.37324205 | J21: =+H21/G21-1 -> -0.19851029
J22: =E21/D21-1 -> -0.19851029
B23: Total de encomiendas y valijas | C23: 32943152 | D23: 19105834 | E23: 19105834
B24: kgCO2e/pieza | C24: =+C21*1000/C23 -> 1.5263877 | D24: =+D21*1000/D23 -> 1.8802151 | E24: =+E21*1000/E23 -> 1.5069731
C25: =+C24*0.96 -> 1.4653322 | D25: =E24/D24-1 -> -0.19851029 | E25: =+E24/C25-1 -> 0.028417389
E26: =+E7+E5+E4 -> 18085
E27: =+E26/E21 -> 0.62812636
D28: =E21-D21 -> -7131.1007
E29: =D24-E24 -> 0.37324205
C31: =C7+C9 -> 11041.988 | D31: =D7+D9 -> 9671
C32: =C7+C17 -> 11041.988 | D32: =D7+D17 -> 9671

Sheet Graficos
B3: Resumen de Huella de Carbono 2021 Chilexpres
G5: *Categorías en gris no aplican para la huella de carbono de Chilexpress | AH5: Comparación 2020/2021
C6: Alcance | D6: Emisiones de GEI (tCO2-e) | E6: % | G6: Alcance | H6: Categoría | I6: Emisiones de GEI (tCO2-e) | J6: %
C7: Alcance 1 | D7: =SUM(I7:I9) -> #REF! | E7: =D7/$D$10 -> #REF! | G7: Alcance 1 | H7: Combustión- fuentes fijas | I7: =+'13. Combustible Fuentes fijas'!K37 -> 11.393384 | J7: =+I7/SUM($I$7:$I$17) -> #REF! | M7: =+D7 -> #REF!
C8: Alcance 2 | D8: =I10 -> 1073.2022 | E8: =D8/$D$10 -> #REF! | H8: Combustión- fuentes móviles | I8: #REF! | J8: =+I8/SUM($I$7:$I$17) -> #REF! | M8: =+D8 -> 1073.2022 | AI8: Medio terrestre - Petróleo 2 (Diesel) | AJ8: 5107.4999 | AL8: Categoría | AM8: 2020 | AN8: 2021 | AP8: Categoría | AQ8: 2020 | AR8: 2021
C9: Alcance 3 | D9: =SUM(I11:I17) -> #REF! | E9: =D9/$D$10 -> #REF! | H9: Emisiones fugitivas | I9: =+'11. Refrigerantes'!J37 -> 263.2324 | J9: =+I9/SUM($I$7:$I$17) -> #REF! | K9: =+C7 -> Alcance 1 | L9: =+SUM(I7:I9)/I18 -> #REF! | M9: =+I11 -> #REF! | AI9: Medio terrestre - Gasolina | AJ9: 35.729913 | AL9: Combustión- fuentes fijas | AM9: =+AJ11 -> 1.6515112 | AN9: 166.35626 | AP9: Combustión- fuentes fijas | AQ9: =+AM9 -> 1.6515112 | AR9: =+I7 -> 11.393384
C10: TOTAL | D10: =SUM(D7:D9) -> #REF! | E10: =D10/$D$10 -> #REF! | G10: Alcance 2 | H10: Compra de electricidad | I10: =+'7. Energia Electrica'!X16 -> 1073.2022 | J10: =+I10/SUM($I$7:$I$17) -> #REF! | K10: =+C8 -> Alcance 2 | L10: =+I10/I18 -> #REF! | M10: =+I12 -> 0 | AI10: Medio terrestre - Gas natural | AJ10: 1.4988028 | AL10: Combustión- fuentes móviles | AM10: =+SUM(AJ8:AJ10) -> 5144.7286 | AN10: 4652.3625 | AP10: Combustión- fuentes móviles | AQ10: =+AM10 -> 5144.7286 | AR10: =+I8 -> #REF!
C11: Emisiones indirectas transporte aéreo | D11: =+I19 -> #REF! | G11: Alcance 3 | H11: Cat 1: Compra de bienes y servicios | I11: =+SUM('4. Transporte troncal'!J25:K25,#REF!)+#REF!+'8. Insumos y Empaque'!J27 -> #REF! | J11: =+I11/SUM($I$7:$I$17) -> #REF! | K11: =+H11 -> Cat 1: Compra de bienes y servicios | L11: =+I11/$I$18 -> #REF! | M11: =+I13 -> #REF! | AI11: Generador - Petróleo 2 (Diésel) | AJ11: 1.6515112 | AL11: Emisiones fugitivas | AM11: 0 | AN11: 27.706 | AP11: Emisiones fugitivas | AQ11: =+AM11 -> 0 | AR11: =+I9 -> 263.2324
H12: Cat 2: Bienes de capital | J12: =+I12/SUM($I$7:$I$17) -> #REF! | K12: =+H12 -> Cat 2: Bienes de capital | L12: =+I12/$I$18 -> #REF! | AI12: R410A - R410A | AJ12: 0 | AL12: Compra de electricidad | AM12: =+SUM(AJ14:AJ17) -> 1501.4519 | AN12: 1950.1519 | AP12: Compra de electricidad | AQ12: =+AM12 -> 1501.4519 | AR12: =+I10 -> 1073.2022
H13: Cat 3: Otras emisiones de energía y combustibles | I13: #REF! | J13: =+I13/SUM($I$7:$I$17) -> #REF! | K13: =+H13 -> Cat 3: Otras emisiones de energía y combustibles | L13: =+I13/$I$18 -> #REF! | M13: =+#REF! -> #REF! | AI13: EMISIONES INDIRECTAS POR ENERGÍA IMPORTADA | AL13: Cat 1: Compra de bienes y servicios | AM13: =+SUM(AJ19:AJ24) -> 16114.954 | AN13: 39159.103 | AP13: Cat 1: Empaque | AQ13: =+AI31 -> 1459.6755 | AR13: =+M94 -> 1972.983
H14: Cat 5: Residuos generados en las operaciones | I14: =+SUM('9. Residuos'!N25:O25) -> 317.55459 | J14: =+I14/SUM($I$7:$I$17) -> #REF! | K14: =+H14 -> Cat 5: Residuos generados en las operaciones | L14: =+I14/$I$18 -> #REF! | M14: =+I14 -> 317.55459 | AI14: Sistema Eléctrico de Los Lagos - Sistema Eléctrico de Los Lagos | AJ14: 0 | AL14: Cat 2: Bienes de capital | AM14: 0 | AN14: 1158.1922 | AP14: Cat 1: Transporte terrestre terceros | AQ14: =+AJ19 -> 7084.2782 | AR14: =+M87 -> 10100
H15: Cat 6: Viajes de negocio | J15: =+I15/SUM($I$7:$I$17) -> #REF! | K15: =+H15 -> Cat 6: Viajes de negocio | L15: =+I15/$I$18 -> #REF! | M15: =+I15 -> 0 | AI15: Sistema Eléctrico de Aysén - Sistema Eléctrico de Aysén | AJ15: 11.469488 | AL15: Cat 3: Emisiones energía y combustibles | AM15: 0 | AN15: 510.46359 | AP15: Cat 1: Transporte aéreo | AQ15: =+AJ21 -> 7571 | AR15: =+M90 -> #REF!
H16: Cat 7: Traslado de trabajadores | I16: =+'A3- Transporte colaboradores 2'!P7 -> 0 | J16: =+I16/SUM($I$7:$I$17) -> #REF! | K16: =+H16 -> Cat 7: Traslado de trabajadores | L16: =+I16/$I$18 -> #REF! | M16: =+I16 -> 0 | AI16: Sistema Eléctrico de Magallanes - Sistema Eléctrico de Magallanes | AJ16: 16.575856 | AL16: Cat 5: Residuos generados en las operaciones | AM16: 0 | AN16: 526.68069 | AP16: Cat 1: Bienes y servicios | AQ16: 0 | AR16: =+M91+H35 -> #REF!
H17: Cat 12: Fin de vida de productos vendidos | I17: =+'8. Insumos y Empaque'!K27 -> 539.33996 | J17: =+I17/SUM($I$7:$I$17) -> #REF! | K17: =+H17 -> Cat 12: Fin de vida de productos vendidos | L17: =+I17/$I$18 -> #REF! | M17: =+#REF! -> #REF! | AI17: Sistema Eléctrico Nacional - Sistema Eléctrico Nacional | AJ17: 1473.4066 | AL17: Cat 6: Viajes de negocio | AM17: 0 | AN17: 331.45871 | AP17: Cat 2: Bienes de capital | AQ17: 0 | AR17: =+M109 -> 0
H18: TOTAL | I18: =+SUM(I7:I17) -> #REF! | J18: =+I18/SUM($I$7:$I$17) -> #REF! | M18: =+#REF! -> #REF! | AI18: OTRAS EMISIONES INDIRECTAS DE GEI | AL18: Cat 7: Traslado de trabajadores | AM18: 0 | AN18: 2397.8629 | AP18: Cat 3: Emisiones energía y combustibles | AQ18: 0 | AR18: =+I13 -> #REF!
H19: Emisiones indirectas transporte aéreo | I19: =+#REF! -> #REF! | M19: =+#REF! -> #REF! | AI19: Transporte de carga 1 - Usar FE propio | AJ19: 7084.2782 | AL19: Cat 12: Fin de vida de productos vendidos | AM19: 0 | AN19: 1.7560997 | AP19: Cat 5: Residuos generados en las operaciones | AQ19: 0 | AR19: =+I14 -> 317.55459
M20: =+#REF! -> #REF! | AI20: Transporte de carga 2 - Usar FE propio | AJ20: 0 | AL20: Cat 14: Franquicias | AM20: 0 | AN20: 357.15594 | AP20: Cat 6: Viajes de negocio | AQ20: 0 | AR20: =+I15 -> 0
L21: =+SUM(L9:L18) -> #REF! | M21: =+I17 -> 539.33996 | AI21: Productos - aéreos - Aéreo - Avión trayecto doméstico (Chile continental) | AJ21: 7571 | AL21: TOTAL | AM21: =+SUM(AM9:AM20) -> 22762.786 | AN21: 51239.25 | AP21: Cat 7: Traslado de trabajadores | AQ21: 0 | AR21: =+I16 -> 0
M22: =+I23 -> 0 | AI22: Bienes adquiridos - Papel | AJ22: 611.93409 | AL22: Emisiones indirectas transporte aéreo | AN22: 9139.2274 | AP22: Cat 12: Fin de vida de productos vendidos | AQ22: 0 | AR22: =+I17 -> 539.33996
M23: =+#REF! -> #REF! | AI23: Bienes adquiridos - Plásticos: Plástico film promedio | AJ23: 681.98326 | AP23: Cat 14: Franquicias | AQ23: 0 | AR23: =+#REF! -> #REF!
M24: =+I25 -> 0 | AI24: Bienes adquiridos - Plásticos: Polietileno de baja densidad (LDPE) y LLDPE | AJ24: 165.75816 | AQ24: =+SUM(AQ9:AQ23) -> 22762.786 | AR24: =+SUM(AR9:AR23) -> #REF!
AI25: OTRAS EMISIONES DE GEI FUERA DEL INVENTARIO
AI26: Montreal - HCFC-22/R22 | AJ26: 0
AI31: =+SUM(AJ22:AJ24) -> 1459.6755
G32: Ítem | H32: Emisiones de GEI (tCO2-e) | AT32: =+(AR24-AQ24)/AQ24 -> #REF!
G33: Transporte terrestre terceros | H33: =+SUM('4. Transporte troncal'!J25:K25) -> 11041.76 | I33: =+H33/$H$38 -> #REF!
G34: Transporte aéreo | H34: =+#REF! -> #REF! | I34: =+H34/$H$38 -> #REF!
G35: Insumos | H35: =+#REF! -> #REF! | I35: =+H35/$H$38 -> #REF!
G36: Empaque | H36: =+'8. Insumos y Empaque'!J27 -> 979.73984 | I36: =+H36/$H$38 -> #REF!
G37: Servicios | H37: =+#REF! -> #REF! | I37: =+H37/$H$38 -> #REF!
G38: Total | H38: =+SUM(H33:H37) -> #REF!
N80: =+SUM(M87:M91) -> #REF!
M81: =+M87+M88+M89 -> 21141.515
L86: Ítem | M86: Emisiones de GEI (tCO2-e)
L87: Transporte terrestre terceros local | M87: 10100 | O87: =+M87/$M$97 -> #REF! | P87: =+SUM(O87:O90) -> #REF!
L88: Transporte terrestre terceros troncal | M88: 6108 | O88: =+M88/$M$97 -> #REF!
L89: Transporte terrestre propio | M89: 4933.5149 | O89: =+M89/$M$97 -> #REF! | T89: =+M89+T108 -> 5164.1706
L90: Transporte aéreo | M90: =+#REF! -> #REF! | O90: =+M90/$M$97 -> #REF!
L91: Servicios | M91: =+H37 -> #REF! | O91: =+M91/$M$97 -> #REF!
L92: Transporte colaboradores | M92: =+I16 -> 0 | O92: =+M92/$M$97 -> #REF!
L93: Insumos | M93: 3760.7436 | O93: =+M93/$M$97 -> #REF!
L94: Empaque y Fin de vida | M94: =+M105+T97 -> 1972.983 | O94: =+M94/$M$97 -> #REF! | T94: =+M95+T107 -> 2197.1647
L95: Electricidad | M95: 1894.1647 | O95: =+M95/$M$97 -> #REF!
L96: Otros | M96: 1730.5681 | O96: =+M96/$M$97 -> #REF! | R96: Insumos | T96: 3760.7436
L97: Total | M97: =+SUM(M87:M96) -> #REF! | R97: Fin de vida | T97: 1534.3592
R98: Fugitivas | T98: 28
R99: Otras emisiones de energia | T99: 533.65571
N100: =+SUM(O92,O95:O96) -> #REF! | R100: fijas | T100: 4
R101: Residuos generados en las operaciones | T101: 544.40704 | U101: =+SUM(T96:T101) -> 6405.1655
M102: =+M96-T97 -> 196.2089 | R102: Viajes de negocio | T102: 108 | U102: 6512
L103: =+M96+M109 -> 1730.5681 | U103: =+U102-U101 -> 106.83446
T104: =+M96-T99 -> 1196.9124
M105: 438.6238
S107: Energía | T107: 303
S108: Combustible | T108: =+T99-T107 -> 230.65571
L109: Bienes de Capital | M109: =+I12 -> 0

Sheet Categorías GHG
A1: Categoría de negocio | B1: Categorias GHG Protocol | H1: Factores de emisión | L1: Respaldo
B2: Alcance | C2: Categoria GHG Protocol | D2: Definición Protocolo GHG (OFICIAL) | E2: Incluida (SI/NO) | F2: Justificación de exclusión | H2: Fuente de información | I2: Unidad | J2: Licenciamiento | K2: link | L2: Responsable de respaldo | M2: Jefatura Responsable | N2: Tipo de respaldo | O2: Origen del dato
A3: =C3 -> Fuentes móviles (Transporte propio troncal) | B3: 1 | C3: Fuentes móviles (Transporte propio troncal) | D3: Emisiones de fuentes móviles propias o alquiladas (tanto en carretera y vehículos que no son de carretera) que se encuentran dentro de los límites del inventario de la empresa | E3: Sí | F3: incluida | H3: IPCC 2006 | I3: kg CO2e/l | J3: No | L3: Diego Maturana | M3: Andres Gruettner | N3: Facturas (COPEC-AGASNAR) Reporte de transporte troncal Plataformas de consumo (TCT, surtidor interno)
A4: =C4 -> Fuentes Fijas | B4: 1 | C4: Fuentes Fijas | D4: Fuentes que queman sólidos, líquidos o combustible gaseoso, generalmente para producir electricidad, generación de vapor o calor para fines de procesamiento de productos. | E4: Sí | F4: incluida | H4: IPCC 2006 | I4: kg CO2e/l | J4: No | L4: Felipe Villalobos | M4: Rodrigo Martinez | N4: Facturas
A5: =C5 -> Emisiones Fugitivas | B5: 1 | C5: Emisiones Fugitivas | D5: Las emisiones fugitivas de refrigeración y aire acondicionado resultan de fugas y cargas de servicio durante la vida útil del equipo y su eliminación. | E5: Sí | F5: incluida | H5: DEFRA | I5: kg CO2e/kg | J5: No | L5: Felipe Villalobos | M5: Rodrigo Martinez | N5: Facturas
A6: =C6 -> Compra de electricidad | B6: 2 | C6: Compra de electricidad | D6: Emisiones indirectas de la generación de energía comprada. | E6: Sí | F6: incluida | H6: Ministerio de energía | I6: kg CO2eq/kWh | J6: No | L6: Gustavo Guerrero / Ivana Alvear | M6: Paulina Sanchez / Sebastián Blamey | N6: Facturas Distribuidoras (CGE-CHILQUINTA-FRONTEL-SAESA-LUZ OSORNO-EDELAYSEN-EDELMAG-ENEL-EEPA-AES) Metodología de estimacion de acuerdo a criterios utilizados Certificado ERNC
A7: =C7 -> Cat.1 Distribución | B7: 3 | C7: Cat.1 Distribución | D7: Emisiones de la producción de productos comprados o adquiridos por la empresa informante en el año de informe. | E7: Sí | F7: incluida | H7: IPCC 2006 | I7: kg CO2e/l | J7: No | L7: Diego Maturana | M7: Andres Gruettner | N7: Datos medidos con instrumentos Drivin SIGO GPS Planilla
A8: =C8 -> Cat.1 Transporte Troncal - solo externo | B8: 3 | C8: Cat.1 Transporte Troncal - solo externo | E8: Sí | F8: incluida | H8: IPCC 2006 | I8: kg CO2e/l | J8: No | L8: Diego Maturana | M8: Andres Gruettner | N8: Reporte de transporte troncal
A9: =C9 -> Cat.1 Transporte Aéreo | B9: 3 | C9: Cat.1 Transporte Aéreo | E9: Sí | F9: incluida | H9: DEFRA 2021 | I9: kg CO2eq/tkm | J9: No | L9: Diego Maturana | M9: Andres Gruettner | N9: Facturas (LATAM-SKY) Calculo Vuela Neutral Latam
A10: =C10 -> Cat.1 Bienes y servicios - Compra de servicios | B10: 3 | C10: Cat.1 Bienes y servicios - Compra de servicios | E10: Sí | F10: incluida | H10: exiobase | I10: kg CO2e/USD | J10: Sí | L10: Oswaldo Caldera | M10: Germán Yañez | N10: Factura según proveedor de servicio
A11: =C11 -> Cat.1 Bienes y servicios - Insumos Operacionales | B11: 3 | C11: Cat.1 Bienes y servicios - Insumos Operacionales | E11: Sí | F11: incluida | H11: ecoinvent v3.6 | I11: kg CO2e/kg | J11: Sí | L11: Cristián Vergaray | M11: Paulina Sanchez | N11: Factura (pendiente proveedores) Base recepción de insumos)
A12: =C12 -> Cat.1 Bienes y servicios - Compra de empaques | B12: 3 | C12: Cat.1 Bienes y servicios - Compra de empaques | E12: Sí | F12: incluida | H12: ecoinvent v3.6 | I12: kg CO2e/USD | J12: Sí | L12: Cristián Vergaray | M12: Paulina Sanchez | N12: Factura (pendiente proveedores) Certificado material reciclado Base recepción de empaques
A13: =C13 -> Cat.2 Compra de bienes de capital | B13: 3 | C13: Cat.2 Compra de bienes de capital | D13: Emisiones de la producción de bienes de capital comprados o adquiridos por la empresa informante en el año de informe. | E13: Sí | F13: incluida | H13: exiobase | I13: kg CO2e/USD | J13: Sí | L13: Manuel Reyes | M13: Vanessa Luna | N13: Factura según proveedor de activo adquirido
A14: =C14 -> Cat.3 Otras emisiones de energía | B14: 3 | C14: Cat.3 Otras emisiones de energía | D14: Emisiones relacionadas con la producción de combustibles y energía comprado y consumido que no están incluidos en el alcance 2 | E14: Sí | F14: incluida | H14: MMA | I14: kg CO2eq/kWh | J14: No | L14: Gustavo Guerrero / Ivana Alvear | M14: Paulina Sanchez / Sebastián Blamey | N14: Facturas Distribuidoras (CGE-CHILQUINTA-FRONTEL-SAESA-LUZ OSORNO-EDELAYSEN-EDELMAG-ENEL-EEPA-AES) Metodología de estimacion de acuerdo a criterios utilizados Certificado ERNC
A15: =C15 -> Cat.3 Otras emisiones de combustible | B15: 3 | C15: Cat.3 Otras emisiones de combustible | E15: Sí | F15: incluida | H15: DEFRA | I15: kg CO2e/l | J15: No | L15: Diego Maturana | M15: Andres Gruettner | N15: Datos medidos con instrumentos Reporte de transporte troncal Plataformas de consumo (TCT, surtidor interno)
A16: =C16 -> Cat 4: Transporte aguas arriba | B16: 3 | C16: Cat 4: Transporte aguas arriba | D16: Emisiones del transporte y distribución de los productos adquiridos | E16: No | F16: Menos del 1% de contribución, por lo tanto, por falta de mejor información, esta categoría quedó fuera excluida. Corresponde al transporte proveedores de insumos hacia nosotros. | H16: excluida | I16: excluida | J16: excluida | L16: No aplica | M16: No aplica | N16: N/A
A17: =C17 -> Cat 5: Residuos generados en las operaciones | B17: 3 | C17: Cat 5: Residuos generados en las operaciones | D17: Emisiones de la eliminación y el tratamiento de residuos por parte de terceros generados en las operaciones propias o controladas por la empresa que informa | E17: Sí | F17: incluida | H17: Ecoinvent v3.6 | I17: kg CO2/kg | J17: Sí | L17: Claudia Escarate | M17: Constanza Bazan | N17: Estado de Pago Volta Certificado de disposición final Boleta con peso de valorización Metodología de estimación
A18: =C18 -> Cat 6: Viajes de negocio | B18: 3 | C18: Cat 6: Viajes de negocio | D18: Emisiones del transporte de empleados para actividades relacionadas con el negocio | E18: Sí | F18: incluida | H18: exiobase | I18: kg CO2eq/USD | J18: Sí | L18: Eduardo Estay | M18: Paulina Sanchez | N18: Factura (LATAM-SKY-HOSPEDAJE)
A19: =C19 -> Cat 7: Traslado de trabajadores | B19: 3 | C19: Cat 7: Traslado de trabajadores | D19: Emisiones del transporte de los empleados entre sus hogares y sus lugares de trabajo. | E19: Sí | F19: incluida | H19: ecoinvent v3.6 | I19: kg CO2e/personkm | J19: Sí | L19: Danilo Muñoz / Carlos Escarate | M19: Donna Barrera / Solange Mc Guire | N19: Encuesta de hábitos de transpore Documento Metodología de extrapolación
A20: =C20 -> Cat 8: Bienes arrendados aguas arriba | B20: 3 | C20: Cat 8: Bienes arrendados aguas arriba | D20: Emisiones provenientes de la operación de activos que son arrendados por la empresa informante | E20: No | F20: Los consumos por la operación de bienes arrendados fueron consolidados en el alcance 2 (consumo electrico). No se incluye los bienes arrendados como tal, porque no es una categoría obligatoria dentro del protocolo y la información disponible tiene alta incertidumbre. | H20: excluida | I20: excluida | J20: excluida | L20: No aplica | M20: No aplica | N20: N/A
A21: =C21 -> Cat 9: Transporte aguas abajo | B21: 3 | C21: Cat 9: Transporte aguas abajo | D21: Emisiones del transporte y distribución de productos vendidos en vehículos e instalaciones que no son propiedad ni están bajo el control de la empresa informante. | E21: No | F21: Transporte hacia clientes esta categoría no aplica, ya que corresponde al transporte hacia el consumidor cuando no lo paga la empresa, y en nuestro caso está incluido en alcance 1 y 3. | H21: excluida | I21: excluida | J21: excluida | L21: No aplica | M21: No aplica | N21: N/A
A22: =C22 -> Cat 10: Procesamiento productos vendidos: | B22: 3 | C22: Cat 10: Procesamiento productos vendidos: | D22: Emisiones del procesamiento de productos vendidospor terceros | E22: No | F22: Los productos que vendemos (embalajes) están considerados en compras de embalajes y fin de vida. | H22: excluida | I22: excluida | J22: excluida | L22: No aplica | M22: No aplica | N22: N/A
A23: =C23 -> Cat 11: Uso de productos vendidos: | B23: 3 | C23: Cat 11: Uso de productos vendidos: | D23: Emisiones por el uso de bienes y servicios vendidos por el compañía. | E23: No | F23: Los productos que vendemos (embalajes) están considerados en compras de embalajes y fin de vida. | H23: excluida | I23: excluida | J23: excluida | L23: No aplica | M23: No aplica | N23: N/A
A24: =C24 -> Cat 12: Fin de vida empaques | B24: 3 | C24: Cat 12: Fin de vida empaques | D24: Emisiones de la eliminación de residuos y el tratamiento de productos vendido por la empresa y su fin de vida | E24: Sí | F24: incluida | H24: ecoinvent v3.6 | I24: kg CO2e/kg | J24: Sí | L24: Cristián Vergaray | M24: Paulina Sanchez | N24: Factura (pendiente proveedores) Certificado material reciclado Base recepción de empaques
A25: =C25 -> Cat 13: Activos arrendados aguas abajo | B25: 3 | C25: Cat 13: Activos arrendados aguas abajo | D25: Emisiones provenientes de la operación de los activos que son propiedad de la empresa informante | E25: No | F25: No se incluyó en la medición de huella porque no es una categoría obligatoria dentro del protocolo y la información disponible tiene alta incertidumbre. | H25: excluida | I25: excluida | J25: excluida | L25: No aplica | M25: No aplica | N25: N/A
A26: =C26 -> Cat 14: Franquicias | B26: 3 | C26: Cat 14: Franquicias | D26: Emisiones de la operación de franquicias no incluidas en el alcance 1 o alcance 2 | E26: No | F26: Dada la naturaleza operacional de las franquicias en Chilexpress y el control sobre ellas, el impacto de dichas unidades se encuentra contabilizados en el alcance 2 y 3. Esto pues dado que el inmueble es de chilexpress, se considera como parte del control operacional. | H26: excluida | I26: excluida | J26: excluida | L26: No aplica | M26: No aplica | N26: N/A
A27: =C27 -> Cat 15: Inversiones: | B27: 3 | C27: Cat 15: Inversiones: | D27: Emisiones asociadas con la empresa que reporta inversiones | E27: No | F27: Corresponde a inversiones en el mercado bursátil. | H27: excluida | I27: excluida | J27: excluida | L27: No aplica | M27: No aplica | N27: N/A

Sheet Indice
A1: Criticidad de Categorías | B1: N° Cat | C1: Categorias de Negocio Huella de Carbono 2022 | D1: Area que gestiona de la categoria | E1: Area que validación de la información | F1: Presentación del área
A2: ALTA | B2: 1 | C2: Demanda | D2: Mejora Continua | E2: Sost. Operacional
B3: =B2+1 -> 2 | C3: Transporte Aéreo | D3: Transporte | E3: Ing. Operacional
B4: =B3+1 -> 3 | C4: Distribución (UM, PM, TL) (Propio y Externo) | D4: Distribución | E4: Ing. Operacional
B5: =B4+1 -> 4 | C5: Transporte Troncal (Propio y Externo) | D5: Transporte | E5: Ing. Operacional
B6: =B5+1 -> 5 | C6: Residuos | D6: Mejora Continua | E6: Seguridad y Salud Operacional / Sostenibilidad Operacional | F6: Resultados Huella CO2 Residuos
A7: MEDIA | B7: =B6+1 -> 6 | C7: Compra de bienes y servicios | D7: Finanzas | E7: Finanzas
B8: =B7+1 -> 7 | C8: Traslado de colaboradores | D8: Personas | E8: Sost. Operacional
B9: =B8+1 -> 8 | C9: Insumos Operacionales Compra de empaques y fin de vida de productos vendidos | D9: Compras Tácticas | E9: Administración / Mejora Continua
B10: =B9+1 -> 9 | C10: Energía Electrica | D10: Inmobiliaria | E10: Administración/ Mejora Continua | F10: https://docs.google.com/presentation/d/1cp8dckgiY_StKqz7z6E9pG6-RV9b4GgTvjg2w5SmnoY/edit#slide=id.g181f8695f58_0_578
A11: BAJA | B11: =B10+1 -> 10 | C11: Bienes de Capital | D11: Finanzas | E11: Finanzas
B12: =B11+1 -> 11 | C12: Viajes de negocio | D12: Operaciones | E12: Finanzas
B13: =B12+1 -> 12 | C13: Fuentes Fijas | D13: Inmobiliaria | E13: Inmobiliaria
B14: =B13+1 -> 13 | C14: Emisiones Fugitivas | D14: Inmobiliaria | E14: Inmobiliaria

Sheet Ppt
B2: Por categoría de negocio | C2: % | D2: TONELADAS CO2 | H2: ACCIONES REALIZADAS 2022
C3: 2022 | D3: 2021 | E3: 2022 | F3: Dif | G3: Dif % | H3: Acción | I3: Descripción | J3: Impacto | K3: Impacto %
B4: Transporte distribución | C4: 0.23 | D4: 10100 | E4: 6945 | F4: -3155 | G4: -0.31 | H4: Optimización de Red | I4: Optimizaciones de flota de vehículos primera y última milla según las variaciones de demanda. Reducción del 27% de kilómetros recorridos. | J4: -2.700 tCO2e
H5: Electromovilidad | I5: Incorporación de 94 vehículos eléctricos en flota primera y última milla RM. Incorporación gradual de 30 (septiembre) a 94 vehículos eléctricos (diciembre) . | J5: -100 tCO2e
B6: Transporte aéreo | C6: 0.23 | D6: 10259 | E6: 6789 | F6: -3470 | G6: -0.34
B7: Transporte troncal | C7: 0.15 | D7: 11042 | E7: 4359 | F7: -6683 | G7: -0.61 | H7: Optimización de malla troncal | I7: Optimización de rutas actuales adaptadas a demanda requerida y servicio. Reducción del 28% de kilómetros recorridos. | J7: -1.300 tCO2e
B8: Compra de servicios | C8: 0.14 | D8: 6615 | E8: 4140 | F8: -2475 | G8: -0.37
B9: Traslado de trabajadores | C9: 0.11 | D9: 4424 | E9: 3248 | F9: -1176 | G9: -0.27
B10: Energía Eléctrica | C10: 0.04 | D10: 1894 | E10: 1344 | F10: -550 | G10: -0.29 | H10: Uso de ERNC | I10: Utilización de ERNC para el CD ENEA I y IV, contrato cliente libre con AES Andes. Aumento de consumo ERNC respecto del total +1% lo que presenta a 1,42 GWh. 29% de uso de ERNC sobre el total de energía consumida | J10: -425 tCO2e
H11: Implementación Luces LED | I11: Menor consumo energético por avance en plan de implementación de luces LED. Disminución del 11% (580.438 kWh) del consumo eléctrico en las instalaciones operacionales (CD,CR,CO,OC,FR). Disminución de hasta un 20% de consumo en luminarias por unidad. Hasta el momento, 21 CDs han sido mejorados. Avance de plan de un 18% a un 77%. | J11: -200 tCO2e
B12: Insumos operacionales y embalajes | C12: 0.05 | D12: 4220 | E12: 1519 | F12: -2700 | G12: -0.64 | H12: Negociación de tarifas y menor compras de insumos y materiales | I12: Disminución de compras realizadas de insumos y embalajes. -46% de toneladas de material | J12: -1.941 tCO2e
H13: Embalajes bajos en emisiones | I13: Certificación de cajas de embalaje con un 99,76% de materiales de origen reciclado. -150 tCO2e evitadas 98% de nuestro embalaje es fabricado con 100% fibras recicladas. | J13: -150 tCO2e
B14: Residuos | C14: 0.01 | D14: 544 | E14: 318 | F14: -226 | G14: -0.42 | H14: Mejora en gestión de Puntos Limpios y Mini Puntos Limpios | I14: Mejora en la gestión de 19 puntos limpios y mini puntos limpios para la gestión de reciclaje de residuos reciclables operacionales y domiciliarios en 23 unidades operacionales a nivel nacional (CD/CR/CO/CORP). | J14: -60 tCO2e +9% Tasa de Valorización de 46% a 55%.
H15: Optimización Film y Bolsas contenedoras | I15: Reducción y control del consumo de Film (Enea) y Bolsas Contenedoras (OC nivel nacional)
B16: Otras categorías | C16: 0.04 | D16: 1186 | E16: 1235 | F16: 49 | G16: 0.04
B17: TOTAL | C17: 1 | D17: 50284 | E17: 29897 | F17: -20387 | G17: -0.41

Sheet 2022 Resumen
C2: VISTA 1
C3: Por año | D3: DISTRIBUCIÓN % | G3: TONELADAS CO2 | O3: KGCO2/pieza
D4: 2021 | E4: 2022 | F4: DIF | G4: 2021 | H4: 2022 | I4: DIF | J4: % DIF | K4: EXPLICACION | O4: 2021 | P4: 2022 | Q4: DIF | R4: % DIF | S4: EXPLICACION
D5: 1 | E5: 1 | F5: 0 | G5: =SUM(G37:G51) -> 50284.021 | H5: =SUM(H37:H51) -> 29928.615 | I5: =H5-G5 -> -20355.405 | J5: =I5/G5 -> -0.40480863 | O5: =SUM(O37:O51) -> 1.5263877 | P5: =SUM(P37:P51) -> 1.5664647 | Q5: =P5-O5 -> 0.04007708 | R5: =Q5/O5 -> 0.026256161
C7: Total de documentos, encomiendas y valijas | O7: ='1. Demanda'!N7 -> 32943152 | P7: ='1. Demanda'!N4 -> 19105834 | Q7: =+P7-O7 -> -13837318 | R7: =Q7/O7 -> -0.42003625
C10: VISTA 2
C11: Por categoria de negocio macro-agrupada | D11: DISTRIBUCIÓN % | G11: TONELADAS CO2 | O11: KGCO2/pieza
D12: 2021 | E12: 2022 | F12: DIF | G12: 2021 | H12: 2022 | I12: DIF | J12: % DIF | K12: EXPLICACION | O12: 2021 | P12: 2022 | Q12: DIF | R12: % DIF | S12: EXPLICACION
C13: Transporte | D13: =SUM(D22:D24) -> 0.62445487 | E13: =SUM(E22:E24) -> 0.6045405 | F13: =E13-D13 -> -0.019914367 | G13: =SUM(G22:G24) -> 31400.404 | H13: =SUM(H22:H24) -> 18093.06 | I13: =H13-G13 -> -13307.344 | J13: =I13/G13 -> -0.42379531 | O13: =SUM(O22:O24) -> 0.9531694 | P13: =SUM(P22:P24) -> 0.94699138 | Q13: =P13-O13 -> -0.0061780146 | R13: =Q13/O13 -> -0.0064815495
C14: Compra de servicios, insumos y energia electrica | D14: =D25+D28+D27 -> 0.2531479 | E14: =E25+E28+E27 -> 0.23399364 | F14: =E14-D14 -> -0.019154259 | G14: =G25+G28+G27 -> 12729.417 | H14: =H25+H28+H27 -> 7003.1056 | I14: =H14-G14 -> -5726.3112 | J14: =I14/G14 -> -0.44984867 | O14: =O25+O28+O27 -> 0.38640555 | P14: =P25+P28+P27 -> 0.36654278 | Q14: =P14-O14 -> -0.019862768 | R14: =Q14/O14 -> -0.051403941
C15: Otras categorias | D15: =D26+D29+D30 -> 0.12239724 | E15: =E26+E29+E30 -> 0.16146586 | F15: =E15-D15 -> 0.039068627 | G15: =G26+G29+G30 -> 6154.6845 | H15: =H26+H29+H30 -> 4832.4497 | I15: =H15-G15 -> -1322.2348 | J15: =I15/G15 -> -0.21483389 | O15: =O26+O29+O30 -> 0.18682743 | P15: =P26+P29+P30 -> 0.25293058 | Q15: =P15-O15 -> 0.066103149 | R15: =Q15/O15 -> 0.35381929
C16: TOTAL | D16: =D15+D14+D13 -> 1 | E16: =E15+E14+E13 -> 1 | F16: =E16-D16 -> 0 | G16: =G15+G14+G13 -> 50284.506 | H16: =H15+H14+H13 -> 29928.615 | I16: =H16-G16 -> -20355.89 | J16: =I16/G16 -> -0.40481436 | O16: =O15+O14+O13 -> 1.5264024 | P16: =P15+P14+P13 -> 1.5664647 | Q16: =Q15+Q14+Q13 -> 0.040062367 | R16: =Q16/O16 -> 0.026246268
C19: VISTA 3 (input) | AF19: GRAFICOS
C20: Por categoria de negocio agrupada | D20: DISTRIBUCIÓN % | G20: TONELADAS CO2 | O20: KGCO2/pieza | AF20: Categorías según impacto en toneladas | AG20: 2022 | AH20: kgCO27pieza 2022 | AI20: 2021 | AJ20: kgCO27pieza 2021 | AK20: tCO2 2022 | AL20: tCO2 2021
D21: 2021 | E21: 2022 | F21: DIF | G21: 2021 | H21: 2022 | I21: DIF | J21: % DIF | K21: EXPLICACION | L21: x ACCION | M21: x METOD | N21: x F.EXT. | O21: 2021 | P21: 2022 | Q21: DIF | R21: % DIF | S21: EXPLICACION | AF21: Transporte distribución | AG21: =H22/$H$31 -> 0.23204498 | AH21: =H22* 1000/$P$7 -> 0.36349028 | AI21: =D22 -> 0.20084797 | AJ21: =G22*1000/$O$7 -> 0.30657482 | AK21: =H22 -> 6944.7849 | AL21: =G22 -> 10099.541
C22: Transporte distribución | D22: =G22/$G$31 -> 0.20084797 | E22: =H22/$H$31 -> 0.23204498 | F22: =E22-D22 -> 0.031197009 | G22: =G37 -> 10099.541 | H22: =H37 -> 6944.7849 | I22: =-G22+H22 -> -3154.7559 | J22: =I22/G22 -> -0.31236627 | K22: 1) Optimizacion de capacidad de flota por menor demanda, sin embargo no es proporcional a la baja de demanda (-42%) por concentración de piezas (-27%) 2) Mejora metodologica en incorporación de motos y limpieza de datos (-3%) 3) Incorporacion operacion de vehiculos elecltricos (-100 ton, -1%) | L22: =I22-M22 -> -3060.1132 | M22: =0.03*I22 -> -94.642677 | O22: =G22*1000/$O$7 -> 0.30657482 | P22: =H22*1000/$P$7 -> 0.36349028 | Q22: =-O22+P22 -> 0.056915459 | R22: =Q22/O22 -> 0.18564949 | S22: 1) Aumento de km/pieza por concentración de piezas en +26% 2) Mejora en rendimiento al incorporar motos, bicicletas y peatones en la caracterización de flota (-7%). | AF22: Transporte aéreo | AG22: =H23/$H$31 -> 0.22683976 | AH22: =H23* 1000/$P$7 -> 0.35533649 | AI22: =D23 -> 0.20401664 | AJ22: =G23*1000/$O$7 -> 0.31141148 | AK22: =H23 -> 6789 | AL22: =G23 -> 10258.876
C23: Transporte aéreo | D23: =G23/$G$31 -> 0.20401664 | E23: =H23/$H$31 -> 0.22683976 | F23: =E23-D23 -> 0.022823122 | G23: =G38 -> 10258.876 | H23: =H38 -> 6789 | I23: =-G23+H23 -> -3469.8759 | J23: =I23/G23 -> -0.33823159 | K23: 1) Disminución tkm no proporcional a la baja de demanda (-24%) 2) Mejora en el factor de emisión Latam (-10%) (-984 tonCO2) | L23: =I23-M23 -> -2485.8759 | M23: -984 | O23: =G23*1000/$O$7 -> 0.31141148 | P23: =H23*1000/$P$7 -> 0.35533649 | Q23: =-O23+P23 -> 0.043925006 | R23: =Q23/O23 -> 0.14105133 | S23: Se mantiene base por concentración de entregas y menor emisión por cambio en metodología | AF23: Transporte troncal | AG23: =H24/$H$31 -> 0.14565576 | AH23: =H24* 1000/$P$7 -> 0.22816461 | AI23: =D24 -> 0.21959026 | AJ23: =G24*1000/$O$7 -> 0.33518309 | AK23: =H24 -> 4359.2752 | AL23: =G24 -> 11041.988
C24: Transporte troncal | D24: =G24/$G$31 -> 0.21959026 | E24: =H24/$H$31 -> 0.14565576 | F24: =E24-D24 -> -0.073934498 | G24: =G39 -> 11041.988 | H24: =H39 -> 4359.2752 | I24: =-G24+H24 -> -6682.7124 | J24: =I24/G24 -> -0.60520919 | K24: 1) -50% por menor demanda (no proporcional a la baja -42%), modificación/optimización malla troncal y cambio de metodologia de medición (no es posible determinar los impactos de forma independiente) 2) -11% mayor precisión en el dato de rendimiento. | L24: =I24-M24 -> -5947.614 | M24: =0.11*I24 -> -735.09836 | O24: =G24*1000/$O$7 -> 0.33518309 | P24: =H24*1000/$P$7 -> 0.22816461 | Q24: =-O24+P24 -> -0.10701848 | R24: =Q24/O24 -> -0.31928364 | S24: Aumento 15% km/pieza pero compensa con mejor rendimiento y por cambio metodologia | AF24: Compra de servicios | AG24: =H25/$H$31 -> 0.13833597 | AH24: =H25* 1000/$P$7 -> 0.21669842 | AI24: =D25 -> 0.13156094 | AJ24: =G25*1000/$O$7 -> 0.20081493 | AK24: =H25 -> 4140.204 | AL24: =G25 -> 6615.4766
C25: Compra de servicios | D25: =G25/$G$31 -> 0.13156094 | E25: =H25/$H$31 -> 0.13833597 | F25: =E25-D25 -> 0.006775034 | G25: =G40 -> 6615.4766 | H25: =H40 -> 4140.204 | I25: =-G25+H25 -> -2475.2726 | J25: =I25/G25 -> -0.37416391 | K25: 1) Disminución del gasto en mayor proporción que el gasto en pesos por aumento del tipo de cambio(-13%) 2) Menores gastos realizados en pesos (-8%) 3) Reubicación de gastos incluidos en otras categorias (-16%) (ej. transporte y arreglos) | L25: =0.08*I25 -> -198.02181 | M25: - | N25: =I25-L25 -> -2277.2508 | O25: =G25*1000/$O$7 -> 0.20081493 | P25: =H25*1000/$P$7 -> 0.21669842 | Q25: =-O25+P25 -> 0.015883494 | R25: =Q25/O25 -> 0.079095188 | S25: Reducción de emisiones totales (-37%) no proporcional a la baja de demanda (-42%) | AF25: Traslado de trabajadores | AG25: =H26/$H$31 -> 0.1085249 | AH25: =H26* 1000/$P$7 -> 0.17000043 | AI25: =D26 -> 0.087986719 | AJ25: =G26*1000/$O$7 -> 0.13430314 | AK25: =H26 -> 3248 | AL25: =G26 -> 4424.3687
C26: Traslado de colaboradores | D26: =G26/$G$31 -> 0.087986719 | E26: =H26/$H$31 -> 0.1085249 | F26: =E26-D26 -> 0.020538182 | G26: =G41 -> 4424.3687 | H26: =H41 -> 3248 | I26: =-G26+H26 -> -1176.3687 | J26: =I26/G26 -> -0.26588396 | K26: 1) Menor base de colaboradores (-20%) 2) Menor distancia recorrida por dia (declarada) por colaborador (-7%) | L26: =I26 -> -1176.3687 | O26: =G26*1000/$O$7 -> 0.13430314 | P26: =H26*1000/$P$7 -> 0.17000043 | Q26: =-O26+P26 -> 0.035697293 | R26: =Q26/O26 -> 0.26579642 | S26: Reducción de emisiones totales (-27%) no proporcinal a la baja de demanda (-42%) | AF26: Energía Electrica | AG26: =H27/$H$31 -> 0.04489938 | AH26: =H27* 1000/$P$7 -> 0.070333297 | AI26: =D27 -> 0.037659299 | AJ26: =G27*1000/$O$7 -> 0.057483244 | AK26: =H27 -> 1343.7763 | AL26: =G27 -> 1893.6792
C27: Energía Electrica | D27: =G27/$G$31 -> 0.037659299 | E27: =H27/$H$31 -> 0.04489938 | F27: =E27-D27 -> 0.0072400812 | G27: =G42+G43 -> 1893.6792 | H27: =H42+H43 -> 1343.7763 | I27: =-G27+H27 -> -549.90295 | J27: =I27/G27 -> -0.29038865 | K27: 1) Mejora de factor de emisión de matriz energetica nacional de un -23% (-18%) 2) Menor consumo electrico por instalaciones LED y menor cantidad de unidades (-11%) 3) Aumento de consumo ERNC respceto del total (+1%) | L27: =I27-N27 -> -450.92042 | N27: =0.18*I27 -> -98.982531 | O27: =G27*1000/$O$7 -> 0.057483244 | P27: =H27*1000/$P$7 -> 0.070333297 | Q27: =-O27+P27 -> 0.012850053 | R27: =Q27/O27 -> 0.22354432 | S27: Reduccion de emisiones totales (-29%) no es proporcional a la baja de demanda (-42%) por consumo fijo en instalaciones. Intensidad energetica por pieza aumenta +54%, sin embargo la mejora del factor de emisión contribuye a reducir -32% | AF27: Insumos operacionales y embalajes | AG27: =H28/$H$31 -> 0.050758287 | AH27: =H28* 1000/$P$7 -> 0.079511066 | AI27: =D28 -> 0.083927661 | AJ27: =G28*1000/$O$7 -> 0.12810738 | AK27: =H28 -> 1519.1252 | AL27: =G28 -> 4220.2609
C28: Insumos operacionales y embalajes | D28: =G28/$G$31 -> 0.083927661 | E28: =H28/$H$31 -> 0.050758287 | F28: =E28-D28 -> -0.033169375 | G28: ='8. Insumos y Empaque'!L62 -> 4220.2609 | H28: =H45+H46+H44 -> 1519.1252 | I28: =-G28+H28 -> -2701.1357 | J28: =I28/G28 -> -0.64003997 | K28: 1) Menor consumo de toneladas de material y optimización de compras de insumos y empaques (-46%) 2) Menor factor de emisión segun proporcion de uso de materiales por corrección (-18%) | L28: =I28-M28 -> -2214.9313 | M28: =0.18*I28 -> -486.20443 | O28: =G28*1000/$O$7 -> 0.12810738 | P28: =H28*1000/$P$7 -> 0.079511066 | Q28: =-O28+P28 -> -0.048596315 | R28: =Q28/O28 -> -0.37934048 | S28: 1) Menor consumo de material por pieza (-7%) 2) Menor factor de emision ponderado (-30%) | AF28: Residuos | AG28: =H29/$H$31 -> 0.0106104 | AH28: =H29* 1000/$P$7 -> 0.016620818 | AI28: =D29 -> 0.010818442 | AJ28: =G29*1000/$O$7 -> 0.016513295 | AK28: =H29 -> 317.55459 | AL28: =G29 -> 544
C29: Residuos | D29: =G29/$G$31 -> 0.010818442 | E29: =H29/$H$31 -> 0.0106104 | F29: =E29-D29 -> -0.00020804157 | G29: 544 | H29: =H47 -> 317.55459 | I29: =-G29+H29 -> -226.44541 | J29: =I29/G29 -> -0.41625995 | K29: 1) Menor compra/uso de materiales por menor demanda, mejora en tasa de valorización (recupero de residuos regiones y gestión de punto limpio Enea) (-34%) 2) Menor cantidad de colaboradores (-12%) 3) Aumento del factor de emisión ponderado por incorporación de tratamiento de residuos peligrosos (+2%) | L29: =I29-N29 -> -199.27196 | N29: =0.12*I29 -> -27.173449 | O29: =G29*1000/$O$7 -> 0.016513295 | P29: =H29*1000/$P$7 -> 0.016620818 | Q29: =-O29+P29 -> 0.0001075226 | R29: =Q29/O29 -> 0.0065112748 | S29: Disminucion absoluta de emisiones (-41,6%) no proporcional a disminución de demanda (-42%) | AF29: Otras categorías | AG29: =H30/$H$31 -> 0.042330561 | AH29: =H30* 1000/$P$7 -> 0.066309332 | AI29: =D30 -> 0.023592075 | AJ29: =G29*1000/$O$7 -> 0.016513295 | AK29: =H30 -> 1266.8951 | AL29: =G30 -> 1186.3158
C30: Otras categorías | D30: =G30/$G$31 -> 0.023592075 | E30: =H30/$H$31 -> 0.042330561 | F30: =E30-D30 -> 0.018738487 | G30: 1186.3158 | H30: =H51+H50+H48+H49 -> 1266.8951 | I30: =-G30+H30 -> 80.579286 | J30: =I30/G30 -> 0.067923976 | M30: =I30 -> 80.579286 | O30: =G30*1000/$O$7 -> 0.036010999 | P30: =H30*1000/$P$7 -> 0.066309332 | Q30: =-O30+P30 -> 0.030298333 | R30: =Q30/O30 -> 0.84136332 | AF30: TOTAL | AG30: =H31/$H$31 -> 1 | AH30: =H31* 1000/$P$7 -> 1.5664647 | AI30: =D31 -> 1 | AJ30: =G31*1000/$O$7 -> 1.5264024 | AK30: =H31 -> 29928.615 | AL30: =G31 -> 50284.506
C31: TOTAL | D31: =G31/$G$31 -> 1 | E31: =H31/$H$31 -> 1 | F31: =SUM(F22:F30) -> 0 | G31: =SUM(G22:G30) -> 50284.506 | H31: =SUM(H22:H30) -> 29928.615 | I31: =-G31+H31 -> -20355.89 | J31: =I31/G31 -> -0.40481436 | L31: =SUM(L22:L30) -> -15733.117 | M31: =SUM(M22:M30) -> -2219.3662 | N31: =SUM(N22:N30) -> -2403.4067 | O31: =G31*1000/$O$7 -> 1.5264024 | P31: =H31*1000/$P$7 -> 1.5664647 | Q31: =-O31+P31 -> 0.040062367 | R31: =Q31/O31 -> 0.026246268
L32: =L31/I31 -> 0.77290244 | M32: =M31/I31 -> 0.10902821 | N32: =N31/I31 -> 0.11806935
C34: VISTA 4
C35: Por categoria de negocio desagrupada | D35: DISTRIBUCIÓN % | G35: TONELADAS CO2 | O35: KGCO2/pieza
D36: 2021 | E36: 2022 | F36: DIF | G36: 2021 | H36: 2022 | I36: DIF | J36: % DIF | K36: EXPLICACION | O36: 2021 | P36: 2022 | Q36: DIF | R36: % DIF | S36: EXPLICACION
C37: Transporte Distribución | D37: =G37/$G$52 -> 0.2008499 | E37: =H37/$H$52 -> 0.23204498 | F37: =E37-D37 -> 0.031195073 | G37: 10099.541 | H37: ='2. Distribución'!K16 -> 6944.7849 | I37: =+H37-G37 -> -3154.7559 | J37: =I37/G37 -> -0.31236627 | K37: =K22 -> 1) Optimizacion de capacidad de flota por menor demanda, sin embargo no es proporcional a la baja de demanda (-42%) por concentración de piezas (-27%) 2) Mejora metodologica en incorporación de motos y limpieza de datos (-3%) 3) Incorporacion operacion de vehiculos elecltricos (-100 ton, -1%) | O37: =+G37*1000/$O$7 -> 0.30657482 | P37: =+H37*1000/$P$7 -> 0.36349028 | Q37: =+P37-O37 -> 0.056915459 | R37: =Q37/O37 -> 0.18564949 | S37: =S22 -> 1) Aumento de km/pieza por concentración de piezas en +26% 2) Mejora en rendimiento al incorporar motos, bicicletas y peatones en la caracterización de flota (-7%).
C38: Transporte aéreo | D38: =G38/$G$52 -> 0.20401861 | E38: =H38/$H$52 -> 0.22683976 | F38: =E38-D38 -> 0.022821156 | G38: 10258.876 | H38: ='3. Transporte aéreo'!D56 -> 6789 | I38: =+H38-G38 -> -3469.8759 | J38: =I38/G38 -> -0.33823159 | K38: =K23 -> 1) Disminución tkm no proporcional a la baja de demanda (-24%) 2) Mejora en el factor de emisión Latam (-10%) (-984 tonCO2) | O38: =+G38*1000/$O$7 -> 0.31141148 | P38: =+H38*1000/$P$7 -> 0.35533649 | Q38: =+P38-O38 -> 0.043925006 | R38: =Q38/O38 -> 0.14105133 | S38: =S23 -> Se mantiene base por concentración de entregas y menor emisión por cambio en metodología
C39: Transporte troncal | D39: =G39/$G$52 -> 0.21959238 | E39: =H39/$H$52 -> 0.14565576 | F39: =E39-D39 -> -0.073936615 | G39: 11041.988 | H39: ='4. Transporte troncal'!L12 -> 4359.2752 | I39: =+H39-G39 -> -6682.7124 | J39: =I39/G39 -> -0.60520919 | K39: =K24 -> 1) -50% por menor demanda (no proporcional a la baja -42%), modificación/optimización malla troncal y cambio de metodologia de medición (no es posible determinar los impactos de forma independiente) 2) -11% mayor precisión en el dato de rendimiento. | O39: =+G39*1000/$O$7 -> 0.33518309 | P39: =+H39*1000/$P$7 -> 0.22816461 | Q39: =+P39-O39 -> -0.10701848 | R39: =Q39/O39 -> -0.31928364 | S39: =S24 -> Aumento 15% km/pieza pero compensa con mejor rendimiento y por cambio metodologia
C40: Compra de servicios | D40: =G40/$G$52 -> 0.1315622 | E40: =H40/$H$52 -> 0.13833597 | F40: =E40-D40 -> 0.0067737658 | G40: 6615.4766 | H40: ='5. Bienes y servicios'!$O$35 -> 4140.204 | I40: =+H40-G40 -> -2475.2726 | J40: =I40/G40 -> -0.37416391 | K40: =K25 -> 1) Disminución del gasto en mayor proporción que el gasto en pesos por aumento del tipo de cambio(-13%) 2) Menores gastos realizados en pesos (-8%) 3) Reubicación de gastos incluidos en otras categorias (-16%) (ej. transporte y arreglos) | O40: =+G40*1000/$O$7 -> 0.20081493 | P40: =+H40*1000/$P$7 -> 0.21669842 | Q40: =+P40-O40 -> 0.015883494 | R40: =Q40/O40 -> 0.079095188 | S40: =S25 -> Reducción de emisiones totales (-37%) no proporcional a la baja de demanda (-42%)
C41: Traslado de colaboradores | D41: =G41/$G$52 -> 0.087987567 | E41: =H41/$H$52 -> 0.1085249 | F41: =E41-D41 -> 0.020537333 | G41: 4424.3687 | H41: ='6. Traslado colaboradores'!$L$12 -> 3248 | I41: =+H41-G41 -> -1176.3687 | J41: =I41/G41 -> -0.26588396 | K41: =K26 -> 1) Menor base de colaboradores (-20%) 2) Menor distancia recorrida por dia (declarada) por colaborador (-7%) | O41: =+G41*1000/$O$7 -> 0.13430314 | P41: =+H41*1000/$P$7 -> 0.17000043 | Q41: =+P41-O41 -> 0.035697293 | R41: =Q41/O41 -> 0.26579642 | S41: =S26 -> Reducción de emisiones totales (-27%) no proporcinal a la baja de demanda (-42%)
C42: Compra de electricidad | D42: =G42/$G$52 -> 0.031643545 | E42: =H42/$H$52 -> 0.035858731 | F42: =E42-D42 -> 0.0042151857 | G42: 1591.1647 | H42: ='7. Energia Electrica'!$X$16 -> 1073.2022 | I42: =+H42-G42 -> -517.96253 | J42: =I42/G42 -> -0.32552414 | K42: =K27 -> 1) Mejora de factor de emisión de matriz energetica nacional de un -23% (-18%) 2) Menor consumo electrico por instalaciones LED y menor cantidad de unidades (-11%) 3) Aumento de consumo ERNC respceto del total (+1%) | O42: =+G42*1000/$O$7 -> 0.048300317 | P42: =+H42*1000/$P$7 -> 0.056171438 | Q42: =+P42-O42 -> 0.0078711207 | R42: =Q42/O42 -> 0.16296209 | S42: =S27 -> Reduccion de emisiones totales (-29%) no es proporcional a la baja de demanda (-42%) por consumo fijo en instalaciones. Intensidad energetica por pieza aumenta +54%, sin embargo la mejora del factor de emisión contribuye a reducir -32%
C43: Otras emisiones energia electrica | D43: =G43/$G$52 -> 0.0060161168 | E43: =H43/$H$52 -> 0.0090406493 | F43: =E43-D43 -> 0.0030245325 | G43: 302.51454 | H43: ='7. Energia Electrica'!$Y$16 -> 270.57411 | I43: =+H43-G43 -> -31.940426 | J43: =I43/G43 -> -0.10558311 | O43: =+G43*1000/$O$7 -> 0.0091829264 | P43: =+H43*1000/$P$7 -> 0.014161858 | Q43: =+P43-O43 -> 0.0049789319 | R43: =Q43/O43 -> 0.54219447
C44: Insumos operacionales | D44: =G44/$G$52 -> 0.044677033 | E44: =H44/$H$52 -> 0.026371037 | F44: =E44-D44 -> -0.018305996 | G44: 2246.5409 | H44: ='8. Insumos y Empaque'!$J$29 -> 789.24863 | I44: =+H44-G44 -> -1457.2922 | J44: =I44/G44 -> -0.64868271 | K44: =K28 -> 1) Menor consumo de toneladas de material y optimización de compras de insumos y empaques (-46%) 2) Menor factor de emisión segun proporcion de uso de materiales por corrección (-18%) | O44: =+G44*1000/$O$7 -> 0.068194472 | P44: =+H44*1000/$P$7 -> 0.0413093 | Q44: =+P44-O44 -> -0.026885172 | R44: =Q44/O44 -> -0.39424268 | S44: =S28 -> 1) Menor consumo de material por pieza (-7%) 2) Menor factor de emision ponderado (-30%)
C45: Empaque | D45: =G45/$G$52 -> 0.0087229261 | E45: =H45/$H$52 -> 0.0063648521 | F45: =E45-D45 -> -0.002358074 | G45: 438.6238 | H45: ='8. Insumos y Empaque'!$J$28 -> 190.49121 | I45: =+H45-G45 -> -248.13259 | J45: =I45/G45 -> -0.56570708 | O45: =+G45*1000/$O$7 -> 0.013314567 | P45: =+H45*1000/$P$7 -> 0.0099703164 | Q45: =+P45-O45 -> -0.0033442504 | R45: =Q45/O45 -> -0.2511723
C46: Fin de vida empaques | D46: =G46/$G$52 -> 0.030513853 | E46: =H46/$H$52 -> 0.018022397 | F46: =E46-D46 -> -0.012491456 | G46: 1534.3592 | H46: ='8. Insumos y Empaque'!$K$28 -> 539.38539 | I46: =+H46-G46 -> -994.97385 | J46: =I46/G46 -> -0.64846212 | O46: =+G46*1000/$O$7 -> 0.046575969 | P46: =+H46*1000/$P$7 -> 0.02823145 | Q46: =+P46-O46 -> -0.01834452 | R46: =Q46/O46 -> -0.39386233
C47: Residuos | D47: =G47/$G$52 -> 0.010826641 | E47: =H47/$H$52 -> 0.0106104 | F47: =E47-D47 -> -0.00021624063 | G47: 544.40704 | H47: ='9. Residuos'!P25 -> 317.55459 | I47: =+H47-G47 -> -226.85245 | J47: =I47/G47 -> -0.41669639 | K47: =K29 -> 1) Menor compra/uso de materiales por menor demanda, mejora en tasa de valorización (recupero de residuos regiones y gestión de punto limpio Enea) (-34%) 2) Menor cantidad de colaboradores (-12%) 3) Aumento del factor de emisión ponderado por incorporación de tratamiento de residuos peligrosos (+2%) | O47: =+G47*1000/$O$7 -> 0.016525651 | P47: =+H47*1000/$P$7 -> 0.016620818 | Q47: =+P47-O47 -> 9.5166834e-05 | R47: =Q47/O47 -> 0.0057587343 | S47: =S29 -> Disminucion absoluta de emisiones (-41,6%) no proporcional a disminución de demanda (-42%)
C48: Bienes de capital | D48: =G48/$G$52 -> 0.020818647 | E48: =H48/$H$52 -> 0.030928489 | F48: =E48-D48 -> 0.010109842 | G48: 1046.8453 | H48: ='10. Bienes de capital'!J19 -> 925.64686 | I48: =+H48-G48 -> -121.19844 | J48: =I48/G48 -> -0.11577493 | O48: =+G48*1000/$O$7 -> 0.031777327 | P48: =+H48*1000/$P$7 -> 0.048448388 | Q48: =+P48-O48 -> 0.016671062 | R48: =Q48/O48 -> 0.52462127 | S48: No hay inversiones importantes en vehiculos o maquinarias, se incluye la compra de activos tangibles en esta categoría
C49: Emisiones fugitivas | D49: =G49/$G$52 -> 0.00055099015 | E49: =H49/$H$52 -> 0.0087953417 | F49: =E49-D49 -> 0.0082443516 | G49: 27.706 | H49: ='11. Refrigerantes'!$J$37 -> 263.2324 | I49: =+H49-G49 -> 235.5264 | J49: =I49/G49 -> 8.5009168 | O49: =+G49*1000/$O$7 -> 0.00084102456 | P49: =+H49*1000/$P$7 -> 0.013777593 | Q49: =+P49-O49 -> 0.012936568 | R49: =Q49/O49 -> 15.381915 | S49: Se declara una mayor cantidad de carga de gases refrigerantes, considera mantención de equipos nuevos adquiridos en durante 2021
C50: Viajes de negocio | D50: =G50/$G$52 -> 0.0021385481 | E50: =H50/$H$52 -> 0.0022070862 | F50: =E50-D50 -> 6.8538097e-05 | G50: 107.5348 | H50: ='12. Viajes de Negocio'!$G$37 -> 66.055034 | I50: =+H50-G50 -> -41.479763 | J50: =I50/G50 -> -0.3857334 | O50: =+G50*1000/$O$7 -> 0.0032642534 | P50: =+H50*1000/$P$7 -> 0.0034573227 | Q50: =+P50-O50 -> 0.00019306928 | R50: =Q50/O50 -> 0.059146534 | S50: Disminuye el monto considerado en viajes de negocio el año 2022, modificación en la metodología de cálculo, En linea con la disminución de la actividad
C51: Combustión fuentes fijas (calderas, generadores, etc) | D51: =G51/$G$52 -> 8.1039742e-05 | E51: =H51/$H$52 -> 0.00039964395 | F51: =E51-D51 -> 0.00031860421 | G51: 4.0750041 | H51: =SUM('13. Combustible Fuentes fijas'!$K$37:$L$37) -> 11.96079 | I51: =+H51-G51 -> 7.8857859 | J51: =I51/G51 -> 1.9351603 | O51: =+G51*1000/$O$7 -> 0.00012369806 | P51: =+H51*1000/$P$7 -> 0.00062602816 | Q51: =+P51-O51 -> 0.00050233009 | R51: =Q51/O51 -> 4.0609374 | S51: Se declara una mayor cantidad de generadores y calefactores en centros de distribución a nivel nacional
C52: TOTAL | D52: =SUM(D37:D51) -> 1 | E52: =SUM(E37:E51) -> 1 | F52: =E52-D52 -> 0 | G52: =+SUM(G37:G51) -> 50284.021 | H52: =+SUM(H37:H51) -> 29928.615 | I52: =+SUM(I37:I51) -> -20355.405 | J52: =I52/G52 -> -0.40480863 | O52: =+SUM(O37:O51) -> 1.5263877 | P52: =+SUM(P37:P51) -> 1.5664647 | Q52: =+P52-O52 -> 0.04007708 | R52: =Q52/O52 -> 0.026256161
C55: VISTA 5
C56: Por alcance GHG Protocol | D56: DISTRIBUCIÓN % | G56: TONELADAS CO2 | O56: KGCO2/pieza
D57: 2021 | E57: 2022 | F57: DIF | G57: 2021 | H57: 2022 | I57: DIF | J57: % DIF | K57: EXPLICACION | O57: 2021 | P57: 2022 | Q57: DIF | R57: % DIF | S57: EXPLICACION
C58: Alcance 1 | D58: =SUM(D67:D69) -> 0.094158368 | E58: =SUM(E67:E69) -> 0.092379844 | F58: =E58-D58 -> -0.0017785245 | G58: =SUM(G67:G69) -> 4734.641 | H58: =SUM(H67:H69) -> 2764.8008 | I58: =H58-G58 -> -1969.8402 | J58: =I58/G58 -> -0.41604848 | O58: =SUM(O67:O69) -> 0.14372155 | P58: =SUM(P67:P69) -> 0.14470977 | Q58: =P58-O58 -> 0.000988214 | R58: =Q58/O58 -> 0.0068758928
C59: Alcance 2 | D59: =D70 -> 0.031643681 | E59: =E70 -> 0.035858731 | F59: =E59-D59 -> 0.0042150498 | G59: =G70 -> 1591.1647 | H59: =H70 -> 1073.2022 | I59: =H59-G59 -> -517.96253 | J59: =I59/G59 -> -0.32552414 | O59: =O70 -> 0.048300317 | P59: =P70 -> 0.056171438 | Q59: =P59-O59 -> 0.0078711207 | R59: =Q59/O59 -> 0.16296209
C60: Alcance 3 | D60: =SUM(D71:D83) -> 0.87419795 | E60: =SUM(E71:E83) -> 0.87176143 | F60: =E60-D60 -> -0.0024365253 | G60: =SUM(G71:G83) -> 43957.999 | H60: =SUM(H71:H83) -> 26090.612 | I60: =H60-G60 -> -17867.387 | J60: =I60/G60 -> -0.40646497 | O60: =SUM(O71:O83) -> 1.3343592 | P60: =SUM(P71:P83) -> 1.3655835 | Q60: =P60-O60 -> 0.031224303 | R60: =Q60/O60 -> 0.023400222
C61: TOTAL | D61: =D60+D59+D58 -> 1 | E61: =E60+E59+E58 -> 1 | F61: =SUM(F58:F60) -> 2.0122792e-16 | G61: =SUM(G58:G60) -> 50283.805 | H61: =SUM(H58:H60) -> 29928.615 | I61: =H61-G61 -> -20355.189 | J61: =I61/G61 -> -0.40480607 | O61: =SUM(O58:O60) -> 1.5263811 | P61: =SUM(P58:P60) -> 1.5664647 | Q61: =P61-O61 -> 0.040083637 | R61: =Q61/O61 -> 0.02626057
C64: VISTA 6
C65: Por categoria de emisión GHG Protocol | D65: DISTRIBUCIÓN % | G65: TONELADAS CO2 | O65: KGCO2/pieza
D66: 2021 | E66: 2022 | F66: DIF | G66: 2021 | H66: 2022 | I66: DIF | J66: % DIF | K66: EXPLICACION | O66: 2021 | P66: 2022 | Q66: DIF | R66: % DIF | S66: EXPLICACION
B67: 1 | C67: A1: Fuentes móviles (Transporte propio troncal y local) | D67: =G67/$G$84 -> 0.093526336 | E67: =H67/$H$84 -> 0.083184858 | F67: =E67-D67 -> -0.010341478 | G67: ='4. Transporte troncal'!J24 -> 4702.86 | H67: ='2. Distribución'!N5+'4. Transporte troncal'!P16 -> 2489.6076 | I67: =H67-G67 -> -2213.2524 | J67: =I67/G67 -> -0.47061839 | O67: =G67*1000/$O$7 -> 0.14275683 | P67: =H67*1000/$P$7 -> 0.13030615 | Q67: =P67-O67 -> -0.012450684 | R67: =Q67/O67 -> -0.087216031
B68: 1 | C68: A1: Fuentes Fijas | D68: =G68/$G$84 -> 8.104009e-05 | E68: =H68/$H$84 -> 0.00039964395 | F68: =E68-D68 -> 0.00031860386 | G68: =G51 -> 4.0750041 | H68: =H51 -> 11.96079 | I68: =H68-G68 -> 7.8857859 | J68: =I68/G68 -> 1.9351603 | O68: =G68*1000/$O$7 -> 0.00012369806 | P68: =H68*1000/$P$7 -> 0.00062602816 | Q68: =P68-O68 -> 0.00050233009 | R68: =Q68/O68 -> 4.0609374
B69: 1 | C69: A1: Emisiones Fugitivas | D69: =G69/$G$84 -> 0.00055099251 | E69: =H69/$H$84 -> 0.0087953417 | F69: =E69-D69 -> 0.0082443492 | G69: =G49 -> 27.706 | H69: =H49 -> 263.2324 | I69: =H69-G69 -> 235.5264 | J69: =I69/G69 -> 8.5009168 | O69: =G69*1000/$O$7 -> 0.00084102456 | P69: =H69*1000/$P$7 -> 0.013777593 | Q69: =P69-O69 -> 0.012936568 | R69: =Q69/O69 -> 15.381915
B70: 2 | C70: A2: Compra de electricidad | D70: =G70/$G$84 -> 0.031643681 | E70: =H70/$H$84 -> 0.035858731 | F70: =E70-D70 -> 0.0042150498 | G70: =G42 -> 1591.1647 | H70: =H42 -> 1073.2022 | I70: =H70-G70 -> -517.96253 | J70: =I70/G70 -> -0.32552414 | O70: =G70*1000/$O$7 -> 0.048300317 | P70: =H70*1000/$P$7 -> 0.056171438 | Q70: =P70-O70 -> 0.0078711207 | R70: =Q70/O70 -> 0.16296209
B71: 3 | C71: A3 Cat.1 Distribución - Solo externo | D71: =G71/$G$84 -> 0.20085077 | E71: =H71/$H$84 -> 0.18820635 | F71: =E71-D71 -> -0.01264442 | G71: ='2. Distribución'!K22 -> 10099.541 | H71: ='2. Distribución'!N6+'2. Distribución'!O6 -> 5632.7554 | I71: =H71-G71 -> -4466.7854 | J71: =I71/G71 -> -0.44227609 | O71: =G71*1000/$O$7 -> 0.30657482 | P71: =H71*1000/$P$7 -> 0.29481861 | Q71: =P71-O71 -> -0.011756209 | R71: =Q71/O71 -> -0.038346949
B72: 3 | C72: A3 Cat.1 Transporte Troncal - solo externo | D72: =G72/$G$84 -> 0.12147027 | E72: =H72/$H$84 -> 0.10223311 | F72: =E72-D72 -> -0.019237161 | G72: =SUM('4. Transporte troncal'!J18:K23) -> 6107.9872 | H72: ='4. Transporte troncal'!J11+'4. Transporte troncal'!K11 -> 3059.6953 | I72: =H72-G72 -> -3048.2919 | J72: =I72/G72 -> -0.49906651 | O72: =G72*1000/$O$7 -> 0.18540992 | P72: =H72*1000/$P$7 -> 0.16014456 | Q72: =P72-O72 -> -0.025265364 | R72: =Q72/O72 -> -0.13626759
B73: 3 | C73: A3 Cat.1 Transporte Aéreo | D73: =G73/$G$84 -> 0.20401948 | E73: =H73/$H$84 -> 0.22683976 | F73: =E73-D73 -> 0.022820279 | G73: =G38 -> 10258.876 | H73: =H38 -> 6789 | I73: =H73-G73 -> -3469.8759 | J73: =I73/G73 -> -0.33823159 | O73: =G73*1000/$O$7 -> 0.31141148 | P73: =H73*1000/$P$7 -> 0.35533649 | Q73: =P73-O73 -> 0.043925006 | R73: =Q73/O73 -> 0.14105133
B74: 3 | C74: A3 Cat.1 Bienes y servicios - Compra de servicios | D74: =G74/$G$84 -> 0.13156277 | E74: =H74/$H$84 -> 0.13833597 | F74: =E74-D74 -> 0.0067732006 | G74: =G40 -> 6615.4766 | H74: =H40 -> 4140.204 | I74: =H74-G74 -> -2475.2726 | J74: =I74/G74 -> -0.37416391 | O74: =G74*1000/$O$7 -> 0.20081493 | P74: =H74*1000/$P$7 -> 0.21669842 | Q74: =P74-O74 -> 0.015883494 | R74: =Q74/O74 -> 0.079095188
B75: 3 | C75: A3 Cat.1 Bienes y servicios - Insumos Operacionales | D75: =G75/$G$84 -> 0.044677225 | E75: =H75/$H$84 -> 0.026371037 | F75: =E75-D75 -> -0.018306187 | G75: =G44 -> 2246.5409 | H75: =H44 -> 789.24863 | I75: =H75-G75 -> -1457.2922 | J75: =I75/G75 -> -0.64868271 | O75: =G75*1000/$O$7 -> 0.068194472 | P75: =H75*1000/$P$7 -> 0.0413093 | Q75: =P75-O75 -> -0.026885172 | R75: =Q75/O75 -> -0.39424268
B76: 3 | C76: A3 Cat.1 Bienes y servicios - Compra de empaques | D76: =G76/$G$84 -> 0.0087231148 | E76: =H76/$H$84 -> 0.0063648521 | F76: =E76-D76 -> -0.0023582627 | G76: ='8. Insumos y Empaque'!J63 -> 438.6314 | H76: ='8. Insumos y Empaque'!J28 -> 190.49121 | I76: =H76-G76 -> -248.14019 | J76: =I76/G76 -> -0.56571461 | O76: =G76*1000/$O$7 -> 0.013314798 | P76: =H76*1000/$P$7 -> 0.0099703164 | Q76: =P76-O76 -> -0.0033444812 | R76: =Q76/O76 -> -0.25118528
B77: 3 | C77: A3 Cat.2 Compra de bienes de capital | D77: =G77/$G$84 -> 0.020818737 | E77: =H77/$H$84 -> 0.030928489 | F77: =E77-D77 -> 0.010109753 | G77: =G48 -> 1046.8453 | H77: =H48 -> 925.64686 | I77: =H77-G77 -> -121.19844 | J77: =I77/G77 -> -0.11577493 | O77: =G77*1000/$O$7 -> 0.031777327 | P77: =H77*1000/$P$7 -> 0.048448388 | Q77: =P77-O77 -> 0.016671062 | R77: =Q77/O77 -> 0.52462127
B78: 3 | C78: A3 Cat.3 Otras emisiones de energía | D78: =G78/$G$84 -> 0.0060161426 | E78: =H78/$H$84 -> 0.0090406493 | F78: =E78-D78 -> 0.0030245067 | G78: =G43 -> 302.51454 | H78: =H43 -> 270.57411 | I78: =H78-G78 -> -31.940426 | J78: =I78/G78 -> -0.10558311 | O78: =G78*1000/$O$7 -> 0.0091829264 | P78: =H78*1000/$P$7 -> 0.014161858 | Q78: =P78-O78 -> 0.0049789319 | R78: =Q78/O78 -> 0.54219447
B79: 3 | C79: A3 Cat.3 Otras emisiones de combustible | D79: =G79/$G$84 -> 0.0045921943 | E79: =H79/$H$84 -> 0.0040764257 | F79: =E79-D79 -> -0.00051576856 | G79: ='4. Transporte troncal'!K24 -> 230.913 | H79: ='2. Distribución'!O5+'4. Transporte troncal'!Q16 -> 122.00178 | I79: =H79-G79 -> -108.91122 | J79: =I79/G79 -> -0.47165479 | O79: =G79*1000/$O$7 -> 0.0070094386 | P79: =H79*1000/$P$7 -> 0.0063855771 | Q79: =P79-O79 -> -0.00062386142 | R79: =Q79/O79 -> -0.089003051
B80: 3 | C80: A3 Cat 5: Residuos generados en las operaciones | D80: =G80/$G$84 -> 0.010826687 | E80: =H80/$H$84 -> 0.0106104 | F80: =E80-D80 -> -0.00021628714 | G80: =G47 -> 544.40704 | H80: =H47 -> 317.55459 | I80: =H80-G80 -> -226.85245 | J80: =I80/G80 -> -0.41669639 | O80: =G80*1000/$O$7 -> 0.016525651 | P80: =H80*1000/$P$7 -> 0.016620818 | Q80: =P80-O80 -> 9.5166834e-05 | R80: =Q80/O80 -> 0.0057587343
B81: 3 | C81: A3 Cat 6: Viajes de negocio | D81: =G81/$G$84 -> 0.0021385573 | E81: =H81/$H$84 -> 0.0022070862 | F81: =E81-D81 -> 6.852891e-05 | G81: =G50 -> 107.5348 | H81: =H50 -> 66.055034 | I81: =H81-G81 -> -41.479763 | J81: =I81/G81 -> -0.3857334 | O81: =G81*1000/$O$7 -> 0.0032642534 | P81: =H81*1000/$P$7 -> 0.0034573227 | Q81: =P81-O81 -> 0.00019306928 | R81: =Q81/O81 -> 0.059146534
B82: 3 | C82: A3 Cat 7: Traslado de trabajadores | D82: =G82/$G$84 -> 0.087987945 | E82: =H82/$H$84 -> 0.1085249 | F82: =E82-D82 -> 0.020536955 | G82: =G41 -> 4424.3687 | H82: =H41 -> 3248 | I82: =H82-G82 -> -1176.3687 | J82: =I82/G82 -> -0.26588396 | O82: =G82*1000/$O$7 -> 0.13430314 | P82: =H82*1000/$P$7 -> 0.17000043 | Q82: =P82-O82 -> 0.035697293 | R82: =Q82/O82 -> 0.26579642
B83: 3 | C83: A3 Cat 12: Fin de vida empaques | D83: =G83/$G$84 -> 0.030514059 | E83: =H83/$H$84 -> 0.018022397 | F83: =E83-D83 -> -0.012491662 | G83: ='8. Insumos y Empaque'!K63 -> 1534.363 | H83: ='8. Insumos y Empaque'!K28 -> 539.38539 | I83: =H83-G83 -> -994.97759 | J83: =I83/G83 -> -0.64846298 | O83: =G83*1000/$O$7 -> 0.046576083 | P83: =H83*1000/$P$7 -> 0.02823145 | Q83: =P83-O83 -> -0.018344633 | R83: =Q83/O83 -> -0.39386381
C84: TOTAL | D84: =SUM(D67:D83) -> 1 | E84: =SUM(E67:E83) -> 1 | F84: =SUM(F67:F83) -> 1.3877788e-16 | G84: =+SUM(G67:G83) -> 50283.805 | H84: =+SUM(H67:H83) -> 29928.615 | I84: =+SUM(I67:I83) -> -20355.189 | J84: =I84/G84 -> -0.40480607 | O84: =+SUM(O67:O83) -> 1.5263811 | P84: =+SUM(P67:P83) -> 1.5664647 | Q84: =+P84-O84 -> 0.040083637 | R84: =Q84/O84 -> 0.02626057
C87: VISTA 7
C88: Por indicador operacional | D88: INDICADOR OPERACIONAL 1 | I88: INDICADOR OPERACIONAL 2 | Q88: INDICADOR OPERACIONAL 3 | V88: INDICADOR OPERACIONAL 4
D89: INDICADOR | E89: 2021 | F89: 2022 | G89: DIF | H89: % DIF | I89: INDICADOR | J89: 2021 | K89: 2022 | O89: DIF | P89: % DIF | Q89: INDICADOR | R89: 2021 | S89: 2022 | T89: DIF | U89: % DIF | V89: INDICADOR | W89: 2021 | X89: 2022 | Y89: DIF | Z89: % DIF
C90: Transporte Distribución | D90: Kms recorridos | E90: ='2. Distribución'!C38 -> 42162803 | F90: ='2. Distribución'!D38 -> 30753064 | G90: =F90-E90 -> -11409739 | H90: =G90/E90 -> -0.27061149 | I90: km/pieza | J90: ='2. Distribución'!C39 -> 1.2798655 | K90: ='2. Distribución'!D39 -> 1.6096164 | O90: =K90-J90 -> 0.32975093 | P90: =O90/J90 -> 0.257645 | Q90: kgcCO2/pieza evitado (VE) | R90: 0 | S90: ='2. Distribución'!D48 -> 0.0051293233 | T90: =S90-R90 -> 0.0051293233 | U90: 1 | V90: Kms VEs | W90: ='2. Distribución'!C45 -> 0 | X90: ='2. Distribución'!D45 -> 430662 | Y90: =X90-W90 -> 430662 | Z90: 1
C91: Transporte aéreo | D91: tkm | E91: ='3. Transporte aéreo'!C11 -> 4316623 | F91: ='3. Transporte aéreo'!D11 -> 3270844 | G91: =F91-E91 -> -1045779 | H91: =G91/E91 -> -0.24226786 | I91: tkm/pieza | J91: ='3. Transporte aéreo'!C26 -> 0.13103248 | K91: ='3. Transporte aéreo'!D26 -> 0.17119609 | O91: =K91-J91 -> 0.040163603 | P91: =O91/J91 -> 0.30651639 | Q91: % tkm Latam | R91: ='3. Transporte aéreo'!C14 -> 0.38176301 | S91: ='3. Transporte aéreo'!D14 -> 0.33608267 | T91: =S91-R91 -> -0.045680338 | U91: =T91 -> -0.045680338 | V91: KgCO2/tkm | W91: ='3. Transporte aéreo'!C61 -> 2.3763947 | X91: ='3. Transporte aéreo'!D61 -> 2.0756111 | Y91: =X91-W91 -> -0.30078363 | Z91: =Y91/W91 -> -0.12657141
C92: Transporte troncal | D92: kms recorridos | E92: ='4. Transporte troncal'!C31 -> 13897306 | F92: ='4. Transporte troncal'!D31 -> 6860911 | G92: =F92-E92 -> -7036395 | H92: =G92/E92 -> -0.5063136 | I92: km/pieza | J92: ='4. Transporte troncal'!C32 -> 0.4218572 | K92: ='4. Transporte troncal'!D32 -> 0.35910031 | O92: =K92-J92 -> -0.06275689 | P92: =O92/J92 -> -0.14876335
C93: Compra de servicios | D93: Gasto en pesos | E93: ='5. Bienes y servicios'!B40 -> 16301080658 | F93: ='5. Bienes y servicios'!C40 -> 14978136314 | G93: =F93-E93 -> -1322944344 | H93: =G93/E93 -> -0.081156849 | I93: Tipo de cambio | J93: ='5. Bienes y servicios'!B41 -> 759 | K93: ='5. Bienes y servicios'!C41 -> 886 | O93: =K93-J93 -> 127 | P93: =O93/J93 -> 0.16732543 | Q93: Gasto en dolares | R93: ='5. Bienes y servicios'!B42 -> 21477050 | S93: ='5. Bienes y servicios'!C42 -> 16905346 | T93: =S93-R93 -> -4571703.9 | U93: =T93/R93 -> -0.21286461 | V93: - | W93: - | X93: - | Y93: - | Z93: -%
C94: Traslado de colaboradores | D94: Presencialidad | E94: ='6. Traslado colaboradores'!B55 -> 0.677725 | F94: ='6. Traslado colaboradores'!C55 -> 0.736626 | G94: =F94-E94 -> 0.058901 | H94: =G94 -> 0.058901 | I94: Km/dia/colab | J94: ='6. Traslado colaboradores'!B56 -> 27.551423 | K94: ='6. Traslado colaboradores'!C56 -> 23.496471 | O94: =K94-J94 -> -4.0549524 | P94: =O94/J94 -> -0.1471776 | Q94: Uso de auto | R94: ='6. Traslado colaboradores'!B57 -> 0.5034 | S94: ='6. Traslado colaboradores'!C57 -> 0.58433 | T94: =S94-R94 -> 0.08093 | U94: =T94 -> 0.08093 | V94: kgCO2/dia por colaborador | W94: ='6. Traslado colaboradores'!B58 -> 5.8774139 | X94: ='6. Traslado colaboradores'!C58 -> 5.4491616 | Y94: =X94-W94 -> -0.42825237 | Z94: =Y94/W94 -> -0.072864081
C95: Energia Electrica | D95: Consumo kwh | E95: ='7. Energia Electrica'!P16 -> 5497449 | F95: ='7. Energia Electrica'!W16 -> 4917011 | G95: =F95-E95 -> -580437.95 | H95: =G95/E95 -> -0.10558314 | I95: Intensidad energetica por pieza | J95: ='7. Energia Electrica'!O38 -> 0.16687684 | K95: ='7. Energia Electrica'!P38 -> 0.25735653 | O95: =K95-J95 -> 0.090479688 | P95: =O95/J95 -> 0.54219441 | Q95: % ERNC | R95: ='7. Energia Electrica'!O40 -> 0.28027454 | S95: ='7. Energia Electrica'!P40 -> 0.28986532 | T95: =S95-R95 -> 0.009590782 | U95: =T95 -> 0.009590782 | V95: Consumo/unidad | W95: ='7. Energia Electrica'!O44 -> 22347.354 | X95: ='7. Energia Electrica'!P44 -> 21285.762 | Y95: =X95-W95 -> -1061.5915 | Z95: =Y95/W95 -> -0.047504128
C96: Insumos operacionales y embalajes | D96: Kg insumos/pieza | E96: ='8. Insumos y Empaque'!C156 -> 0.035509656 | F96: ='8. Insumos y Empaque'!D156 -> 0.041813243 | G96: =F96-E96 -> 0.0063035865 | H96: =G96/E96 -> 0.17751753 | I96: Kg empaques/pieza | J96: ='8. Insumos y Empaque'!C157 -> 0.025699423 | K96: ='8. Insumos y Empaque'!D157 -> 0.015389195 | O96: =K96-J96 -> -0.010310228 | P96: =O96/J96 -> -0.40118521 | Q96: - | R96: - | S96: - | T96: - | U96: - | V96: - | W96: - | X96: - | Y96: - | Z96: -
C97: Residuos | D97: Res.generados/pieza | E97: ='9. Residuos'!D53 -> 0.037614039 | F97: ='9. Residuos'!E53 -> 0.04306538 | G97: =F97-E97 -> 0.0054513411 | H97: =G97/E97 -> 0.14492836 | I97: Res.env.relleno/pieza | J97: ='9. Residuos'!D56 -> 0.020157604 | K97: ='9. Residuos'!E56 -> 0.019251188 | O97: =K97-J97 -> -0.00090641574 | P97: =O97/J97 -> -0.044966443 | Q97: Tasa de valorización | R97: ='9. Residuos'!D55 -> 0.46409361 | S97: ='9. Residuos'!E55 -> 0.55297764 | T97: =S97-R97 -> 0.088884023 | U97: =T97 -> 0.088884023 | V97: - | W97: - | X97: - | Y97: - | Z97: -
C98: Bienes de capital

Sheet 1. Demanda
A1: Demanda CXP 2022 | B1: Enero | C1: Febrero | D1: Marzo | E1: Abril | F1: Mayo | G1: Junio | H1: Julio | I1: Agosto | J1: Septiembre | K1: Octubre | L1: Noviembre | M1: Diciembre | N1: Total
A2: Encomiendas y valijas | B2: 1570029 | C2: 1405041 | D2: 1534834 | E2: 1451744 | F2: 1441651 | G2: 1522102 | H2: 1265657 | I2: 1313760 | J2: 1128292 | K2: 1374975 | L2: 1221741 | M2: 1529817 | N2: 16759643
A3: Documentos | B3: 199250 | C3: 176648 | D3: 237526 | E3: 199281 | F3: 214697 | G3: 185027 | H3: 186969 | I3: 202981 | J3: 179265 | K3: 178750 | L3: 191116 | M3: 194681 | N3: 2346191
A4: Total | B4: 1769279 | C4: 1581689 | D4: 1772360 | E4: 1651025 | F4: 1656348 | G4: 1707129 | H4: 1452626 | I4: 1516741 | J4: 1307557 | K4: 1553725 | L4: 1412857 | M4: 1724498 | N4: 19105834
A7: Demanda CXP 2021 | B7: 2647774 | C7: 2330302 | D7: 2764544 | E7: 2749646 | F7: 3536982 | G7: 3651844 | H7: 2949034 | I7: 2544053 | J7: 2337380 | K7: 2383714 | L7: 2367896 | M7: 2679983 | N7: =SUM(B7:M7) -> 32943152
A10: Demanda
A11: 2021 | B11: 32943152
A12: 2022 | B12: 19105834

Sheet 2. Distribución
A1: TRANSPORTE TERRESTRE DE TERCEROS - DISTRIBUCIÓN
B3: Por favor llene la siguiente información sobre la cantidad y tipo de combustibles consumidos para todos los vehículos de terceros durante el año calendario 2022. Indique además información de tipo de servicio, marca - modelo, rendimiento y km recorridos. Si no cuenta con la información de combustible consumido, dejar en blanco. | L3: GHG Protocolo
L4: Propiedad | M4: Alcance | N4: Directas | O4: Indirectas | P4: Total
L5: PROPIO | M5: Alcance 1 | N5: =I10 -> 1250.7378 | O5: =J10 -> 61.291681 | P5: =SUM(N5:O5) -> 1312.0295
B6: TIPO DE RESPALDOS: | C6: Facturas, registros internos de compra, respaldos de SAP, documentación con supuestos y estimaciones si aplica. | L6: EXTERNO | M6: Alcance 3 | N6: =SUM(I11:I12) -> 5361.4857 | O6: =SUM(J11:J13) -> 271.26972 | P6: =SUM(N6:O6) -> 5632.7554
M7: Total | N7: =SUM(N5:N6) -> 6612.2235 | O7: =SUM(O5:O6) -> 332.5614 | P7: =SUM(N7:O7) -> 6944.7849
B8: 2022 | I8: Directo | J8: Indirecto
B9: Tipo de vehículo | C9: Rendimiento (km/l) | D9: Km recorridos | E9: Tipo de combustible | F9: Fecha | G9: Cantidad combustible consumido (mes) | H9: Unidad | I9: ton CO2-e | J9: ton CO2-e
B10: Furgones propios | C10: 12 | D10: 5477362 | E10: Diesel vehículos todo terreno | F10: 2022 | G10: =+D10/C10 -> 456446.83 | H10: Lt | I10: =+G10*VLOOKUP(E10,'Factores Emisión EDGE'!$K$7:$L$13,2,FALSE)/1000 -> 1250.7378 | J10: =+G10*VLOOKUP(E10,'Factores Emisión EDGE'!$K$254:$L$260,2,FALSE)/1000 -> 61.291681
B11: Furgones externos | C11: 12 | D11: 23047281 | E11: Diesel vehículos todo terreno | F11: 2022 | G11: =+D11/C11 -> 1920606.8 | H11: Lt | I11: =+G11*VLOOKUP(E11,'Factores Emisión EDGE'!$K$7:$L$13,2,FALSE)/1000 -> 5262.7717 | J11: =+G11*VLOOKUP(E11,'Factores Emisión EDGE'!$K$254:$L$260,2,FALSE)/1000 -> 257.89907
B12: Motos | C12: 42 | D12: 1797759 | E12: Gasolina | F12: 2022 | G12: =+D12/C12 -> 42803.786 | H12: Lt | I12: =+G12*VLOOKUP(E12,'Factores Emisión EDGE'!$K$7:$L$13,2,FALSE)/1000 -> 98.713962 | J12: =+G12*VLOOKUP(E12,'Factores Emisión EDGE'!$K$254:$L$260,2,FALSE)/1000 -> 5.2700021 | M12: BNE
B13: Vehiculo Electrico | C13: 0 | D13: 430662 | E13: Energía Eléctrica | F13: 2022 | G13: 147209 | H13: kWh | I13: 0 | J13: =G13*D30/1000 -> 8.1006417 | M13: Gasolina | N13: =G12+G15 -> 47913.786 | O13: =H12 -> Lt
B14: Vehiculo Hibrido (Gas Natural) | C14: 7.51 | D14: =G14/C14 -> 1266.1784 | E14: Gas natural | G14: 9509 | H14: m3 | I14: =9509000*C28/1000 -> 19.911846 | J14: =9509000*D28/1000 -> 3.1627409 | M14: Gas natural | N14: =G14 -> 9509 | O14: =H14 -> m3
B15: Vehiculo Hibrido (Gasolina) | C15: Ya incluido | D15: Ya incluido | E15: Gasolina | G15: 5110 | H15: Lt | I15: =G15*C27/1000 -> 11.784667 | J15: =G15*D27/1000 -> 0.6861708 | M15: EE | N15: =G13 -> 147209 | O15: =H13 -> kWh
D16: =SUM(D9:D13) -> 30753064 | I16: =SUM(I10:I15)-I14-I15 -> 6612.2235 | J16: =SUM(J10:J15)-J14-J15 -> 332.5614 | K16: =J16+I16 -> 6944.7849 | M16: Diesel | N16: =G10+G11 -> 2377053.6 | O16: =H11 -> Lt
B19: 2021 | I19: Directo | J19: Indirecto | M19: Rendimiento 7,51 km/m3
B20: Tipo de vehículo | C20: Rendimiento (km/l) | D20: Km recorridos | E20: Tipo de combustible | F20: Fecha | G20: Cantidad combustible consumido (mes) | H20: Unidad | I20: ton CO2-e | J20: ton CO2-e
B21: FURGON | C21: 12 | D21: 42162803 | E21: Diesel vehículos todo terreno | F21: 2021 | G21: =D21/C21 -> 3513566.9 | H21: Lt | I21: =+G21*VLOOKUP(E21,'Factores Emisión EDGE'!$K$7:$L$13,2,FALSE)/1000 -> 9627.739 | J21: =+G21*VLOOKUP(E21,'Factores Emisión EDGE'!$K$254:$L$260,2,FALSE)/1000 -> 471.80177
I22: =+SUM(I21) -> 9627.739 | J22: =+SUM(J21) -> 471.80177 | K22: =J22+I22 -> 10099.541
B25: Factor de Emisión según combustible | C25: Directas | D25: Indirectas | E25: Totales | F25: Unidad de medida
B26: Diesel | C26: 2.740161 | D26: 0.12312 | E26: =D26+C26 -> 2.863281 | F26: kgCO2/l
B27: Gasolina | C27: 2.306197 | D27: 0.13428 | E27: =D27+C27 -> 2.440477 | F27: kgCO2/l
B28: Gas natural | C28: 0.002094 | D28: 0.000332605 | E28: =D28+C28 -> 0.002426605 | F28: kgCO2/l
B29: Energía Electrica (SEN) | C29: 0.3006 | D29: 0.055028169 | E29: =D29+C29 -> 0.35562817 | F29: kgCO2/kWh | G29: SEN: Sistema Eléctrico Nacional
B30: Energia Electrica (ERNC) | C30: 0 | D30: 0.055028169 | E30: =D30+C30 -> 0.055028169 | F30: kgCO2/kWh | G30: SEN: Sistema Eléctrico Nacional
B31: Energia Electrica Punta Arenas (SEM) | C31: 0.59279167 | D31: 0.055028169 | E31: =D31+C31 -> 0.64781984 | F31: kgCO2/kWh | G31: SEM: Sistema Eléctrico Magallanes
B32: Energia Electrica Aysén (SEA) | C32: 0.7245 | D32: 0.055028169 | E32: =D32+C32 -> 0.77952817 | F32: kgCO2/kWh | G32: SEA: Sistema Eléctrico Aysen
B36: Resumen
B37: Distribución | C37: 2021 | D37: 2022 | F37: Diferencia | G37: Explicacion
B38: kilometros recorridos | C38: =D21 -> 42162803 | D38: =SUM(D10:D13) -> 30753064 | E38: =D38-C38 -> -11409739 | F38: =D38/C38-1 -> -0.27061149 | G38: Se disminuyen los kilometros recorridos por la red por menor demanda, sin embargo no es proporcional por concentración de piezas.
B39: km/pieza | C39: =D21/C54 -> 1.2798655 | D39: =D38/C55 -> 1.6096164 | E39: 0.33 | F39: =D39/C39-1 -> 0.257645 | G39: Aumento de km/pieza por base de coberturas para entregas (concentración de piezas)
B40: factor de ajuste | C40: 0.761 | D40: 0.706 | E40: =D40-C40 -> -0.055 | F40: =D40-C40 -> -0.055 | G40: disminución de factor
B41: Entregas por planilla | C41: 0.0558 | D41: 0.0278 | E41: =D41-C41 -> -0.028 | F41: =D41-C41 -> -0.028 | G41: disminución de entregas por planilla
B42: Rendimiento promedio | C42: =C43 -> 12 | D42: =D38/SUM(G10:G12) -> 12.708627 | E42: 0.71 | F42: =D42/C42-1 -> 0.059052226
B43: Rendimiento furgon | C43: 12 | D43: 12 | F43: =C43-D43 -> 0 | G43: se mantiene
B44: Rendimiento motos | C44: No aplica | D44: 42 | F44: No hay en 2021 | G44: se incorporan motos
B45: kms VE (descontados) | C45: 0 | D45: 430662 | E45: =D45-C45 -> 430662 | F45: No hay en 2021 | G45: Inicio operacion electrica septiembre 2022
B46: Piezas entregadas VE 2022 | E46: =D46-C46 -> 0 | F46: No hay en 2021 | G46: Inicio operacion electrica septiembre 2022
B47: tCO2 evitado VE | C47: 0 | D47: 98 | E47: =D47-C47 -> 98 | F47: No hay en 2021 | G47: inicio operacion electrica septiembre 2022
B48: kgCO2/pieza evitado VE | C48: 0 | D48: =D47*1000/C55 -> 0.0051293233 | E48: =D48-C48 -> 0.0051293233 | F48: No hay en 2021 | G48: inicio operacion electrica septiembre 2022
B49: tCO2 | C49: =SUM(I22:J22) -> 10099.541 | D49: =SUM(I16:J16) -> 6944.7849 | E49: =D49-C49 -> -3154.7559 | F49: =D49/C49-1 -> -0.31236627 | G49: 1) Optimizacion de capacidad de flota por menor demanda, sin embargo no es proporcional a la baja de demanda (-42%) por concentración de piezas --> (2.700 t, -27%) 2) Mejora metodologica en incorporación de motos y limpieza de datos (-3%) 3) Incorporacion operacion de vehiculos elecltricos (-100 ton, -1%)
B50: kgCO2/pieza | C50: =C49*1000/C54 -> 0.30657482 | D50: =D49*1000/C55 -> 0.36349028 | E50: =D50-C50 -> 0.056915459 | F50: =D50/C50-1 -> 0.18564949 | G50: 1) Aumento de km/pieza por concentración de piezas en +26% 2) Mejora en rendimiento al incorporar motos, bicicletas y peatones en la caracterización de flota (-7%).
B53: Demanda
B54: 2021 | C54: 32943152
B55: 2022 | C55: 19105834

Sheet 3. Transporte aéreo
A1: TRANSPORTE AÉREO
B3: Por favor llene la siguiente información sobre el peso transportado y km recorridos o bien indique origen y destino, para todo el transporte de carga aéreo realizado durante el año calendario 2021.
B7: TIPO DE RESPALDOS: | C7: Facturas, respaldos de SAP u otros.
B9: Transporte aéreo
B10: Resumen aéreo | C10: 2021 | D10: 2022 | E10: Dif | F10: Dif % | G10: Justificación
A11: TOTALES | B11: ton*km total | C11: 4316623 | D11: 3270844 | E11: =D11-C11 -> -1045779 | F11: =D11/C11-1 -> -0.24226786 | G11: Disminución de tkm (-24%) por menor cantidad de piezas aereas (-22%) y menor cantidad de vuelos (-2%). Disminución no proporcional a la baja demanda de piezas totales (-42%).
B12: tkm Latam | C12: 1647927 | D12: 1099274 | E12: =D12-C12 -> -548653 | F12: =E12/C12 -> -0.33293526
B13: tkm Sky | C13: 2668695 | D13: 2171610 | E13: =D13-C13 -> -497085 | F13: =E13/C13 -> -0.1862652
B14: % tkm Latam | C14: =C12/C11 -> 0.38176301 | D14: =D12/D11 -> 0.33608267 | E14: =D14-C14 -> -0.045680338 | F14: =E14 -> -0.045680338 | G14: -5% tkm Latam en 2022
B15: % tkm Sky | C15: =C13/C11 -> 0.61823676 | D15: =D13/D11 -> 0.66392955 | E15: =D15-C15 -> 0.045692799 | F15: =E15 -> 0.045692799
B16: km recorrido | C16: 12819508 | D16: 12580674 | E16: =D16-C16 -> -238834 | F16: =E16/C16 -> -0.018630512 | G16: Se mantienen los vuelos realizados
B17: km recorrido Latam | C17: 7588782 | D17: 5750014 | E17: =D17-C17 -> -1838768 | F17: =E17/C17 -> -0.24230081
B18: km recorrido Sky | C18: 5230726 | D18: 6830660 | E18: =D18-C18 -> 1599934 | F18: =E18/C18 -> 0.30587226
B19: % km recorrido Latam | C19: =C17/C16 -> 0.59197139 | D19: =D17/D16 -> 0.45705135 | E19: =D19-C19 -> -0.13492005 | F19: =E19 -> -0.13492005
B20: % km recorrido Sky | C20: =C18/C16 -> 0.40802861 | D20: =D18/D16 -> 0.54294865 | E20: =D20-C20 -> 0.13492005 | F20: =E20 -> 0.13492005
B21: toneladas transportadas | C21: 2865035 | D21: 2221871 | E21: =D21-C21 -> -643164 | F21: =E21/C21 -> -0.22448731 | G21: -22% Disminución por cantidad de piezas enviadas (o peso de las piezas TBC)
B22: ton transportadas Latam | C22: 930882 | D22: 611415 | E22: =D22-C22 -> -319467 | F22: =E22/C22 -> -0.34318743
B23: ton transportadas Sky | C23: 1934153 | D23: 1610456 | E23: =D23-C23 -> -323697 | F23: =E23/C23 -> -0.16735853
B24: % ton transportadas Latam | C24: =C22/C21 -> 0.32491121 | D24: =D22/D21 -> 0.27518024 | E24: =D24-C24 -> -0.049730972 | F24: =E24 -> -0.049730972
B25: % ton transportadas Sky | C25: =C23/C21 -> 0.67508879 | D25: =D23/D21 -> 0.72481976 | E25: =D25-C25 -> 0.049730972 | F25: =E25 -> 0.049730972
A26: POR PIEZA DDA TOTAL | B26: ton*km total/ pieza (dda total) | C26: =C11/$C$73 -> 0.13103248 | D26: =D11/$C$74 -> 0.17119609 | E26: =D26-C26 -> 0.040163603 | F26: =D26/C26-1 -> 0.30651639
B27: tkm Latam / Pieza | C27: =C12/$C$73 -> 0.050023355 | D27: =D12/$C$74 -> 0.057536038 | E27: =D27-C27 -> 0.0075126831 | F27: =E27/C27 -> 0.15018351
B28: tkm Sky / pieza | C28: =C13/$C$73 -> 0.081009097 | D28: =D13/$C$74 -> 0.11366214 | E28: =D28-C28 -> 0.032653044 | F28: =E28/C28 -> 0.40307873
B29: % tkm Latam | C29: =C27/C26 -> 0.38176301 | D29: =D27/D26 -> 0.33608267 | E29: =D29-C29 -> -0.045680338 | F29: =E29 -> -0.045680338
B30: % tkm Sky | C30: =C28/C26 -> 0.61823676 | D30: =D28/D26 -> 0.66392955 | E30: =D30-C30 -> 0.045692799 | F30: =E30 -> 0.045692799
B31: km recorrido / pieza | C31: =C16/C73 -> 0.3891403 | D31: =D16/C74 -> 0.6584729 | E31: =D31-C31 -> 0.26933261 | F31: =E31/C31 -> 0.69212211
B32: km recorrido Latam | C32: =C17/$C$73 -> 0.23035992 | D32: =D17/$C$74 -> 0.30095593 | E32: =D32-C32 -> 0.070596004 | F32: =E32/C32 -> 0.30645957
B33: km recorrido Sky | C33: =C18/$C$73 -> 0.15878037 | D33: =D18/$C$74 -> 0.35751698 | E33: =D33-C33 -> 0.1987366 | F33: =E33/C33 -> 1.2516446
B34: % km recorrido Latam | C34: =C32/C31 -> 0.59197139 | D34: =D32/D31 -> 0.45705135 | E34: =D34-C34 -> -0.13492005 | F34: =E34 -> -0.13492005
B35: % km recorrido Sky | C35: =C33/C31 -> 0.40802861 | D35: =D33/D31 -> 0.54294865 | E35: =D35-C35 -> 0.13492005 | F35: =E35 -> 0.13492005
B36: toneladas transportadas /pieza | C36: =C21/$C$73 -> 0.086969061 | D36: =D21/$C$74 -> 0.1162928 | E36: =D36-C36 -> 0.029323742 | F36: =E36/C36 -> 0.33717442
B37: ton transportadas Latam | C37: =C22/$C$73 -> 0.028257223 | D37: =D22/$C$74 -> 0.032001482 | E37: =D37-C37 -> 0.0037442586 | F37: =E37/C37 -> 0.13250625
B38: ton transportadas Sky | C38: =C23/$C$73 -> 0.058711838 | D38: =D23/$C$74 -> 0.084291322 | E38: =D38-C38 -> 0.025579484 | F38: =E38/C38 -> 0.43567847
B39: % ton transportadas Latam | C39: =C37/C36 -> 0.32491121 | D39: =D37/D36 -> 0.27518024 | E39: =D39-C39 -> -0.049730972 | F39: =E39 -> -0.049730972
B40: % ton transportadas Sky | C40: =C38/C36 -> 0.67508879 | D40: =D38/D36 -> 0.72481976 | E40: =D40-C40 -> 0.049730972 | F40: =E40 -> 0.049730972
A41: POR PIEZA AEREA | B41: ton*km total/ pieza | E41: =D41-C41 -> 0 | F41: =D41/C41-1 -> #DIV/0!
B42: tkm Latam / Pieza | E42: =D42-C42 -> 0 | F42: =E42/C42 -> #DIV/0!
B43: tkm Sky / pieza | E43: =D43-C43 -> 0 | F43: =E43/C43 -> #DIV/0!
B44: % tkm Latam | E44: =D44-C44 -> 0 | F44: =E44 -> 0
B45: % tkm Sky | E45: =D45-C45 -> 0 | F45: =E45 -> 0
B46: km recorrido / pieza | E46: =D46-C46 -> 0 | F46: =E46/C46 -> #DIV/0!
B47: km recorrido Latam | E47: =D47-C47 -> 0 | F47: =E47/C47 -> #DIV/0!
B48: km recorrido Sky | E48: =D48-C48 -> 0 | F48: =E48/C48 -> #DIV/0!
B49: % km recorrido Latam | E49: =D49-C49 -> 0 | F49: =E49 -> 0
B50: % km recorrido Sky | E50: =D50-C50 -> 0 | F50: =E50 -> 0
B51: toneladas transportadas /pieza | E51: =D51-C51 -> 0 | F51: =E51/C51 -> #DIV/0!
B52: ton transportadas Latam | E52: =D52-C52 -> 0 | F52: =E52/C52 -> #DIV/0!
B53: ton transportadas Sky | E53: =D53-C53 -> 0 | F53: =E53/C53 -> #DIV/0!
B54: % ton transportadas Latam | E54: =D54-C54 -> 0 | F54: =E54 -> 0
B55: % ton transportadas Sky | E55: =D55-C55 -> 0 | F55: =E55 -> 0
A56: Emisiones CO2 | B56: Emisiones totales CO2 | C56: 10258 | D56: 6789 | E56: =D56-C56 -> -3469 | F56: =E56/C56 -> -0.33817508 | G56: 1) Disminución tkm por menor cantidad aereas (-24%) 2) Mejora en el factor de emisión Latam (-10%) (-984 tonCO2)
B57: Emisiones totales Latam | C57: 3916 | D57: 1628 | E57: =D57-C57 -> -2288 | F57: =E57/C57 -> -0.58426966
B58: Emisiones totales Sky | C58: 6342 | D58: 5161 | E58: =D58-C58 -> -1181 | F58: =E58/C58 -> -0.18621886
B59: % Emisiones totales Latam | C59: =C57/C56 -> 0.38175083 | D59: =D57/D56 -> 0.23979968 | E59: =D59-C59 -> -0.14195115 | F59: =E59 -> -0.14195115
B60: % Emisiones totales Sky | C60: =C58/C56 -> 0.61824917 | D60: =D58/D56 -> 0.76020032 | E60: =D60-C60 -> 0.14195115 | F60: =E60 -> 0.14195115
B61: kgCO2/tkm | C61: =C56*1000/C11 -> 2.3763947 | D61: =D56*1000/D11 -> 2.0756111 | E61: =D61-C61 -> -0.30078363 | F61: =E61/C61 -> -0.12657141 | G61: -13% factor de emision ponderado, por -38% factor de emision de latam
B62: kgCO2 Latam/tkm Latam | C62: =C57*1000/C12 -> 2.3763189 | D62: =D57*1000/D12 -> 1.4809774 | E62: =D62-C62 -> -0.89534141 | F62: =E62/C62 -> -0.37677663 | G62: -38% Factor emision de latam
B63: kgCO2 Sky /tkm Sky | C63: =C58*1000/C13 -> 2.3764424 | D63: =D58*1000/D13 -> 2.3765777 | E63: =D63-C63 -> 0.00013532798 | F63: =E63/C63 -> 5.6945617e-05
B64: kgCO2/pieza (dda total) | C64: =C56*1000/C73 -> 0.3113849 | D64: =D56*1000/C74 -> 0.35533649 | E64: =D64-C64 -> 0.043951593 | F64: =E64/C64 -> 0.14114876
B65: Piezas aéreas y contenedores | C65: 760227 | D65: 524516 | E65: =D65-C65 -> -235711 | F65: =E65/C65 -> -0.31005344
B68: Factores de Emision 2022 | C68: kgCO2/tkm | D68: kgCO2/tkm
B69: Latam | C69: =1628/1099000*1000 -> 1.4813467 | D69: n/a | F69: =D57/2 -> 814
B70: Sky | C70: =4836/2035225*1000 -> 2.3761501 | D70: =4836/2035225*1000 -> 2.3761501
B72: Demanda Total
B73: 2021 | C73: 32943152 | F73: 2022 sin cambio metodologia
B74: 2022 | C74: 19105834 | F74: 7733 | G74: emisiones totales
B76: Piezas Aereas
B77: 2021
B78: 2022 | C78: 1058034 | D78: =C78/C74 -> 0.055377535
B84: Considerar emisiones indirectas del transporte aerea
B85: tonkm 2022 | C85: =D11 -> 3270844
B86: factor de emision indirecto | C86: 2.11713 | D86: kgCO2/tkm
B87: total emisiones indirectas | C87: =C85*C86/1000 -> 6924.802 | D87: ton CO2
B91: Q Enc Aereo: 1.058.034

Sheet 4. Transporte troncal
A1: TRANSPORTE TRONCAL
B3: Por favor llene la siguiente información sobre la cantidad y tipo de combustibles consumidos para todos los vehículos de terceros durante el año calendario 2022. Indique además información de tipo de servicio, marca - modelo, rendimiento y km recorridos. Si no cuenta con la información de combustible consumido, dejar en blanco.
B6: TIPO DE RESPALDOS: | C6: Facturas, registros internos de compra, respaldos de SAP, documentación con supuestos y estimaciones si aplica.
B8: Transporte TRONCAL 2022 | J8: Directas | K8: Indirectas
B9: Tipo de movimiento | C9: Tipo de vehículo | D9: Rendimiento (km/l) | E9: Km recorridos | F9: Tipo de combustible | G9: Fecha | H9: Cantidad combustible consumido (mes) | I9: Unidad | J9: ton CO2-e | K9: ton CO2-e
C10: Troncal propio | D10: 4.5033229 | E10: 2036023 | F10: Diesel vehículos todo terreno | G10: 2022 | H10: =+E10/D10 -> 452115.7 | I10: Lt | J10: =+H10*VLOOKUP(F10,'Factores Emisión EDGE'!$K$7:$L$13,2,FALSE)/1000 -> 1238.8698 | K10: =+H10*VLOOKUP(F10,'Factores Emisión EDGE'!$K$254:$L$260,2,FALSE)/1000 -> 60.710096
C11: Troncal Externo | D11: 4.5327571 | E11: 4824888 | F11: Diesel vehículos todo terreno | G11: 2021 | H11: =+E11/D11 -> 1064448.8 | I11: Lt | J11: =+H11*VLOOKUP(F11,'Factores Emisión EDGE'!$K$7:$L$13,2,FALSE)/1000 -> 2916.7612 | K11: =+H11*VLOOKUP(F11,'Factores Emisión EDGE'!$K$254:$L$260,2,FALSE)/1000 -> 142.93419
B12: Total | D12: =E12/H12 -> 4.5239823 | E12: =E11+E10 -> 6860911 | H12: =H11+H10 -> 1516564.5 | J12: =J11+J10 -> 4155.631 | K12: =K11+K10 -> 203.64428 | L12: =K12+J12 -> 4359.2752
O14: Emisiones transporte troncal
P15: Directas | Q15: Indirectas | R15: Total
B16: Transporte TRONCAL 2021 | J16: Alcance 1 | K16: Alcance 3 | N16: PROPIO | O16: Alcance 1 | P16: =J10 -> 1238.8698 | Q16: =K10 -> 60.710096 | R16: =Q16+P16 -> 1299.5799
B17: Tipo de movimiento | C17: Tipo de vehículo | D17: Rendimiento (km/l) | E17: Km recorridos | F17: Tipo de combustible | G17: Fecha | H17: Cantidad combustible consumido (mes) | I17: Unidad | J17: ton CO2-e | K17: ton CO2-e | N17: EXTERNO | O17: Alcance 3 | P17: 2917 | Q17: 142 | R17: =Q17+P17 -> 3059
C18: CAMIONES | D18: 3 | E18: 5420945 | F18: Diesel vehículos todo terreno | G18: 2021 | H18: =+E18/D18 -> 1806981.7 | I18: Lt | J18: =+H18*VLOOKUP(F18,'Factores Emisión EDGE'!$K$7:$L$13,2,FALSE)/1000 -> 4951.4207 | K18: =+H18*VLOOKUP(F18,'Factores Emisión EDGE'!$K$254:$L$260,2,FALSE)/1000 -> 242.6415 | O18: Total | P18: =P17+P16 -> 4155.8698 | Q18: =Q17+Q16 -> 202.7101 | R18: =SUM(R16:R17) -> 4358.5799
C19: CAMION 3/4 | D19: 4 | E19: 31705 | F19: Diesel vehículos todo terreno | G19: 2021 | H19: =+E19/D19 -> 7926.25 | I19: Lt | J19: =+H19*VLOOKUP(F19,'Factores Emisión EDGE'!$K$7:$L$13,2,FALSE)/1000 -> 21.719201 | K19: =+H19*VLOOKUP(F19,'Factores Emisión EDGE'!$K$254:$L$260,2,FALSE)/1000 -> 1.0643368
C20: TRACTO | D20: 2.7 | E20: 31501 | F20: Diesel vehículos todo terreno | G20: 2021 | H20: =+E20/D20 -> 11667.037 | I20: Lt | J20: =+H20*VLOOKUP(F20,'Factores Emisión EDGE'!$K$7:$L$13,2,FALSE)/1000 -> 31.96956 | K20: =+H20*VLOOKUP(F20,'Factores Emisión EDGE'!$K$254:$L$260,2,FALSE)/1000 -> 1.5666497
C21: RAMPA | D21: 2.7 | E21: 350888 | F21: Diesel vehículos todo terreno | G21: 2021 | H21: =+E21/D21 -> 129958.52 | I21: Lt | J21: =+H21*VLOOKUP(F21,'Factores Emisión EDGE'!$K$7:$L$13,2,FALSE)/1000 -> 356.10726 | K21: =+H21*VLOOKUP(F21,'Factores Emisión EDGE'!$K$254:$L$260,2,FALSE)/1000 -> 17.45083 | O21: BNE
C22: CAMIONETAS | D22: 10 | E22: 161181 | F22: Diesel vehículos livianos | G22: 2021 | H22: =+E22/D22 -> 16118.1 | I22: Lt | J22: =+H22*VLOOKUP(F22,'Factores Emisión EDGE'!$K$7:$L$13,2,FALSE)/1000 -> 44.166189 | K22: =+H22*VLOOKUP(F22,'Factores Emisión EDGE'!$K$254:$L$260,2,FALSE)/1000 -> 2.1643385 | O22: Diesel | P22: =H12 -> 1516564.5 | Q22: =I11 -> Lt
C23: OTROS | D23: 2.7 | E23: 411153 | F23: Diesel vehículos todo terreno | G23: 2021 | H23: =+E23/D23 -> 152278.89 | I23: Lt | J23: =+H23*VLOOKUP(F23,'Factores Emisión EDGE'!$K$7:$L$13,2,FALSE)/1000 -> 417.26867 | K23: =+H23*VLOOKUP(F23,'Factores Emisión EDGE'!$K$254:$L$260,2,FALSE)/1000 -> 20.448009
C24: Transporte propio | D24: 2.93 | E24: 7489933 | F24: Diesel vehículos todo terreno | G24: 2021 | H24: 3042567 | I24: Lt | J24: 4702.86 | K24: 230.913
B25: Total | D25: =E25/H25 -> 2.6893687 | E25: =+SUM(E18:E24) -> 13897306 | H25: =SUM(H18:H24) -> 5167497.5 | J25: =+SUM(J18:J24) -> 10525.512 | K25: =+SUM(K18:K24) -> 516.24866 | L25: =K25+J25 -> 11041.76
B26: *Agregar filas en caso de ser necesario
B29: Resumen
B30: Transporte troncal | C30: 2021 | D30: 2022 | F30: Diferencia | G30: Justificación
B31: kilometros recorridos | C31: =E25 -> 13897306 | D31: =E12 -> 6860911 | E31: =D31-C31 -> -7036395 | F31: =D31/C31-1 -> -0.5063136 | G31: -50% por menor demanda (no proporcional a la baja -42%), modificación/optimización malla troncal y cambio de metodologia de medición (no es posible determinar los impactos de forma independiente)
B32: km/pieza | C32: =C31/C38 -> 0.4218572 | D32: =D31/C39 -> 0.35910031 | E32: =D32-C32 -> -0.06275689 | F32: =D32/C32-1 -> -0.14876335 | G32: -15% por menor demanda no proporcional a la baja de demanda -42% (se mantiene base estructural) y cambio de metodologia (no es posible determinar los impactos de forma independiente).
B33: Rendimiento promedio km/lt | C33: =D25 -> 2.6893687 | D33: 4.5 | E33: =D33-C33 -> 1.8106313 | F33: =D33/C33-1 -> 0.67325513 | G33: Mayor precisión en el dato de rendimiento por mejora en información de entrada.
B34: tCO2 | C34: =J25+K25 -> 11041.76 | D34: =J12+K12 -> 4359.2752 | E34: =D34-C34 -> -6682.485 | F34: =D34/C34-1 -> -0.60520106 | G34: -50% por menor demanda (no proporcional a la baja -42%), modificación/optimización malla troncal y cambio de metodologia de medición (no es posible determinar los impactos de forma independiente) y -11% mayor precisión en el dato de rendimiento.
B35: kgCO2/pieza | C35: =C34*1000/C38 -> 0.33517619 | D35: =D34*1000/C39 -> 0.22816461 | E35: =D35-C35 -> -0.10701158 | F35: =D35/C35-1 -> -0.31926963 | G35: -15% por menor demanda no proporcional a la baja de demanda -42% (se mantiene base estructural) y cambio de metodologia (no es posible determinar los impactos de forma independiente) y -17% por mayor precisión en el dato de rendimiento.
B37: Demanda
B38: 2021 | C38: 32943152
B39: 2022 | C39: 19105834
F40: 2022 con antigua metodologia y menor rendimiento
E41: kms | F41: 10000894 | G41: =(F41-C31)/C31 -> -0.28037175
B42: Factores de emision | E42: tco2 | F42: 9673 | G42: =(F42-C34)/C34 -> -0.12396214
B43: Tipo de combustible | C43: Emisiones directas | D43: Emisiones indirectas | E43: kgCO2/pieza | F43: =F42/C39*1000 -> 0.50628515 | G43: =(F43-C35)/C35 -> 0.51050451
B44: Diesel vehículos todo terreno | C44: 2.740161 | D44: 0.13428
F45: =F42-C34 -> -1368.7602

Sheet 5. Bienes y servicios
A1: COMPRA DE BIENES Y SERVICIOS
B3: Por favor indique la compra de otros insumos (no cuantificados en las otras pestañas) realizadas sólo durante el año calendario 2022. Completar con información de insumos necesarios para el funcionamiento de la empresa. Algunos tipos pueden incluir: - Materiales y equipos de oficina: papel, computadores, etc. - Artículos de higiene: papel higiénico, jabón, etc. - Bienes de capital: vehículos, instalaciones, etc. - Servicios: marketing, servicios financieros, página web,etc. Es importante que se incluya al menos el 80% de las compras de bienes y servicios. No considerar la compra de vehículos de terceros.
B7: TIPO DE RESPALDOS: | C7: Facturas, registros internos de compras, SAP u otros.
B8: Recomendación: | C8: Si haciendo un screening económico, algún gasto representa una contribución relevante al total de gastos, evaluar si se puede obtener su compra en unidades
C9: de masa, de lo contrario, utilizar directamente información en pesos chilenos.
C10: Todos los gastos de bienes de capital como vehículos, maquinaria, instalaciones o reparaciones, deben ser reportados en pesos chilenos.
A14: 2021 - CON NUEVA CATEGORIZACION | G14: 2021 CON ANTIGUA CATEGORIZACION | M14: 2022 - CON NUEVA CATEGORIZACION | R14: EMISIONES CO2 | T14: Monto en pesos
A15: Tipo de servicio | B15: $ | C15: ton CO2-e | D15: Categoría | E15: Contribución | G15: Tipo de servicio | H15: Monto | I15: ton CO2-e | J15: Categoría | K15: Contribución | M15: Tipo de servicio | N15: $ | O15: ton CO2-e | P15: Categoría | Q15: Contribución | R15: Diferencia | S15: Diferencia % | T15: Diferencia | U15: Diferencia %
A16: Agua | B16: =+SUMIF($L$93:$L$167,$A16,$M$93:$M$167) -> 113416853 | C16: =+SUMIF($L$93:$L$167,$A16,$O$93:$O$167) -> 75.37 | D16: Servicio | E16: =B16/$B$34 -> 0.0071174504 | G16: Agua | H16: 109964105 | I16: 72.16311 | J16: Servicio | K16: =H16/$H$35 -> 0.0067458169 | M16: Agua | N16: =+SUMIF($D$93:$D$167,$M16,$E$93:$E$167) -> 116009037 | O16: =+SUMIF($D$93:$D$167,$M16,$G$93:$G$167) -> 66.540675 | P16: Servicio | Q16: =N16/$N$35 -> 0.0077452251 | R16: =O16-I16 -> -5.6224347 | S16: =R16/I16 -> -0.077912867 | T16: =N16-H16 -> 6044932
A17: Arriendo de vehículos | B17: =+SUMIF($L$93:$L$167,$A17,$M$93:$M$167) -> 511190660 | C17: =+SUMIF($L$93:$L$167,$A17,$O$93:$O$167) -> 235.44 | D17: Servicio | E17: =B17/$B$34 -> 0.032079661 | G17: Articulos de aseo y oficina | H17: 178647274 | I17: 1136.4643 | J17: Servicio | K17: =H17/$H$35 -> 0.010959229 | M17: Arriendo de vehículos | N17: =+SUMIF($D$93:$D$167,$M17,$E$93:$E$167) -> 383015502 | O17: =+SUMIF($D$93:$D$167,$M17,$G$93:$G$167) -> 152.03836 | P17: Servicio | Q17: =N17/$N$35 -> 0.025571639 | S17: =R17/I17 -> 0
A18: Capacitaciones y entrenamientos | B18: =+SUMIF($L$93:$L$167,$A18,$M$93:$M$167) -> 199760973 | C18: =+SUMIF($L$93:$L$167,$A18,$O$93:$O$167) -> 62.06 | D18: Servicio | E18: =B18/$B$34 -> 0.012535957 | G18: Asesorías financieras | H18: 35036025 | I18: 6 | J18: Servicio | K18: =H18/$H$35 -> 0.0021493069 | M18: Capacitaciones y entrenamientos | N18: =+SUMIF($D$93:$D$167,$M18,$E$93:$E$167) -> 109318192 | O18: =+SUMIF($D$93:$D$167,$M18,$G$93:$G$167) -> 29.742609 | P18: Servicio | Q18: =N18/$N$35 -> 0.0072985176 | R18: =O18-I19 -> -44.257391 | S18: =R18/I18 -> -7.3762318 | T18: =N18-H19 -> -119569735
A19: Investigación | B19: =+SUMIF($L$93:$L$167,$A19,$M$93:$M$167) -> 1779663442 | C19: =+SUMIF($L$93:$L$167,$A19,$O$93:$O$167) -> 559.34 | D19: Servicio | E19: =B19/$B$34 -> 0.1116824 | G19: Capacitaciones y entrenamientos | H19: 228887927 | I19: 74 | J19: Servicio | K19: =H19/$H$35 -> 0.014041273 | M19: Investigación | N19: =+SUMIF($D$93:$D$167,$M19,$E$93:$E$167) -> 1814125681 | O19: =+SUMIF($D$93:$D$167,$M19,$G$93:$G$167) -> 481.85328 | P19: Servicio | Q19: =N19/$N$35 -> 0.12111825 | R19: =O19-I21 -> -58.146718 | S19: =R19/I19 -> -0.78576646 | T19: =N19-H21 -> 43653098
A20: Licencias (Software) | B20: =+SUMIF($L$93:$L$167,$A20,$M$93:$M$167) -> 2069832179 | C20: =+SUMIF($L$93:$L$167,$A20,$O$93:$O$167) -> 565.18 | D20: Servicio | E20: =B20/$B$34 -> 0.12989188 | G20: Gastos Bancarios | H20: 17018447 | I20: 3 | J20: Servicio | K20: =H20/$H$35 -> 0.0010440073 | M20: Licencias (Software) | N20: =+SUMIF($D$93:$D$167,$M20,$E$93:$E$167) -> 2769155553 | O20: =+SUMIF($D$93:$D$167,$M20,$G$93:$G$167) -> 644.25548 | P20: Servicio | Q20: =N20/$N$35 -> 0.18487985 | R20: =O20-I22 -> 249.25548 | S20: =R20/I20 -> 83.08516 | T20: =N20-H22 -> 1319958465
A21: Limpieza | B21: =+SUMIF($L$93:$L$167,$A21,$M$93:$M$167) -> 1573466544 | C21: =+SUMIF($L$93:$L$167,$A21,$O$93:$O$167) -> 504.47 | D21: Servicio | E21: =B21/$B$34 -> 0.098742557 | G21: Investigación | H21: 1770472583 | I21: 540 | J21: Servicio | K21: =H21/$H$35 -> 0.10861075 | M21: Limpieza | N21: =+SUMIF($D$93:$D$167,$M21,$E$93:$E$167) -> 977833304 | O21: =+SUMIF($D$93:$D$167,$M21,$G$93:$G$167) -> 269.63573 | P21: Servicio | Q21: =N21/$N$35 -> 0.065284044 | R21: =O21-I23 -> -190.36427 | S21: =R21/I21 -> -0.35252642 | T21: =N21-H23 -> -461161482
A22: Mantención vehículos | B22: =+SUMIF($L$93:$L$167,$A22,$M$93:$M$167) -> 358274307 | C22: =+SUMIF($L$93:$L$167,$A22,$O$93:$O$167) -> 63.87 | D22: Servicio | E22: =B22/$B$34 -> 0.022483428 | G22: Licencias (Softwares) | H22: 1449197088 | I22: 395 | J22: Servicio | K22: =H22/$H$35 -> 0.088901903 | M22: Mantención vehículos | N22: =+SUMIF($D$93:$D$167,$M22,$E$93:$E$167) -> 299398083 | O22: =+SUMIF($D$93:$D$167,$M22,$G$93:$G$167) -> 45.945911 | P22: Servicio | Q22: =N22/$N$35 -> 0.019989008 | S22: =R22/I22 -> 0
A23: Marketing | B23: =+SUMIF($L$93:$L$167,$A23,$M$93:$M$167) -> 538421762 | C23: =+SUMIF($L$93:$L$167,$A23,$O$93:$O$167) -> 165.52 | D23: Servicio | E23: =B23/$B$34 -> 0.033788543 | G23: Limpieza | H23: 1438994786 | I23: 460 | J23: Servicio | K23: =H23/$H$35 -> 0.088276036 | M23: Marketing | N23: =+SUMIF($D$93:$D$167,$M23,$E$93:$E$167) -> 747797840 | O23: =+SUMIF($D$93:$D$167,$M23,$G$93:$G$167) -> 199.89937 | P23: Servicio | Q23: =N23/$N$35 -> 0.04992596 | R23: =O23-I24 -> -160.10063 | S23: =R23/I23 -> -0.34804485 | T23: =N23-H24 -> -409673845
A24: Otros servicios | B24: =+SUMIF($L$93:$L$167,$A24,$M$93:$M$167) -> 1299062898 | C24: =+SUMIF($L$93:$L$167,$A24,$O$93:$O$167) -> 421.76 | D24: Servicio | E24: =B24/$B$34 -> 0.081522414 | G24: Marketing | H24: 1157471685 | I24: 360 | J24: Servicio | K24: =H24/$H$35 -> 0.071005825 | M24: Otros servicios | N24: =+SUMIF($D$93:$D$167,$M24,$E$93:$E$167) -> 1274735466 | O24: =+SUMIF($D$93:$D$167,$M24,$G$93:$G$167) -> 391.42414 | P24: Servicio | Q24: =N24/$N$35 -> 0.085106414 | R24: =O24-I25 -> -5.575857 | S24: =R24/I24 -> -0.015488492 | T24: =N24-H25 -> 32840043
A25: Patentes | B25: =+SUMIF($L$93:$L$167,$A25,$M$93:$M$167) -> 9420476 | C25: =+SUMIF($L$93:$L$167,$A25,$O$93:$O$167) -> 2.91 | D25: Servicio | E25: =B25/$B$34 -> 0.00059117996 | G25: Otros servicios | H25: 1241895423 | I25: 397 | J25: Servicio | K25: =H25/$H$35 -> 0.076184852 | M25: Patentes | N25: =+SUMIF($D$93:$D$167,$M25,$E$93:$E$167) -> 14224547 | O25: =+SUMIF($D$93:$D$167,$M25,$G$93:$G$167) -> 3.8374426 | P25: Servicio | Q25: =N25/$N$35 -> 0.00094968738 | R25: =O25-I26 -> -65.162557 | S25: =R25/I25 -> -0.16413742 | T25: =N25-H26 -> -208032169
A26: Seguros | B26: =+SUMIF($L$93:$L$167,$A26,$M$93:$M$167) -> 1397167076 | C26: =+SUMIF($L$93:$L$167,$A26,$O$93:$O$167) -> 330.45 | D26: Servicio | E26: =B26/$B$34 -> 0.087678921 | G26: Patentes | H26: 222256716 | I26: 69 | J26: Servicio | K26: =H26/$H$35 -> 0.013634477 | M26: Seguros | N26: =+SUMIF($D$93:$D$167,$M26,$E$93:$E$167) -> 997344185 | O26: =+SUMIF($D$93:$D$167,$M26,$G$93:$G$167) -> 205.80781 | P26: Servicio | Q26: =N26/$N$35 -> 0.066586668 | R26: =O26-I28 -> -128.19219 | S26: =R26/I26 -> -1.8578578 | T26: =N26-H28 -> -409104569
A27: Servicio de reclutamiento | B27: =+SUMIF($L$93:$L$167,$A27,$M$93:$M$167) -> 146881991 | C27: =+SUMIF($L$93:$L$167,$A27,$O$93:$O$167) -> 47.08 | D27: Servicio | E27: =B27/$B$34 -> 0.0092175479 | G27: Repuestos | H27: 113257845 | I27: 111.34692 | J27: Servicio | K27: =H27/$H$35 -> 0.0069478734 | M27: Servicio de reclutamiento | N27: =+SUMIF($D$93:$D$167,$M27,$E$93:$E$167) -> 71884631 | O27: =+SUMIF($D$93:$D$167,$M27,$G$93:$G$167) -> 17.09127 | P27: Servicio | Q27: =N27/$N$35 -> 0.0047993041 | R27: =O27-I29 -> -28.90873 | S27: =R27/I27 -> -0.25962758 | T27: =N27-H29 -> -74397360
A28: Servicios Arreglos / mantención oficinas - arquitectos, maestros | B28: =+SUMIF($L$93:$L$167,$A28,$M$93:$M$167) -> 1256229424 | C28: =+SUMIF($L$93:$L$167,$A28,$O$93:$O$167) -> 571.9 | D28: Servicio | E28: =B28/$B$34 -> 0.078834409 | G28: Seguros | H28: 1406448754 | I28: 334 | J28: Servicio | K28: =H28/$H$35 -> 0.086279479 | M28: Servicios Arreglos / mantención oficinas - arquitectos, maestros | N28: =+SUMIF($D$93:$D$167,$M28,$E$93:$E$167) -> 1148314294 | O28: =+SUMIF($D$93:$D$167,$M28,$G$93:$G$167) -> 447.9502 | P28: Servicio | Q28: =N28/$N$35 -> 0.076666033 | R28: =O28-I30 -> -345.0498 | S28: =R28/I28 -> -1.0330832 | T28: =N28-H30 -> -589516343
A29: Servicios computacionales | B29: =+SUMIF($L$93:$L$167,$A29,$M$93:$M$167) -> 2523179363 | C29: =+SUMIF($L$93:$L$167,$A29,$O$93:$O$167) -> 709.11 | D29: Servicio | E29: =B29/$B$34 -> 0.15834158 | G29: Servicio de reclutamiento | H29: 146281991 | I29: 46 | J29: Servicio | K29: =H29/$H$35 -> 0.0089737603 | M29: Servicios computacionales | N29: =+SUMIF($D$93:$D$167,$M29,$E$93:$E$167) -> 2906489376 | O29: =+SUMIF($D$93:$D$167,$M29,$G$93:$G$167) -> 700.76156 | P29: Servicio | Q29: =N29/$N$35 -> 0.1940488 | R29: =O29-I31 -> -11.238437 | S29: =R29/I29 -> -0.24431386 | T29: =N29-H31 -> 371732464
A30: Servicios varios (mantención de las oficinas, etc.) | B30: =+SUMIF($L$93:$L$167,$A30,$M$93:$M$167) -> 455146828 | C30: =+SUMIF($L$93:$L$167,$A30,$O$93:$O$167) -> 145.8 | D30: Servicio | E30: =B30/$B$34 -> 0.028562642 | G30: Servicios Arreglos / mantención oficinas - arquitectos, maestros | H30: 1737830637 | I30: 793 | J30: Servicio | K30: =H30/$H$35 -> 0.10660831 | M30: Servicios varios (mantención de las oficinas, etc.) | N30: =+SUMIF($D$93:$D$167,$M30,$E$93:$E$167) -> 258693810 | O30: =+SUMIF($D$93:$D$167,$M30,$G$93:$G$167) -> 69.158016 | P30: Servicio | Q30: =N30/$N$35 -> 0.017271428 | R30: =O30-I17 -> -1067.3063 | S30: =R30/I30 -> -1.3459096
A31: Suscripciones y membresías | B31: =+SUMIF($L$93:$L$167,$A31,$M$93:$M$167) -> 428370 | C31: =+SUMIF($L$93:$L$167,$A31,$O$93:$O$167) -> 0.21 | D31: Servicio | E31: =B31/$B$34 -> 2.6882268e-05 | G31: Servicios Computacionales | H31: 2534756912 | I31: 712 | J31: Servicio | K31: =H31/$H$35 -> 0.15549625 | M31: Suscripciones y membresías | N31: =+SUMIF($D$93:$D$167,$M31,$E$93:$E$167) -> 10827066 | O31: =+SUMIF($D$93:$D$167,$M31,$G$93:$G$167) -> 4.6338227 | P31: Servicio | Q31: =N31/$N$35 -> 0.00072285802 | R31: =O31-I32 -> 4.6338227 | S31: =R31/I31 -> 0.0065081779 | T31: =N31-H32 -> 10398696
A32: Telefonía e internet | B32: =+SUMIF($L$93:$L$167,$A32,$M$93:$M$167) -> 1605758616 | C32: =+SUMIF($L$93:$L$167,$A32,$O$93:$O$167) -> 713.32 | D32: Servicio | E32: =B32/$B$34 -> 0.10076904 | G32: Suscripciones y membresías | H32: 428370 | I32: 0 | J32: Servicio | K32: =H32/$H$35 -> 2.6278626e-05 | M32: Telefonía e internet | N32: =+SUMIF($D$93:$D$167,$M32,$E$93:$E$167) -> 886452800 | O32: =+SUMIF($D$93:$D$167,$M32,$G$93:$G$167) -> 337.97328 | P32: Servicio | Q32: =N32/$N$35 -> 0.059183117 | R32: =O32-I33 -> -575.02672 | S32: =R32/I32 -> #DIV/0! | T32: =N32-H33 -> -1207059994
A33: Vestuario | B33: =+SUMIF($L$93:$L$167,$A33,$M$93:$M$167) -> 97737789 | C33: =+SUMIF($L$93:$L$167,$A33,$O$93:$O$167) -> 43.31 | D33: Servicio | E33: =B33/$B$34 -> 0.0061335141 | G33: Telefonía e internet | H33: 2093512794 | I33: 913 | J33: Servicio | K33: =H33/$H$35 -> 0.12842785 | M33: Vestuario | N33: =+SUMIF($D$93:$D$167,$M33,$E$93:$E$167) -> 192516947 | O33: =+SUMIF($D$93:$D$167,$M33,$G$93:$G$167) -> 71.655075 | P33: Servicio | Q33: =N33/$N$35 -> 0.012853198 | R33: =O33-I34 -> -121.71573 | S33: =R33/I33 -> -0.13331405 | T33: =N33-H34 -> -226204349
A34: Total | B34: =SUM(B16:B33) -> 15935039551 | C34: =SUM(C16:C33) -> 5217.1 | E34: =SUM(E16:E33) -> 1 | G34: Vestuario | H34: 418721296 | I34: 193.3708 | J34: Servicio | K34: =H34/$H$35 -> 0.02568672
G35: Total | H35: =SUM(H16:H34) -> 16301080658 | I35: =SUM(I16:I34) -> 6615.3451 | K35: =SUM(K16:K34) -> 1 | M35: Total | N35: =SUM(N16:N33) -> 14978136314 | O35: =SUM(O16:O33) -> 4140.204 | Q35: =SUM(Q16:Q33) -> 1 | R35: =SUM(R16:R33) -> -2552.7785
C36: =C34/(B34/B41) -> 0.00024849508 | R36: =O35-I35 -> -2475.1411
A38: Resumen | L38: Tipo de servicio | M38: $ | N38: ton CO2-e | O38: % | P38: % | Q38: Factor Emisión
B39: 2021 | C39: 2022 | D39: Diferencia | E39: Dif % | F39: Justificación | K39: 1 | L39: Servicios computacionales | M39: 2906489376 | N39: 700.76156 | O39: =N39/$N$57 -> 0.16925774 | P39: =SUM(O39:O45) -> 0.79074694 | Q39: 0.2133242
A40: Gasto en pesos | B40: =H35 -> 16301080658 | C40: =N35 -> 14978136314 | D40: =C40-B40 -> -1322944344 | E40: =D40/B40 -> -0.081156849 | F40: 1) Mejora de precios por negociacion con proveedor de telefonia e internet y proyectos internos de mejora (-6%, -1.000.0000) 2) Menor gasto en servicios y arreglos (-2%, -600.000.000) | K40: 2 | L40: Licencias (Software) | M40: 2769155553 | N40: 644.25548 | O40: =N40/$N$57 -> 0.1556096 | Q40: 0.20678607
A41: tipo de cambio | B41: 759 | C41: 886 | D41: =C41-B41 -> 127 | E41: =D41/B41 -> 0.16732543 | F41: Aumento tipo de cambio por condiciones del mercado | K41: 3 | L41: Investigación | M41: 1814125681 | N41: 481.85328 | O41: =N41/$N$57 -> 0.11638395 | Q41: 0.23560118
A42: Gasto en dolares | B42: =B40/B41 -> 21477050 | C42: =C40/C41 -> 16905346 | D42: =C42-B42 -> -4571703.9 | E42: =D42/B42 -> -0.21286461 | F42: 1) Disminución del gasto en mayor proporción que el gasto en pesos por aumento del tipo de cambio(-13%) 2) Menores gastos realizados en pesos (-8%) | K42: 4 | L42: Servicios Arreglos / mantención oficinas - arquitectos, maestros | M42: 1148314294 | N42: 447.9502 | O42: =N42/$N$57 -> 0.1081952 | Q42: 0.34631562
A43: kgCO2/USD ponderado | B43: =B44*1000/B42 -> 0.30801927 | C43: =C44*1000/C42 -> 0.24490502 | D43: =C43-B43 -> -0.06311425 | E43: =D43/B43 -> -0.20490358 | F43: Disminución de factor de emisión ponderado por cambio en servicios consumidos | K43: 5 | L43: Otros servicios | M43: 1274735466 | N43: 391.42414 | O43: =N43/$N$57 -> 0.094542235 | Q43: 0.24271678
A44: Emisiones C02 | B44: =I35 -> 6615.3451 | C44: =O35 -> 4140.204 | D44: =C44-B44 -> -2475.1411 | E44: =D44/B44 -> -0.37415147 | F44: 1) Disminución del gasto en dolares mayor proporción que el gasto en pesos por aumento del tipo de cambio(-13%) 2) Menores gastos realizados en pesos por mejora de negociacion con proveedor de telefonia e internet y menores gastos en servicios y arreglos (-8%) 3) Reubicación de gastos incluidos en otras categorias (-16%) (ej. transporte y arreglos) | K44: 6 | L44: Telefonía e internet | M44: 886452800 | N44: 337.97328 | O44: =N44/$N$57 -> 0.081632034 | Q44: 0.33101681
A45: kgCO2/pieza | B45: =B44*1000/B61 -> 0.20081093 | C45: =C44*1000/B62 -> 0.21669842 | D45: =C45-B45 -> 0.015887485 | E45: =D45/B45 -> 0.079116634 | F45: Reducción de emisiones absolutas (-37%) no proporcional a la baja de demanda (-42%) | K45: 7 | L45: Limpieza | M45: 977833304 | N45: 269.63573 | O45: =N45/$N$57 -> 0.065126194 | Q45: 0.24271678
A46: N°1:Ss computacionales (tCO2) | B46: =I31 -> 712 | C46: =O29 -> 700.76156 | D46: =C46-B46 -> -11.238437 | E46: =D46/B46 -> -0.015784322 | F46: Mayor solicitudes de soporte a plataformas o servicios. | K46: 8 | L46: Seguros | M46: 997344185 | N46: 205.80781 | O46: =N46/$N$57 -> 0.049709582 | P46: =SUM(O46:O56) -> 0.20925306 | Q46: 0.18015993
A47: N°2: Licencias (Software) (tCO2) | B47: =I22 -> 395 | C47: =O20 -> 644.25548 | D47: =C47-B47 -> 249.25548 | E47: =D47/B47 -> 0.63102653 | F47: Aumento por servicios y licencias // Efecto IPC | K47: 9 | L47: Marketing | M47: 747797840 | N47: 199.89937 | O47: =N47/$N$57 -> 0.048282492 | Q47: 0.23610625
A48: N°3: Investigación (tCO2) | B48: =I21 -> 540 | C48: =O19 -> 481.85328 | D48: =C48-B48 -> -58.146718 | E48: =D48/B48 -> -0.10767911 | F48: Aumento en investigaciones, pese a menor cantidad de proyectos (capex) aprobados | K48: 10 | L48: Arriendo de vehículos | M48: 383015502 | N48: 152.03836 | O48: =N48/$N$57 -> 0.036722431 | Q48: 0.34921655
A49: N°4: Ss. de arreglos y mantención (tCO2) | B49: =I30 -> 793 | C49: =O28 -> 447.9502 | D49: =C49-B49 -> -345.0498 | E49: =D49/B49 -> -0.43511955 | F49: Mayores inversiones en reparaciones y mejoras de instalaciones. Efecto inflacionario. Mayor uso de equipamiento operacional. | K49: 11 | L49: Vestuario | M49: 192516947 | N49: 71.655075 | O49: =N49/$N$57 -> 0.017307136 | Q49: 0.32957987
A50: N°5: Otros Servicios (tCO2) | B50: =I25 -> 397 | C50: =O24 -> 391.42414 | D50: =C50-B50 -> -5.575857 | E50: =D50/B50 -> -0.01404498 | F50: Principalmente por mayores costos de seguridad | K50: 12 | L50: Servicios varios (mantención de las oficinas, etc.) | M50: 258693810 | N50: 69.158016 | O50: =N50/$N$57 -> 0.016704011 | Q50: 0.23560118
K51: 13 | L51: Agua | M51: 116009037 | N51: 66.540675 | O51: =N51/$N$57 -> 0.016071835 | Q51: 0.49813174
A52: Factores de emisión | B52: kgCO2/USD | C52: % 2021 | D52: % 2022 | K52: 14 | L52: Mantención vehículos | M52: 299398083 | N52: 45.945911 | O52: =N52/$N$57 -> 0.011097499 | Q52: 0.13468558
A53: N°1:Servicios computacionales | B53: 0.2133242 | C53: =K31 -> 0.15549625 | D53: =Q29 -> 0.1940488 | K53: 15 | L53: Capacitaciones y entrenamientos | M53: 109318192 | N53: 29.742609 | O53: =N53/$N$57 -> 0.007183851 | Q53: 0.24537963
A54: N°2: Licencias (Software) | B54: 0.20678607 | C54: =K22 -> 0.088901903 | D54: =Q20 -> 0.18487985 | K54: 16 | L54: Servicio de reclutamiento | M54: 71884631 | N54: 17.09127 | O54: =N54/$N$57 -> 0.0041281225 | Q54: 0.23560118
A55: N°3: Investigación | B55: 0.23560118 | C55: =K21 -> 0.10861075 | D55: =Q19 -> 0.12111825 | K55: 17 | L55: Suscripciones y membresías | M55: 10827066 | N55: 4.6338227 | O55: =N55/$N$57 -> 0.0011192257 | Q55: 0.374826
A56: N°4: Mantención | B56: 0.34631562 | C56: =K30 -> 0.10660831 | D56: =Q28 -> 0.076666033 | K56: 18 | L56: Patentes | M56: 14224547 | N56: 3.8374426 | O56: =N56/$N$57 -> 0.00092687282 | Q56: 0.23560118
A57: N°5: Otros Servicios | B57: 0.24271678 | C57: =K25 -> 0.076184852 | D57: =Q24 -> 0.085106414 | L57: Total | M57: 14978136314 | N57: 4140.204 | O57: =N57/$N$57 -> 1 | P57: =O57/$N$57 -> 0.00024153399
A60: Demanda
A61: 2021 | B61: 32943152
A62: 2022 | B62: 19105834
A64: 2022 - TOTAL DE GASTO COMPAÑIA - CATEGORIZADO | H64: 2021 - TOTAL DE GASTO COMPAÑIA CON NUEVA CATEGORIZACION | O64: 2021 - TOTAL GASTO COMPAÑIA CON ANTIGUA CARACTERJZACJON
A65: Categoría interna | B65: tCO2e | C65: Total 2022 | D65: % | E65: Incluida | F65: Justificación | H65: Etiquetas de fila | I65: Suma de tCO2 2021 | J65: Suma de Total 2021 | K65: % | L65: Incluida | M65: Justificación | O65: Etiquetas de fila | P65: Suma de tCO2 2021 | Q65: Suma de Total 2021 | R65: % | S65: Incluida | T65: Justificación
A66: Gastos de personal | B66: 0 | C66: 40098072544 | D66: 0.32 | E66: No | F66: Los impactos asociados a remuneracIones y gastos del personal, se reflejan en los impactos propios de la operación (Traslado de colaboradores, residuos, compra de electricidad, entre otros). | H66: Gastos de personal | I66: 0 | J66: 41959738989 | K66: 0.27562 | L66: No | M66: Los impactos asociados a remuneracIones y gastos del personal, se reflejan en los impactos propios de la operación (Traslado de colaboradores, residuos, compra de electricidad, entre otros). | O66: Servicios | P66: =W91 -> 6614.5 | Q66: 16301080658 | R66: =Q66/$Q$81 -> 0.10726153 | S66: Si | T66: Se considera las emisiones servicios de software, servicios computacionales, telefonía, limpieza, marketing, investigación, reclutamiento, otros.
A67: Transporte local | B67: 0 | C67: 25587526511 | D67: 0.21 | E67: No | F67: Impactos considerados en categoría de distribución | H67: Transporte local | I67: 0 | J67: 39367393081 | K67: 0.25859 | L67: No | M67: Impactos considerados en categoría de distribución | O67: Transporte | P67: 0 | Q67: 49515000000 | R67: =Q67/$Q$81 -> 0.32580999 | S67: No | T67: Contabilizados en la categoría de transporte
A68: Servicio | B68: 4140 | C68: 14978136314 | D68: 0.12 | E68: Sí | F68: Se consideran las emisiones servicios de software, servicios computacionales, telefonía, limpieza, marketing, investigación, reclutamiento, entre otros. | H68: Servicio | I68: 5217 | J68: 15935039551 | K68: 0.10467 | L68: Sí | M68: Se consideran las emisiones servicios de software, servicios computacionales, telefonía, limpieza, marketing, investigación, reclutamiento, entre otros. | O68: Gastos de personal | P68: 0 | Q68: 42328000000 | R68: =Q68/$Q$81 -> 0.27851934 | S68: No | T68: Los impactos asociados a remuneracIones y gastos del personal, se reflejan en los impactos propios de la operación
A69: Western Union | B69: 0 | C69: 8914134428 | D69: 0.07 | E69: No | F69: Corresponde a gasto por comisión, se define que su impacto está contabilizado en las distintas categorías de medición (Transporte, compra de insumos, compra de lectricidad, compra de servicios, entre otras) | H69: Western Union | I69: 0 | J69: 12055030464 | K69: 0.07918 | L69: No | M69: Corresponde a gasto por comisión, se define que su impacto está contabilizado en las distintas categorías de medición (Transporte, compra de insumos, compra de lectricidad, compra de servicios, entre otras) | O69: Western Union | P69: 0 | Q69: 12055000000 | R69: =Q69/$Q$81 -> 0.079322213 | S69: No | T69: Corresponde a gasto por comisión, se define que su impacto está contabilizado en las distintas categorías de medición
A70: Comisión | B70: 0 | C70: 7644192281 | D70: 0.06 | E70: No | F70: Corresponde a gasto por comisión, se define que su impacto está contabilizado en las distintas categorías de medición (Transporte, compra de insumos, compra de lectricidad, compra de servicios, entre otras) | H70: Comisión | I70: 0 | J70: 10150638363 | K70: 0.06668 | L70: No | M70: Corresponde a gasto por comisión, se define que su impacto está contabilizado en las distintas categorías de medición (Transporte, compra de insumos, compra de lectricidad, compra de servicios, entre otras) | O70: Depreciación | P70: 0 | Q70: 6.9960001e+09 | R70: =Q70/$Q$81 -> 0.046033862 | S70: No | T70: La depreciación de los activos no se considera dentro de la contabilización, activos se encuentran en categoría bienes de capital
A71: Arriendo inmobiliario | B71: 0 | C71: 6689289021 | D71: 0.05 | E71: No | F71: Categoría opcional, con factor de emisión con alta incertidumbre, por lo que se decide no incluir para este ejercicio | H71: Arriendo inmobiliario | I71: 0 | J71: 6184628640 | K71: 0.04062 | L71: No | M71: Categoría opcional, con factor de emisión con alta incertidumbre, por lo que se decide no incluir para este ejercicio | O71: Arriendo inmobiliario | P71: 0 | Q71: 5.9380006e+09 | R71: =Q71/$Q$81 -> 0.039072198 | S71: No | T71: Categoría opcional, con factor de emisión con alta incertidumbre, por lo que se decide no incluir para este ejercicio
A72: Depreciacion | B72: 0 | C72: 4901205119 | D72: 0.04 | E72: No | F72: La depreciación de los activos no se considera dentro de la contabilización, activos se encuentran en categoría bienes de capital | H72: Transporte Aereo | I72: 0 | J72: 4926643141 | K72: 0.03236 | L72: No | M72: Impactos considerados en categoría de transporte aéreo | O72: Comisiones (PU + AE) | P72: 0 | Q72: 6417000000 | R72: =Q72/$Q$81 -> 0.042224027 | S72: No | T72: Impactos contabilizados en otras categorías de medición.
A73: Transporte Aereo | B73: 0 | C73: 3718276567 | D73: 0.03 | E73: No | F73: Impactos considerados en categoría de transporte aéreo | H73: Depreciacion | I73: 0 | J73: 4228299549 | K73: 0.02777 | L73: No | M73: La depreciación de los activos no se considera dentro de la contabilización, activos se encuentran en categoría bienes de capital | O73: Franquicias | P73: 0 | Q73: 3.9450005e+09 | R73: =Q73/$Q$81 -> 0.025958206 | S73: No | T73: Impactos contabilizados en otras categorías de medición.
A74: Transporte Troncal | B74: 0 | C74: 3579779620 | D74: 0.03 | E74: No | F74: Impactos considerados en categoría de transporte troncal | H74: Indemnización | I74: 0 | J74: 3478037259 | K74: 0.02285 | L74: No | M74: Se define que su impacto está contabilizado en las distintas categorías de medición (Transporte, compra de insumos, compra de lectricidad, compra de servicios, entre otras) | O74: Indemnización | P74: 0 | Q74: 3.5240006e+09 | R74: =Q74/$Q$81 -> 0.023188015 | S74: No | T74: Se reflejan en los impactos propios de la operación
A75: Personal Externo | B75: 0 | C75: 1805295166 | D75: 0.01 | E75: No | F75: Los impactos asociados a remuneracIones y gastos del personal, se reflejan en los impactos propios de la operación (Traslado de colaboradores, residuos, compra de electricidad, entre otros). | H75: Transporte Troncal | I75: 0 | J75: 3149891560 | K75: 0.02069 | L75: No | M75: Impactos considerados en categoría de transporte troncal | O75: Personal Externo | P75: 0 | Q75: 2395000000 | R75: =Q75/$Q$81 -> 0.015759162 | S75: No | T75: Se reflejan en los impactos propios de la operación
A76: Transporte propio | B76: 0 | C76: 1753316608 | D76: 0.01 | E76: No | F76: Impactos asociados a esta categoría, están contabilizados en la cateogría de transporte troncal y distribución | H76: Personal Externo | I76: 0 | J76: 2642593692 | K76: 0.01736 | L76: No | M76: Los impactos asociados a remuneracIones y gastos del personal, se reflejan en los impactos propios de la operación (Traslado de colaboradores, residuos, compra de electricidad, entre otros). | O76: Ajuste Contable/financiero | P76: 0 | Q76: 1738000000 | R76: =Q76/$Q$81 -> 0.011436085 | S76: No | T76: No se considera
A77: Indemnización | B77: 0 | C77: 1668324684 | D77: 0.01 | E77: No | F77: Corresponde a gasto por comisión, se define que su impacto está contabilizado en las distintas categorías de medición (Transporte, compra de insumos, compra de lectricidad, compra de servicios, entre otras) | H77: Transporte propio | I77: 0 | J77: 2512055231 | K77: 0.0165 | L77: No | M77: Impactos asociados a esta categoría, están contabilizados en la cateogría de transporte troncal y distribución | O77: Otros | P77: 0 | Q77: 3.0080007e+09 | R77: =Q77/$Q$81 -> 0.019792723 | S77: No | T77: Se reflejan en los impactos propios de la operación
A78: Insumos Operacionales y comerciales | B78: 0 | C78: 928191981 | D78: 0.01 | E78: No | F78: Los impactos contabilizados en esta categoría,están contabilizados de acuerdo a su materialidad (Categoría de insumos operacionales) | H78: Insumos Operacionales y comerciales | I78: 0 | J78: 1570435687 | K78: 0.01032 | L78: No | M78: Los impactos contabilizados en esta categoría,están contabilizados de acuerdo a su materialidad (Categoría de insumos operacionales) | O78: Insumos Operacionales | P78: 0 | Q78: 1.5700004e+09 | R78: =Q78/$Q$81 -> 0.010330644 | S78: No | T78: Los impactos contabilizados en esta categoría,están contabilizados de acuerdo a su materialidad
... A80: Compra embalaje | B80: 0 | C80: 538212815 | D80: 0 | E80: No | F80: Los impactos contabilizados en esta categoría,están contabilizados de acuerdo a su materialidad (Categoría de empaques) | H80: Otros | I80: 0 | J80: 1056679791 | K80: 0.00694 | L80: No | M80: Se reflejan en los impactos propios de la operación (fuentes fijas, viajes de negocio, entre otros.) | O80: Arriendo NIIF | P80: 0 | Q80: -4687000000 | R80: =Q80/$Q$81 -> -0.030840582 | S80: No | T80: No se considera
A81: Electricidad | B81: 0 | C81: 437258093 | D81: 0 | E81: No | F81: Los impactos contabilizados en esta categoría,están contabilizados de acuerdo a su consumo electrico (kWh) | H81: Compra embalaje | I81: 0 | J81: 932765168 | K81: 0.00613 | L81: No | M81: Los impactos contabilizados en esta categoría,están contabilizados de acuerdo a su materialidad (Categoría de empaques) | O81: . | Q81: =SUM(Q66:Q80) -> 1.5197508e+11 | R81: =SUM(R66:R80) -> 1
A82: Gestión de residuos | B82: 0 | C82: 293906701 | D82: 0 | E82: No | F82: Los impactos contabilizados en esta categoría,están contabilizados de acuerdo a su generación y tratamiento | H82: Electricidad | I82: 0 | J82: 405401935 | K82: 0.00266 | L82: No | M82: Los impactos contabilizados en esta categoría,están contabilizados de acuerdo a su consumo electrico (kWh) | O82: .
A83: Directorio | B83: 0 | C83: 186978000 | D83: 0 | E83: No | F83: se define que su impacto está contabilizado en las distintas categorías de medición (Transporte, compra de insumos, compra de lectricidad, compra de servicios, entre otras) | H83: Gestión de residuos | I83: 0 | J83: 193509093 | K83: 0.00127 | L83: No | M83: Los impactos contabilizados en esta categoría,están contabilizados de acuerdo a su generación y tratamiento | O83: .
A84: Pago proveedores | B84: 0 | C84: 4250932 | D84: 0 | E84: No | F84: Se define que su impacto está contabilizado en las distintas categorías de medición (Transporte, compra de insumos, compra de lectricidad, compra de servicios, entre otras) | H84: Ajuste Contable/financiero | I84: 0 | J84: 7981776 | K84: 5e-05 | L84: No | M84: Se define que su impacto está contabilizado en las distintas categorías de medición (Transporte, compra de insumos, compra de lectricidad, compra de servicios, entre otras) | O84: ..
A85: Ajuste Contable/financiero | B85: 0 | C85: -19070436 | D85: 0 | E85: No | F85: Se define que su impacto está contabilizado en las distintas categorías de medición (Transporte, compra de insumos, compra de lectricidad, compra de servicios, entre otras) | H85: Pago proveedores | I85: 0 | J85: 6347174 | K85: 4e-05 | L85: No | M85: Se define que su impacto está contabilizado en las distintas categorías de medición (Transporte, compra de insumos, compra de lectricidad, compra de servicios, entre otras) | O85: .
B86: =SUM(B66:B85) -> 4140 | C86: =SUM(C66:C85) -> 124476621581 | D86: =SUM(D66:D85) -> 0.98 | H86: Total | I86: =SUM(I66:I85) -> 5217 | J86: =SUM(J66:J85) -> 152240110144 | K86: =SUM(K66:K85) -> 1
W90: =W91-O91 -> 1397.4
A91: 2022 | E91: =+SUM(E93:E167) -> 14978136314 | F91: =-SUM(F93:F167) -> 17152518 | G91: =+SUM(G93:G167) -> 4140.204 | I91: 2021 - TOTAL DE CUENTAS (CON NUEVA CATEGORIZACION) | M91: =SUM(M93:M167) -> 15935039551 | N91: =SUM(N93:N167) -> 21276271 | O91: =SUM(O93:O167) -> 5217.1 | Q91: 2021 - TOTAL DE CUENTAS (CON ANTIGUA CATEGORIZACION) | U91: =SUM(U93:U215) -> 16318682496 | V91: =SUM(V93:V215) -> 21477050 | W91: =SUM(W93:W215) -> 6614.5 | X91: 1.000 por recategorizacion de articulos de aseo a servicios en vez de productos plasticos, 400 se contabilizan en transporte (repuestos y correspondencia reparto y retiro)
A92: N° de cuenta | B92: Descripción cuenta | C92: Tipo de Bien o Servicio | D92: Categoría - Exiobase | E92: Gasto anual (Pesos chilenos) | F92: USD | G92: ton CO2-e | I92: N° de cuenta | J92: Descripción cuenta | K92: Tipo de Bien o Servicio | L92: Categoría - Exiobase | M92: Gasto anual (Pesos chilenos) | N92: USD | O92: ton CO2-e | Q92: N° de cuenta | R92: Descripción cuenta | S92: Tipo de Bien o Servicio | T92: Categoría - Exiobase | U92: Gasto anual (Pesos chilenos) | V92: USD | W92: ton CO2-e
A93: 526104 | B93: MANTENCION COMPUTACI | C93: Servicios | D93: Servicios computacionales | E93: 1539609287 | F93: -1742167.9 | G93: =-F93*VLOOKUP(D93,'Factores Emisión EDGE'!$K$168:$L$203,2,FALSE)/1000 -> 371.64657 | I93: 526710 | J93: SER.EXTE.CALL CENTER | K93: Servicio | L93: Telefonía e internet | M93: 1422970115 | N93: 1913419 | O93: 633.37 | P93: =VLOOKUP(Q93,$I$93:$I$167,1,0) -> 526501 | Q93: 526501 | R93: ASEO OFICINAS Y ORNATO | S93: Servicios | T93: Limpieza | U93: 1401265776 | V93: 1846038 | W93: 448.1
A94: 565601 | B94: ASES. PROFESIONALES | C94: Servicios | D94: Investigación | E94: 1325438043 | F94: -1515701.1 | G94: =-F94*VLOOKUP(D94,'Factores Emisión EDGE'!$K$168:$L$203,2,FALSE)/1000 -> 350.88055 | I94: 526501 | J94: ASEO OFICINAS | K94: Servicio | L94: Limpieza | M94: 1530047367 | N94: 2020752 | O94: 490.47 | P94: =VLOOKUP(Q94,$I$93:$I$167,1,0) -> 526710 | Q94: 526710 | R94: SERVICIOS EXTERN.CALL CENTER | S94: Servicios | T94: Telefonía e internet | U94: 1301403052 | V94: 1779174 | W94: 585
A95: 526710 | B95: SER.EXTE.CALL CENTER | C95: Servicios | D95: Telefonía e internet | E95: 716546125 | F95: -825732.73 | G95: =-F95*VLOOKUP(D95,'Factores Emisión EDGE'!$K$168:$L$203,2,FALSE)/1000 -> 273.33141 | I95: 565601 | J95: ASES. PROFESIONALES | K95: Servicio | L95: Investigación | M95: 1188378574 | N95: 1575318 | O95: 364.68 | P95: =VLOOKUP(Q95,$I$93:$I$167,1,0) -> 565601 | Q95: 565601 | R95: ASESORIAS PROFESIONALES | S95: Servicios | T95: Investigación | U95: 1079619198 | V95: 1422298 | W95: 329.3
A96: 526103 | B96: MANTENCION LICENCIAS | C96: Servicios | D96: Licencias (Software) | E96: 1132508415 | F96: -1266043.7 | G96: =-F96*VLOOKUP(D96,'Factores Emisión EDGE'!$K$168:$L$203,2,FALSE)/1000 -> 261.80021 | I96: 526502 | J96: SEGURIDAD Y ORNATO | K96: Servicio | L96: Otros servicios | M96: 980541648 | N96: 1301093 | O96: 315.8 | P96: =VLOOKUP(Q96,$I$93:$I$167,1,0) -> 526104 | Q96: 526104 | R96: MANTENCION COMPUTACION | S96: Servicios | T96: Servicios Computacionales | U96: 962518568 | V96: 1268029 | W96: 270.5
A97: 565201 | B97: MANT. COMPUTACION | C97: Servicios | D97: Servicios computacionales | E97: 1012669661 | F97: -1146861.1 | G97: =-F97*VLOOKUP(D97,'Factores Emisión EDGE'!$K$168:$L$203,2,FALSE)/1000 -> 244.65323 | I97: 526104 | J97: MANTENCION COMPUTACI | K97: Servicio | L97: Servicios computacionales | M97: 1074845826 | N97: 1422373 | O97: 303.43 | P97: =VLOOKUP(Q97,$I$93:$I$167,1,0) -> 526502 | Q97: 526502 | R97: SEGURIDAD | S97: Servicios | T97: Otros servicios | U97: 912218843 | V97: 1216255 | W97: 295.2
A98: 526553 | B98: REPARACION OFICINAS | C98: Servicios | D98: Servicios Arreglos / mantención oficinas - arquitectos, maestros | E98: 611166475 | F98: -687749.5 | G98: =-F98*VLOOKUP(D98,'Factores Emisión EDGE'!$K$168:$L$203,2,FALSE)/1000 -> 238.1784 | I98: 526103 | J98: MANTENCION LICENCIAS | K98: Servicio | L98: Licencias (Software) | M98: 910525063 | N98: 1201235 | O98: 248.4 | P98: =VLOOKUP(Q98,$I$93:$I$167,1,0) -> 526103 | Q98: 526103 | R98: MANTENCION LICENCIAS SW | S98: Servicios | T98: Licencias (softwares) | U98: 836778661 | V98: 1102378 | W98: 228
A99: 526501 | B99: ASEO OFICINAS | C99: Servicios | D99: Limpieza | E99: 842229158 | F99: -956779.42 | G99: =-F99*VLOOKUP(D99,'Factores Emisión EDGE'!$K$168:$L$203,2,FALSE)/1000 -> 232.22642 | I99: 565201 | J99: MANT. COMPUTACION | K99: Servicio | L99: Servicios computacionales | M99: 853406083 | N99: 1135151 | O99: 242.16 | P99: =VLOOKUP(Q99,$I$93:$I$167,1,0) -> 565201 | Q99: 565201 | R99: MANTENCION COMPUTACION | S99: Servicios | T99: Servicios Computacionales | U99: 810792454 | V99: 1068144 | W99: 227.9
A100: 526502 | B100: SEGURIDAD Y ORNATO | C100: Servicios | D100: Otros servicios | E100: 746800557 | F100: -846383.57 | G100: =-F100*VLOOKUP(D100,'Factores Emisión EDGE'!$K$168:$L$203,2,FALSE)/1000 -> 205.43149 | I100: 526553 | J100: REPARACION OFICINAS | K100: Servicio | L100: Servicios Arreglos / mantención oficinas - arquitectos, maestros | M100: 504205189 | N100: 665950 | O100: 230.63 | P100: =VLOOKUP(Q100,$I$93:$I$167,1,0) -> 526105 | Q100: 526105 | R100: OPEX PROYECTOS TI | S100: Servicios | T100: Investigación | U100: 544274755 | V100: 717032 | W100: 166
A101: 565202 | B101: MANT. LICENCIAS SW | C101: Servicios | D101: Licencias (Software) | E101: 738909910 | F101: -833159.87 | G101: =-F101*VLOOKUP(D101,'Factores Emisión EDGE'!$K$168:$L$203,2,FALSE)/1000 -> 172.28586 | I101: 525502 | J101: OTROS ARRIENDOS | K101: Servicio | L101: Arriendo de vehículos | M101: 457795430 | N101: 603812 | O101: 210.86 | P101: =VLOOKUP(Q101,$I$93:$I$167,1,0) -> 526553 | Q101: 526553 | R101: REPARACION OFICINAS | S101: Servicios | T101: Servicios Arreglos / mantención oficinas - arquitectos, maestros | U101: 504861381 | V101: 665108 | W101: 230.3
A102: 526101 | B102: MEDIOS DE COMUNICAC. | C102: Servicios | D102: Licencias (Software) | E102: 630057437 | F102: -712860.15 | G102: =-F102*VLOOKUP(D102,'Factores Emisión EDGE'!$K$168:$L$203,2,FALSE)/1000 -> 147.40955 | I102: 526105 | J102: OPEX PROYECTOS TI | K102: Servicio | L102: Investigación | M102: 544274755 | N102: 777877 | O102: 180.08 | P102: =VLOOKUP(Q102,$I$93:$I$167,1,0) -> #N/A | Q102: 525201 | R102: CORREO EXTERNO | S102: Servicios | T102: Telefonía e internet | U102: 487754178 | V102: 642571 | W102: 212.7 | X102: Se contabliza en transporte local (reparto y retiro)
A103: 567102 | B103: PUBLICIDAD MEDIOS | C103: Servicios | D103: Marketing | E103: 487654723 | F103: -556631.3 | G103: =-F103*VLOOKUP(D103,'Factores Emisión EDGE'!$K$168:$L$203,2,FALSE)/1000 -> 131.42413 | I103: 565202 | J103: MANT. LICENCIAS SW | K103: Servicio | L103: Licencias (Software) | M103: 538672025 | N103: 710931 | O103: 147.01 | P103: =VLOOKUP(Q103,$I$93:$I$167,1,0) -> 565202 | Q103: 565202 | R103: MANTENCION LICENCIAS SW | S103: Servicios | T103: Licencias (softwares) | U103: 485795264 | V103: 639490 | W103: 132.3
A104: 525502 | B104: OTROS ARRIENDOS | C104: Servicios | D104: Arriendo de vehículos | E104: 327712656 | F104: -372503.88 | G104: =-F104*VLOOKUP(D104,'Factores Emisión EDGE'!$K$168:$L$203,2,FALSE)/1000 -> 130.08452 | I104: 526602 | J104: GASTOS DE MANTENCION | K104: Servicio | L104: Servicios Arreglos / mantención oficinas - arquitectos, maestros | M104: 297660535 | N104: 388668 | O104: 134.6 | P104: =VLOOKUP(Q104,$I$93:$I$167,1,0) -> 526101 | Q104: 526101 | R104: MEDIOS DE COMUNICACION | S104: Servicios | T104: Marketing | U104: 434649547 | V104: 572611 | W104: 135.2
A105: 526602 | B105: GASTOS DE MANTENCION | C105: Servicios | D105: Servicios Arreglos / mantención oficinas - arquitectos, maestros | E105: 331967855 | F105: -374685.99 | G105: =-F105*VLOOKUP(D105,'Factores Emisión EDGE'!$K$168:$L$203,2,FALSE)/1000 -> 129.75961 | I105: 567101 | J105: PUBLIC. CORPORATIVO | K105: Servicio | L105: Marketing | M105: 422040101 | N105: 547551 | O105: 129.28 | P105: =VLOOKUP(Q105,$I$93:$I$167,1,0) -> 567101 | Q105: 567101 | R105: PUBLICIDAD CORPORATIVO | S105: Servicios | T105: Marketing | U105: 388932381 | V105: 512382 | W105: 121
A106: 521202 | B106: VESTUARIO | C106: Servicios | D106: Vestuario | E106: 224776934 | F106: -253653.31 | G106: =-F106*VLOOKUP(D106,'Factores Emisión EDGE'!$K$168:$L$203,2,FALSE)/1000 -> 83.599023 | I106: 526101 | J106: MEDIOS DE COMUNICAC. | K106: Servicio | L106: Licencias (Software) | M106: 465193582 | N106: 616559 | O106: 127.5 | P106: =VLOOKUP(Q106,$I$93:$I$167,1,0) -> 526552 | Q106: 526552 | R106: SEGUROS | S106: Servicios | T106: Seguros | U106: 344730104 | V106: 454158.62 | W106: 81.8
A107: 565603 | B107: INVESTIGA.DE MERCADO | C107: Servicios | D107: Investigación | E107: 298816333 | F107: -338718.43 | G107: =-F107*VLOOKUP(D107,'Factores Emisión EDGE'!$K$168:$L$203,2,FALSE)/1000 -> 78.412365 | I107: 565203 | J107: DESARROLLO COMPUTACI | K107: Servicio | L107: Servicios Computacionales | M107: 457445111 | N107: 583109 | O107: 124.39 | P107: =VLOOKUP(Q107,$I$93:$I$167,1,0) -> 565203 | Q107: 565203 | R107: DESARROLLO COMPUTACION | S107: Servicios | T107: Servicios Computacionales | U107: 334443087 | V107: 440598 | W107: 94
A108: 526601 | B108: CONTRATOS DE MANTENC | C108: Servicios | D108: Servicios Arreglos / mantención oficinas - arquitectos, maestros | E108: 198311342 | F108: -224034.76 | G108: =-F108*VLOOKUP(D108,'Factores Emisión EDGE'!$K$168:$L$203,2,FALSE)/1000 -> 77.586735 | I108: 521901 | J108: ELEM PROTEC PERSONAL | K108: Servicio | L108: Servicios varios (mantención de las oficinas, etc.) | M108: 276479621 | N108: 382274 | O108: 90.06 | P108: =VLOOKUP(Q108,$I$93:$I$167,1,0) -> 525902 | Q108: 525902 | R108: MANTENC.Y REPAR.VEHICULOS | S108: Servicios | T108: Servicios Arreglos / mantención oficinas - arquitectos, maestros | U108: 326760274 | V108: 430476 | W108: 149.1 | X108: pasa a transporte
A109: 526552 | B109: SEGUROS | C109: Servicios | D109: Seguros | E109: 370981087 | F109: -417667.64 | G109: =-F109*VLOOKUP(D109,'Factores Emisión EDGE'!$K$168:$L$203,2,FALSE)/1000 -> 75.246973 | I109: 526552 | J109: SEGUROS | K109: Servicio | L109: Seguros | M109: 344730104 | N109: 454588 | O109: 81.9 | P109: =VLOOKUP(Q109,$I$93:$I$167,1,0) -> 521106 | Q109: 521106 | R109: SEGURO DE INVALIDEZ | S109: Servicios | T109: Seguros | U109: 309381919 | V109: 407582 | W109: 73.4
A110: 565303 | B110: MEDIOS DE COMUN. ADM | C110: Servicios | D110: Licencias (Software) | E110: 267679791 | F110: -303501.42 | G110: =-F110*VLOOKUP(D110,'Factores Emisión EDGE'!$K$168:$L$203,2,FALSE)/1000 -> 62.759865 | I110: 521106 | J110: SEGURO DE INVALIDEZ | K110: Servicio | L110: Seguros | M110: 309381919 | N110: 408505 | O110: 73.6 | P110: =VLOOKUP(Q110,$I$93:$I$167,1,0) -> 526602 | Q110: 526602 | R110: GASTOS DE MANTENCION | S110: Servicios | T110: Servicios Arreglos / mantención oficinas - arquitectos, maestros | U110: 297660535 | V110: 392140 | W110: 135.8
A111: 526401 | B111: AGUA | C111: Servicios | D111: Agua | E111: 104631096 | F111: -120456.04 | G111: =-F111*VLOOKUP(D111,'Factores Emisión EDGE'!$K$168:$L$203,2,FALSE)/1000 -> 60.002978 | I111: 526401 | J111: AGUA | K111: Servicio | L111: Agua | M111: 109964105 | N111: 146654 | O111: 73.05 | P111: =VLOOKUP(Q111,$I$93:$I$167,1,0) -> 521901 | Q111: 521901 | R111: ELEM. PROTECCION PERSONAL | S111: Servicios | T111: Vestuario | U111: 280629726 | V111: 369704 | W111: 121.8
A112: 567101 | B112: PUBLIC. CORPORATIVO | C112: Servicios | D112: Marketing | E112: 212073514 | F112: -237540.06 | G112: =-F112*VLOOKUP(D112,'Factores Emisión EDGE'!$K$168:$L$203,2,FALSE)/1000 -> 56.084693 | I112: 526555 | J112: REMOZAMIENTO OFICINA | K112: Servicio | L112: Servicios Arreglos / mantención oficinas - arquitectos, maestros | M112: 160916705 | N112: 209747 | O112: 72.64 | P112: =VLOOKUP(Q112,$I$93:$I$167,1,0) -> 521105 | Q112: 521105 | R112: SEGURO DE DESEMPLEO | S112: Servicios | T112: Seguros | U112: 267172127 | V112: 251975 | W112: 63.4
A113: 526105 | B113: OPEX PROYECTOS TI | C113: Servicios | D113: Investigación | E113: 189871305 | F113: -227045.38 | G113: =-F113*VLOOKUP(D113,'Factores Emisión EDGE'!$K$168:$L$203,2,FALSE)/1000 -> 52.560367 | I113: 525902 | J113: MANT.Y REP.VEHICULOS | K113: Servicio | L113: Mantención vehículos | M113: 358274307 | N113: 474194 | O113: 63.87 | P113: =VLOOKUP(Q113,$I$93:$I$167,1,0) -> #N/A | Q113: 526572 | R113: PATENTES COMERCIALES | S113: Servicios | T113: Patentes | U113: 185632860 | V113: 244554 | W113: 57.6
A114: 521106 | B114: SEGURO DE INVALIDEZ | C114: Servicios | D114: Seguros | E114: 252304422 | F114: -288899.43 | G114: =-F114*VLOOKUP(D114,'Factores Emisión EDGE'!$K$168:$L$203,2,FALSE)/1000 -> 52.048102 | I114: 526601 | J114: CONTRATOS DE MANTENC | K114: Servicio | L114: Servicios Arreglos / mantención oficinas - arquitectos, maestros | M114: 138880309 | N114: 181780 | O114: 62.95 | P114: =VLOOKUP(Q114,$I$93:$I$167,1,0) -> 562105 | Q114: 562105 | R114: SEGURO DE DESEMPLEO | S114: Servicios | T114: Seguros | U114: 170138400 | V114: 224142 | W114: 40.4
A115: 565106 | B115: SEGURIDAD Y ORNATO | C115: Servicios | D115: Otros servicios | E115: 178273471 | F115: -200412.34 | G115: =-F115*VLOOKUP(D115,'Factores Emisión EDGE'!$K$168:$L$203,2,FALSE)/1000 -> 48.643438 | I115: 521105 | J115: SEGURO DE DESEMPLEO | K115: Servicio | L115: Seguros | M115: 267172127 | N115: 346373 | O115: 62.4 | P115: =VLOOKUP(Q115,$I$93:$I$167,1,0) -> 565303 | Q115: 565303 | R115: MEDIOS DE COMUN. ADM | S115: Servicios | T115: Marketing | U115: 155441509 | V115: 204780 | W115: 48.3
...

Sheet 6. Traslado colaboradores
A1: Descripción del cálculo
A2: 1 | B2: Objetivo | C2: Medir las emisiones de carbono del traslado de colaboradores entre sus domicilios y lugares dede trabajo
A3: 1 | B3: Alcance | C3: Colaboradores propios + colaboradores externos (Subcontrataley y Empresas de Servicios Transitorios) de Chilexpress
A4: 2 | B4: Periodo | C4: Año 2022
A5: 3 | B5: Fuentes de información para realizar la medición | C5: Encuesta de hábitos de transporte realizada a colaboradores propios + externos Dotación de chilexpress aperturada por categoria de funciones
A6: 4 | B6: Metodología de cálculo | C6: Encuesta de hábitos de transporte para obtener - Distancia recorrida al año por colaboradores - Medio de transporte - Modalidad de trabajo (% de teletrabajo) - días trabajados al año - Factor de emisión de acuerdo al medio de transporte aplicado a distancia recorrida y y días trabajados al año Extrapolación de resultados de acuerdo a totalidad de dotación mensual Se excluyen de la medición los colaboradores externos que prestan servicio de: - Transporte - Limpieza - Seguridad - Reciclaje - Digitación - TI La exclusion de estos colaboradores se debe a que el impacto asociado a su traslado o kilometros recorridos se encuentra contabilizado en las categorías de emisión donde se paga su servicio
A7: 5 | B7: Responsables | C7: Control de gestión y análitica, dirección de personas
A10: Traslado de Colaboradores 2022
A11: Distancia promedio ida-regreso por colaborador | B11: Modalidad de trabajo | C11: % Modalidad de trabajo | D11: Metodo de transporte | E11: % Metodo de transporte | F11: Factor de emisión por metodo de transporte | G11: N° Respuestas encuestas | H11: Toneladas CO2 de N° Respuestas | I11: Cantidad colaboradores promedio año | J11: Kilometros recorridos | K11: Km/dia/colaborador | L11: ton CO2-e
B12: 100% presencial | C12: 0.60818 | D12: Auto | E12: 0.58433 | F12: 0.34 | G12: 587 | H12: 758 | I12: 2515 | J12: 14005189 | K12: =J12/237/I12 -> 23.496471 | L12: 3248
B13: 100% Teletebajo / 0% presencial | C13: 0.08859 | D13: Bus | E13: 0.23509 | F13: 0.01
B14: 20% Teletrabajo /80% presencial | C14: 0.02555 | D14: No utiliza | E14: 0.08859 | F14: 0.11
B15: 40% Teletrabajo / 60% presencial | C15: 0.08007 | D15: Bicicleta | E15: 0.06824 | F15: 0.01
B16: 60% Teletrabajo / 40% presencial | C16: 0.10221 | D16: Moto | E16: 0.01533 | F16: 0
B17: 80% Teletrabajo / 20% presencial | C17: 0.0954 | D17: Vehículo eléctrico | E17: 0.0051 | F17: 0
D18: Moto eléctrica | E18: 0.0033 | F18: 0
C19: =SUM(C12:C18) -> 1 | E19: =SUM(E12:E18) -> 0.99998
A22: Traslado de Colaboradores 2021
A23: Distancia promedio ida-regreso por colaborador | B23: Modalidad de trabajo | C23: % Modalidad de trabajo | D23: Metodo de transporte | E23: % Metodo de transporte | F23: Factor de emisión por metodo de transporte | G23: N° Respuestas encuestas | H23: Toneladas CO2 de N° Respuestas | I23: Cantidad colaboradores promedio año | J23: Kilometros recorridos | K23: Km/dia/colaborador | L23: ton CO2-e
B24: 100% trabajo presencial | C24: 0.587 | D24: Auto | E24: 0.5034 | F24: 0.34 | G24: 741 | H24: 1032 | I24: 3176 | J24: 20738287 | K24: =J24/237/I24 -> 27.551423 | L24: 4424
B25: 100% teletrabajo / 0% presencial | C25: 0.1997 | D25: Bus | E25: 0.2537 | F25: 0.01
B26: 75% teletrabajo / 25% presencial | C26: 0.1107 | D26: No Utiliza | E26: 0.1997 | F26: 0.11
B27: 50% teletrabajo | C27: 0.0553 | D27: Bicicleta | E27: 0.0243 | F27: 0.01
B28: 25% teletrabajo /75% presencial | C28: 0.0472 | D28: Moto | E28: 0.0189 | F28: 0.12
C29: =SUM(C24:C28) -> 0.9999 | E29: =SUM(E24:E28) -> 1
A34: Indicadores de la Categoria de Negocio
A35: Nombre Indicador | B35: Descripción | C35: unidad | D35: 2021 | E35: 2022 | F35: Dif | G35: Principales Diferencias
A36: Presencialidad | B36: 100% presencial | C36: % | D36: =C24 -> 0.587 | E36: =C12 -> 0.60818 | F36: =E36-D36 -> 0.02118 | G36: Aumenta un 2,1% el formato 100% presencial
B37: 100% Teletebajo | C37: % | D37: =C25 -> 0.1997 | E37: =C13 -> 0.08859 | F37: =E37-D37 -> -0.11111 | G37: Disminuye un 55,64% el formato 100% teletrabajo
B38: 20% Teletrabajo (4 días a la semana) | C38: % | D38: =C28 -> 0.0472 | E38: =C14 -> 0.02555 | F38: =E38-D38 -> -0.02165 | G38: Disminuye un 48,87% el formato 20% teletrabajo
B39: 40% Teletrabajo (3 días a la semana) | C39: % | D39: =C27 -> 0.0553 | E39: =C15 -> 0.08007 | F39: =E39-D39 -> 0.02477 | G39: Disminuye un 44,79% el formato 40% teletrabajo
B40: 80% Teletrabajo (1 día a la semana) | C40: % | D40: =C26 -> 0.1107 | E40: =C17+C16 -> 0.19761 | F40: =E40-D40 -> 0.08691 | G40: Disminuye un 78,51% el formato 80% teletrabajo
A41: Medios de transporte | B41: Auto | C41: % | D41: =E24 -> 0.5034 | E41: =E12 -> 0.58433 | F41: =E41-D41 -> 0.08093 | G41: Aumenta un 16,08% el medio de transporte auto
B42: Bus | C42: % | D42: =E25 -> 0.2537 | E42: =E13 -> 0.23509 | F42: =E42-D42 -> -0.01861 | G42: Disminuye un 7,34% el medio de transporte bus o transporte público
B43: No utiliza | C43: % | D43: =E26 -> 0.1997 | E43: =E14 -> 0.08859 | F43: =E43-D43 -> -0.11111 | G43: Disminuye un 55,64% los colaboradores que no utilizan medio de transporte
B44: Bicicleta | C44: % | D44: =E27 -> 0.0243 | E44: =E15 -> 0.06824 | F44: =E44-D44 -> 0.04394 | G44: Aumenta un 180,82% el uso de la bicicleta o caminando
B45: Moto | C45: % | D45: =E28 -> 0.0189 | E45: =E16 -> 0.01533 | F45: =E45-D45 -> -0.00357 | G45: Disminuye un 18,89% los colaboradores que no utilizan moto
B46: Vehículo eléctrico | C46: % | D46: 0 | E46: =E17 -> 0.0051 | F46: 0 | G46: Se incorpora esta alternativa en 2022
B47: Moto eléctrica | C47: % | D47: =0 -> 0 | E47: =E18 -> 0.0033 | F47: 0 | G47: Se incorpora esta alternativa en 2022
B48: Kilometros por colaborador promedio | C48: % | D48: =J24/I24 -> 6529.6873 | E48: =J12/I12 -> 5568.6636 | F48: =(E48-D48)/D48 -> -0.1471776 | G48: Disminuye un 14,72% loskilometros recorridos por colaborador
B49: % de respuesta encuesta | C49: % | D49: =G24/I24 -> 0.23331234 | E49: =G12/I12 -> 0.2333996 | F49: =(E49-D49)/D49 -> 0.00037400429 | G49: El % de respuesta considerandolos colaboradores presenta diferencias relevantes
A53: Resumen
B54: 2021 | C54: 2022 | D54: Diferencia | E54: Dif % | F54: Justificación
A55: % presencialidad | B55: =(100*C24+ 0*C25+ 25*C26+ 50*C27+ 75*C28)% -> 0.677725 | C55: =(100*C12+ 0*C13+ 80*C14 + 60*C15+ 40*C16 + 20*C17) % -> 0.736626 | D55: =C55-B55 -> 0.058901 | E55: =D55/B55 -> 0.086909882 | F55: Aumento de presencialidad
A56: km/dia/colaborador | B56: =K24 -> 27.551423 | C56: =K12 -> 23.496471 | D56: =C56-B56 -> -4.0549524 | E56: =D56/B56 -> -0.1471776 | F56: Disminución de distancia recorrida (declarada en encuesta) (distancia efectivamente recorrida segun presencialidad/teletrabajo)
A57: % auto | B57: =D41 -> 0.5034 | C57: =E41 -> 0.58433 | D57: =C57-B57 -> 0.08093 | E57: =D57 -> 0.08093 | F57: Aumento de uso de auto por sobre otros medios de transporte
A58: kgco2/colaborador/dia | B58: =L24*1000/I24/237 -> 5.8774139 | C58: =L12*1000/I12/237 -> 5.4491616 | D58: =C58-B58 -> -0.42825237 | E58: =D58/B58 -> -0.072864081 | F58: 1) Disminución de distancia recorrida (declarada) por colaborador (-15%) 2) Aumento de presencialidad (+9%) 3) Aumento de uso del auto por sobre otros medios de transporte (+8%)
A59: cantidad colaboradores | B59: =I24 -> 3176 | C59: =I12 -> 2515 | D59: =C59-B59 -> -661 | E59: =D59/B59 -> -0.20812343
A60: emision CO2 | B60: =L24 -> 4424 | C60: =L12 -> 3248 | D60: =C60-B60 -> -1176 | E60: =D60/B60 -> -0.26582278 | F60: 1) Menor base de colaboradores (-20%) 2) Menor distancia recorrida por dia (declarada) por colaborador (-7%)
A61: kgco2/pieza | B61: =B60*1000/B75 -> 0.13429195 | C61: =C60*1000/B76 -> 0.17000043 | D61: =C61-B61 -> 0.035708484 | E61: =D61/B61 -> 0.2659019 | F61: Reducción de emisiones totales (-27%) no proporcinal a la baja de demanda (-42%)
A64: Factores de emisión
A65: Medio de transporte | B65: Factor de emisión | C65: Unidad de medida
A66: Auto | B66: 0.33545771 | C66: kg CO2e/personkm
A67: Moto | B67: 0.12418301 | C67: kg CO2e/personkm
A68: Bus | B68: 0.10659823 | C68: kg CO2e/personkm
A69: Tren | B69: 0.077078425 | C69: kg CO2e/personkm
A70: Bicicleta | B70: 0.011280857 | C70: kg CO2e/personkm
A74: Demanda
A75: 2021 | B75: 32943152
A76: 2022 | B76: 19105834

Sheet 7. Energia Electrica
A1: CONSUMO DE ELECTRICIDAD
B3: Por favor llene la siguiente información sobre el consumo de electricidad en sus instalaciones durante el año calendario 2021. | N3: Demanda
N4: 2021 | O4: 32943152
N5: 2022 | O5: 19105834
B6: TIPO DE RESPALDOS: | C6: Facturas, registros internos de consumo, SAP u otros.
B7: Recomendación: | C7: En el caso de no contar con información de ciertas instalaciones, dejar en blanco la casilla de consumo (se extrapolará dependiendo la ubicación, metraje, tipo de unidad operativa y ubicación).
I8: =+SUM(I11:I241) -> 4917011 | K8: =+SUM(K11:K241) -> 1073.2022 | L8: =SUM(L11:L241) -> 270.57411 | N8: 2021 | U8: 2022
B9: 2022 | K9: Directas | L9: Indirectas | N9: Resumen | O9: Q | P9: kWh | Q9: Directas | R9: Indirectas | S9: Total emisiones | U9: Resumen | V9: Q | W9: kWh | X9: Directas | Y9: Indirectas | Z9: Total emisiones | AB9: kwh
A10: Q | B10: Unidad operativa | C10: Nombre sucursal | D10: Región | E10: Comuna | F10: Zona | G10: Tipo de electricidad | H10: Cantidad | I10: Unidad | J10: Matriz | K10: ton CO2-e | L10: ton CO2-e | Q10: ton CO2-e | R10: ton CO2-e | X10: ton CO2-e | Y10: ton CO2-e | AB10: Variación
A11: 1 | B11: CD | C11: ENEA EXPRESS | D11: METROPOLITANA DE SANTIAGO | E11: PUDAHUEL | F11: Rm | G11: Cliente libre (no renovable) | H11: Kwh | I11: 925454 | J11: SEN | K11: 0 | L11: =(I11*0.055028169)/1000 -> 50.926039 | N11: CD | O11: 30 | P11: 3325689 | Q11: 728 | R11: 183 | S11: =R11+Q11 -> 911 | U11: CD | V11: 28 | W11: =+SUMIF($B$11:$B$241,$U11,I$11:I$241) -> 3106938.9 | X11: =+SUMIF($B$11:$B$241,$U11,K$11:K$241) -> 514.92588 | Y11: =+SUMIF($B$11:$B$241,$U11,L$11:L$241) -> 170.96916 | Z11: =Y11+X11 -> 685.89504 | AB11: =-(P11-W11)/W11 -> -0.07040696
A12: 2 | B12: CD | C12: ENEA IV | D12: METROPOLITANA DE SANTIAGO | E12: PUDAHUEL | F12: Rm | G12: Cliente libre (no renovable) | H12: Kwh | I12: 499817 | J12: SEN | K12: 0 | L12: =(I12*0.055028169)/1000 -> 27.504014 | N12: CO | O12: 8 | P12: 383214 | Q12: 150 | R12: 21 | S12: =R12+Q12 -> 171 | U12: CO | V12: 8 | W12: =+SUMIF($B$11:$B$241,$U12,I$11:I$241) -> 191819.72 | X12: =+SUMIF($B$11:$B$241,$U12,K$11:K$241) -> 57.661007 | Y12: =+SUMIF($B$11:$B$241,$U12,L$11:L$241) -> 10.555488 | Z12: =Y12+X12 -> 68.216495 | AB12: =-(P12-W12)/W12 -> -0.99778211
A13: 3 | B13: CD | C13: CD SAN BERNARDO | D13: METROPOLITANA DE SANTIAGO | E13: SAN BERNARDO | F13: Rm | G13: Compra de la matriz energética | H13: Kwh | I13: 344419.78 | J13: SEN | K13: =+I13*VLOOKUP(J13,'Factores Emisión EDGE'!$K$228:$L$230,2,FALSE)/1000 -> 103.53258 | L13: =(I13*0.055028169)/1000 -> 18.95279 | N13: CR | O13: 18 | P13: 260449 | Q13: 102 | R13: 14 | S13: =R13+Q13 -> 116 | U13: CR | V13: 12 | W13: =+SUMIF($B$11:$B$241,$U13,I$11:I$241) -> 139020.64 | X13: =+SUMIF($B$11:$B$241,$U13,K$11:K$241) -> 41.789604 | Y13: =+SUMIF($B$11:$B$241,$U13,L$11:L$241) -> 7.6500512 | Z13: =Y13+X13 -> 49.439655 | AB13: =-(P13-W13)/W13 -> -0.87345564
A14: 4 | B14: CD | C14: ENEA II | D14: METROPOLITANA DE SANTIAGO | E14: PUDAHUEL | F14: RM | G14: Compra de la matriz energética | H14: Kwh | I14: 185453.2 | J14: SEN | K14: =+I14*VLOOKUP(J14,'Factores Emisión EDGE'!$K$228:$L$230,2,FALSE)/1000 -> 55.747232 | L14: =(I14*0.055028169)/1000 -> 10.20515 | N14: OFICINA PROPIA | O14: 66 | P14: 609935 | Q14: 240 | R14: 34 | S14: =R14+Q14 -> 274 | U14: OFICINA PROPIA | V14: 54 | W14: =+SUMIF($B$11:$B$241,$U14,I$11:I$241) -> 551716.61 | X14: =+SUMIF($B$11:$B$241,$U14,K$11:K$241) -> 172.87809 | Y14: =+SUMIF($B$11:$B$241,$U14,L$11:L$241) -> 30.359955 | Z14: =Y14+X14 -> 203.23804 | AB14: =-(P14-W14)/W14 -> -0.10552228
A15: 5 | B15: CD | C15: CDT CURAUMA | D15: VALPARAISO | E15: VALPARAISO | F15: C- NORTE | G15: Compra de la matriz energética | H15: Kwh | I15: 137710.23 | J15: SEN | K15: =+I15*VLOOKUP(J15,'Factores Emisión EDGE'!$K$228:$L$230,2,FALSE)/1000 -> 41.395695 | L15: =(I15*0.055028169)/1000 -> 7.5779418 | N15: FRANQUICIA | O15: 124 | P15: 918162 | Q15: 372 | R15: 50 | S15: =R15+Q15 -> 422 | U15: FRANQUICIA | V15: 129 | W15: =+SUMIF($B$11:$B$241,$U15,I$11:I$241) -> 927515.2 | X15: =+SUMIF($B$11:$B$241,$U15,K$11:K$241) -> 285.94759 | Y15: =+SUMIF($B$11:$B$241,$U15,L$11:L$241) -> 51.039463 | Z15: =Y15+X15 -> 336.98706 | AB15: =-(P15-W15)/W15 -> 0.010084152
A16: 6 | B16: CD | C16: CONCEPCION EXPRESS | D16: BIOBIO | E16: HUALPEN | F16: Sur | G16: Compra de la matriz energética | H16: Kwh | I16: 137400 | J16: SEN | K16: =+I16*VLOOKUP(J16,'Factores Emisión EDGE'!$K$228:$L$230,2,FALSE)/1000 -> 41.30244 | L16: =(I16*0.055028169)/1000 -> 7.5608704 | N16: Total | O16: =SUM(O11:O15) -> 246 | P16: =SUM(P11:P15) -> 5497449 | Q16: =SUM(Q11:Q15) -> 1592 | R16: =SUM(R11:R15) -> 302 | S16: =R16+Q16 -> 1894 | U16: Total | V16: =SUM(V11:V15) -> 231 | W16: =SUM(W11:W15) -> 4917011 | X16: =SUM(X11:X15) -> 1073.2022 | Y16: =SUM(Y11:Y15) -> 270.57411 | Z16: =Y16+X16 -> 1343.7763 | AB16: =-(P16-W16)/W16 -> -0.11804691
A17: 7 | B17: CD | C17: PUERTO MONTT EXPRESS | D17: LOS LAGOS | E17: PUERTO MONTT | F17: Austral | G17: Compra de la matriz energética | H17: Kwh | I17: 127740 | J17: SEN | K17: =+I17*VLOOKUP(J17,'Factores Emisión EDGE'!$K$228:$L$230,2,FALSE)/1000 -> 38.398644 | L17: =(I17*0.055028169)/1000 -> 7.0292983 | N17: Descuento ERNC | O17: 2 | P17: 1540795 | Q17: 603 | R17: 0 | S17: =R17+Q17 -> 603 | U17: Descuento ERNC | V17: 2 | W17: =I11+I12 -> 1425271 | X17: 425 | Y17: 0 | Z17: =X17 -> 425
A18: 8 | B18: CD | C18: IQUIQUE EXPRESS | D18: TARAPACA | E18: IQUIQUE | F18: Norte | G18: Compra de la matriz energética | H18: Kwh | I18: 115860 | J18: SEN | K18: =+I18*VLOOKUP(J18,'Factores Emisión EDGE'!$K$228:$L$230,2,FALSE)/1000 -> 34.827516 | L18: =(I18*0.055028169)/1000 -> 6.3755637 | N18: % ERNC | P18: =P17/P16 -> 0.28027454 | U18: % ERNC | W18: =W17/W16 -> 0.28986532
A19: 9 | B19: CD | C19: LOS ANGELES EXPRESS | D19: BIOBIO | E19: LOS ANGELES | F19: Sur | G19: Compra de la matriz energética | H19: Kwh | I19: 108528 | J19: SEN | K19: =+I19*VLOOKUP(J19,'Factores Emisión EDGE'!$K$228:$L$230,2,FALSE)/1000 -> 32.623517 | L19: =(I19*0.055028169)/1000 -> 5.9720971
A20: 10 | B20: CD | C20: ANTOFAGASTA EXPRESS | D20: ANTOFAGASTA | E20: ANTOFAGASTA | F20: Norte | G20: Compra de la matriz energética | H20: Kwh | I20: 76197.1 | J20: SEN | K20: =+I20*VLOOKUP(J20,'Factores Emisión EDGE'!$K$228:$L$230,2,FALSE)/1000 -> 22.904848 | L20: =(I20*0.055028169)/1000 -> 4.1929869 | N20: Factores de emisión 2021 | S20: Factores de emisión 2022 | W20: Dif. | X20: Dif %
A21: 11 | B21: CD | C21: CHILLAN EXPRESS | D21: NUBLE | E21: CHILLAN | F21: Centro Sur | G21: Compra de la matriz energética | H21: Kwh | I21: 71172 | J21: SEN | K21: =+I21*VLOOKUP(J21,'Factores Emisión EDGE'!$K$228:$L$230,2,FALSE)/1000 -> 21.394303 | L21: =(I21*0.055028169)/1000 -> 3.9164648 | N21: Electricidad- alcance 2 | O21: SEN | P21: 0.3907 | Q21: kg CO2eq/kWh | S21: Electricidad- alcance 2 | T21: SEN | U21: 0.3006 | V21: kg CO2eq/kWh | W21: =-P21+U21 -> -0.0901 | X21: =-W21/P21 -> 0.23061172
A22: 12 | B22: CO | C22: CO CONCON | D22: VALPARAISO | E22: CONCON | F22: Centro Norte | G22: Compra de la matriz energética | H22: Kwh | I22: 66720 | J22: SEN | K22: =+I22*VLOOKUP(J22,'Factores Emisión EDGE'!$K$228:$L$230,2,FALSE)/1000 -> 20.056032 | L22: =(I22*0.055028169)/1000 -> 3.6714794 | O22: SEA | P22: 0.7245 | Q22: kg CO2eq/kWh | T22: SEA | U22: 0.7245 | V22: kg CO2eq/kWh | W22: =-P22+U22 -> 0 | X22: =-W22/P22 -> 0
A23: 13 | B23: CR | C23: QUILPUE CR | D23: VALPARAISO | E23: QUILPUE | F23: C- NORTE | G23: Compra de la matriz energética | H23: Kwh | I23: 56436 | J23: SEN | K23: =+I23*VLOOKUP(J23,'Factores Emisión EDGE'!$K$228:$L$230,2,FALSE)/1000 -> 16.964662 | L23: =(I23*0.055028169)/1000 -> 3.1055697 | O23: SEM | P23: 0.59279167 | Q23: kg CO2eq/kWh | T23: SEM | U23: 0.59279167 | V23: kg CO2eq/kWh | W23: =-P23+U23 -> 0 | X23: =-W23/P23 -> 0
A24: 14 | B24: CO | C24: CO PUERTO VARAS | D24: LOS LAGOS | E24: PUERTO VARAS | F24: Austral | G24: Compra de la matriz energética | H24: Kwh | I24: 50040 | J24: SEN | K24: =+I24*VLOOKUP(J24,'Factores Emisión EDGE'!$K$228:$L$230,2,FALSE)/1000 -> 15.042024 | L24: =(I24*0.055028169)/1000 -> 2.7536096 | N24: Electricidad- alcance 3 | O24: SEN | P24: =+P21*(0.05/0.355) -> 0.055028169 | Q24: kg CO2eq/kWh | T24: ERNC | U24: 0 | V24: kg CO2eq/kWh
A25: 15 | B25: FRANQUICIA | C25: PLAZA NORTE | D25: METROPOLITANA DE SANTIAGO | E25: HUECHURABA | F25: RM | G25: Compra de la matriz energética | H25: Kwh | I25: 44707.039 | J25: SEN | K25: =+I25*VLOOKUP(J25,'Factores Emisión EDGE'!$K$228:$L$230,2,FALSE)/1000 -> 13.438936 | L25: =(I25*0.055028169)/1000 -> 2.4601465 | O25: ERNC | P25: 0.055028169 | Q25: kg CO2eq/kWh | S25: Electricidad- alcance 3 | T25: SEN | U25: 0.055028169 | V25: kg CO2eq/kWh | W25: =-P24+U25 -> 0 | X25: =-W25/P24 -> 0
A26: 16 | B26: CD | C26: VALDIVIA EXPRESS | D26: LOS RÍOS | E26: VALDIVIA | F26: Sur | G26: Compra de la matriz energética | H26: Kwh | I26: 43692 | J26: SEN | K26: =+I26*VLOOKUP(J26,'Factores Emisión EDGE'!$K$228:$L$230,2,FALSE)/1000 -> 13.133815 | L26: =(I26*0.055028169)/1000 -> 2.4042908 | T26: ERNC | U26: 0.055028169 | V26: kg CO2eq/kWh | W26: =-P25+U26 -> 0 | X26: =-W26/P25 -> 0
A27: 17 | B27: OFICINA PROPIA | C27: CURICO ALAMEDA | D27: MAULE | E27: CURICO | F27: C- SUR | G27: Compra de la matriz energética | H27: Kwh | I27: 41228.17 | J27: SEN | K27: =+I27*VLOOKUP(J27,'Factores Emisión EDGE'!$K$228:$L$230,2,FALSE)/1000 -> 12.393188 | L27: =(I27*0.055028169)/1000 -> 2.2687107 | N27: Efecto mejora del factor de emisión
A28: 18 | B28: CD | C28: SAN ANTONIO EXPRESS | D28: VALPARAISO | E28: SAN ANTONIO | F28: Centro Norte | G28: Compra de la matriz energética | H28: Kwh | I28: 40752 | J28: SEN | K28: =+I28*VLOOKUP(J28,'Factores Emisión EDGE'!$K$228:$L$230,2,FALSE)/1000 -> 12.250051 | L28: =(I28*0.055028169)/1000 -> 2.2425079 | P28: Directas | Q28: Indirectas | R28: Total | AB28: https://www.diariosustentable.com/2023/01/2022-presenta-matriz-energetica-mas-limpia-de-los-ultimos-12-anos/
A29: 19 | B29: CD | C29: COPIAPO EXPRESS | D29: ATACAMA | E29: COPIAPO | F29: Norte | G29: Compra de la matriz energética | H29: Kwh | I29: 37255 | J29: SEN | K29: =+I29*VLOOKUP(J29,'Factores Emisión EDGE'!$K$228:$L$230,2,FALSE)/1000 -> 11.198853 | L29: =(I29*0.055028169)/1000 -> 2.0500744 | O29: emisiones 2022 con f.emisión 2021 CO2 | P29: =(W16-W17)*P21/1000 -> 1364.2228 | Q29: =W16*P24/1000 -> 270.57411 | R29: =P29+Q29 -> 1634.797
A30: 20 | B30: OFICINA PROPIA | C30: COPIAPO LOS CARRERA | D30: ATACAMA | E30: COPIAPO | F30: NORTE | G30: Compra de la matriz energética | H30: Kwh | I30: 35976.06 | J30: SEN | K30: =+I30*VLOOKUP(J30,'Factores Emisión EDGE'!$K$228:$L$230,2,FALSE)/1000 -> 10.814404 | L30: =(I30*0.055028169)/1000 -> 1.9796967 | O30: efecto mejora factor de emision kwh | R30: =-R29+Z16 -> -291.02066
A31: 21 | B31: CD | C31: OSORNO EXPRESS | D31: LOS LAGOS | E31: OSORNO | F31: Austral | G31: Compra de la matriz energética | H31: Kwh | I31: 32803.56 | J31: SEN | K31: =+I31*VLOOKUP(J31,'Factores Emisión EDGE'!$K$228:$L$230,2,FALSE)/1000 -> 9.8607501 | L31: =(I31*0.055028169)/1000 -> 1.8051198 | O31: efecto mejora factor emision % | R31: =R30/S16 -> -0.15365399
A32: 22 | B32: OFICINA PROPIA | C32: CONCEPCION MALL EL TREBOL | D32: BIOBIO | E32: CONCEPCION | F32: SUR | G32: Compra de la matriz energética | H32: Kwh | I32: 31482.172 | J32: SEN | K32: =+I32*VLOOKUP(J32,'Factores Emisión EDGE'!$K$228:$L$230,2,FALSE)/1000 -> 9.4635409 | L32: =(I32*0.055028169)/1000 -> 1.7324063
A33: 23 | B33: CD | C33: RANCAGUA EXPRESS | D33: LIBERTADOR GRAL BERNARDO O HIGGINS | E33: RANCAGUA | F33: Centro Sur | G33: Compra de la matriz energética | H33: Kwh | I33: 30874 | J33: SEN | K33: =+I33*VLOOKUP(J33,'Factores Emisión EDGE'!$K$228:$L$230,2,FALSE)/1000 -> 9.2807244 | L33: =(I33*0.055028169)/1000 -> 1.6989397
A34: 24 | B34: FRANQUICIA | C34: MAPOCHO | D34: METROPOLITANA DE SANTIAGO | E34: QUINTA NORMAL | F34: RM | G34: Compra de la matriz energética | H34: Kwh | I34: 30282.1 | J34: SEN | K34: =+I34*VLOOKUP(J34,'Factores Emisión EDGE'!$K$228:$L$230,2,FALSE)/1000 -> 9.1027993 | L34: =(I34*0.055028169)/1000 -> 1.6663685
A35: 25 | B35: CD | C35: TEMUCO EXPRESS | D35: ARAUCANIA | E35: PADRE LAS CASAS | F35: Sur | G35: Compra de la matriz energética | H35: Kwh | I35: 29745.355 | J35: SEN | K35: =+I35*VLOOKUP(J35,'Factores Emisión EDGE'!$K$228:$L$230,2,FALSE)/1000 -> 8.9414537 | L35: =(I35*0.055028169)/1000 -> 1.6368324 | N35: Resumen / Indicadores Operacionales
A36: 26 | B36: OFICINA PROPIA | C36: TALCA VAROLI | D36: MAULE | E36: TALCA | F36: C- SUR | G36: Compra de la matriz energética | H36: Kwh | I36: 28320 | J36: SEN | K36: =+I36*VLOOKUP(J36,'Factores Emisión EDGE'!$K$228:$L$230,2,FALSE)/1000 -> 8.512992 | L36: =(I36*0.055028169)/1000 -> 1.5583977 | O36: 2021 | P36: 2022 | Q36: Diferencia | R36: Dif % | S36: Justificación
A37: 27 | B37: CD | C37: SAN FELIPE EXPRESS | D37: VALPARAISO | E37: SAN FELIPE | F37: Centro Norte | G37: Compra de la matriz energética | H37: Kwh | I37: 26607 | J37: SEN | K37: =+I37*VLOOKUP(J37,'Factores Emisión EDGE'!$K$228:$L$230,2,FALSE)/1000 -> 7.9980642 | L37: =(I37*0.055028169)/1000 -> 1.4641345 | N37: Consumo electrico | O37: =P16 -> 5497449 | P37: =W16 -> 4917011 | Q37: =P37-O37 -> -580437.95 | R37: =Q37/O37 -> -0.10558314 | S37: Menor cantidad de unidades (246 a 231) y menor consumo por instalacion de luces led (pasa de un 18% a un 77% de las instalaciones a nivel nacional con luces led)
A38: 28 | B38: FRANQUICIA | C38: PUENTE ALTO DOS | D38: METROPOLITANA DE SANTIAGO | E38: PUENTE ALTO | F38: RM | G38: Compra de la matriz energética | H38: Kwh | I38: 25860 | J38: SEN | K38: =+I38*VLOOKUP(J38,'Factores Emisión EDGE'!$K$228:$L$230,2,FALSE)/1000 -> 7.773516 | L38: =(I38*0.055028169)/1000 -> 1.4230285 | N38: intensidad kwh/pieza | O38: =O37/O4 -> 0.16687684 | P38: =P37/O5 -> 0.25735653 | Q38: =P38-O38 -> 0.090479688 | R38: =Q38/O38 -> 0.54219441 | S38: No proporcional a la demanda por consumo fijo en instalaciones
A39: 29 | B39: FRANQUICIA | C39: PAJARITOS | D39: METROPOLITANA DE SANTIAGO | E39: MAIPU | F39: RM | G39: Compra de la matriz energética | H39: Kwh | I39: 23142.857 | J39: SEN | K39: =+I39*VLOOKUP(J39,'Factores Emisión EDGE'!$K$228:$L$230,2,FALSE)/1000 -> 6.9567428 | L39: =(I39*0.055028169)/1000 -> 1.273509 | N39: ERNC | O39: =P17 -> 1540795 | P39: =W17 -> 1425271 | Q39: =P39-O39 -> -115524 | R39: =Q39/O39 -> -0.074976879 | S39: Menor consumo de energia en ENEA
A40: 30 | B40: FRANQUICIA | C40: VICTORIA CENTRO | D40: VALPARAISO | E40: VALPARAISO | F40: C- NORTE | G40: Compra de la matriz energética | H40: Kwh | I40: 21439.4 | J40: SEN | K40: =+I40*VLOOKUP(J40,'Factores Emisión EDGE'!$K$228:$L$230,2,FALSE)/1000 -> 6.4446836 | L40: =(I40*0.055028169)/1000 -> 1.1797709 | N40: % ERNC | O40: =O39/O37 -> 0.28027454 | P40: =P39/P37 -> 0.28986532 | Q40: =P40-O40 -> 0.009590782 | R40: =Q40 -> 0.009590782 | S40: Aumento 1%
A41: 31 | B41: CD | C41: CALAMA EXPRESS | D41: ANTOFAGASTA | E41: CALAMA | F41: Norte | G41: Compra de la matriz energética | H41: Kwh | I41: 21065.455 | J41: SEN | K41: =+I41*VLOOKUP(J41,'Factores Emisión EDGE'!$K$228:$L$230,2,FALSE)/1000 -> 6.3322756 | L41: =(I41*0.055028169)/1000 -> 1.1591934 | N41: consumo electrico s/ERNC | O41: =O37-O39 -> 3956654 | P41: =P37-P39 -> 3491740 | Q41: =P41-O41 -> -464913.95 | R41: =Q41/O41 -> -0.1175018
A42: 32 | B42: OFICINA PROPIA | C42: COQUIMBO CENTRO EMPRESARIAL | D42: COQUIMBO | E42: COQUIMBO | F42: C- NORTE | G42: Compra de la matriz energética | H42: Kwh | I42: 21000 | J42: SEN | K42: =+I42*VLOOKUP(J42,'Factores Emisión EDGE'!$K$228:$L$230,2,FALSE)/1000 -> 6.3126 | L42: =(I42*0.055028169)/1000 -> 1.1555915 | N42: Factor emisión ponderado | O42: =O47*1000/O37 -> 0.34452343 | P42: =P47*1000/P37 -> 0.27329129 | Q42: =P42-O42 -> -0.071232143 | R42: =Q42/O42 -> -0.20675558 | S42: Efecto mejora matriz energetica -20% y aumento 1% ERNC en el total del consumo
A43: 33 | B43: OFICINA PROPIA | C43: PUNTA ARENAS MENENDEZ | D43: MAGALLANES Y LA ANTARTICA CHILENA | E43: PUNTA ARENAS | F43: AUSTRAL | G43: Compra de la matriz energética | H43: Kwh | I43: 19888 | J43: SEM | K43: =+I43*VLOOKUP(J43,'Factores Emisión EDGE'!$K$228:$L$230,2,FALSE)/1000 -> 11.789441 | L43: =(I43*0.055028169)/1000 -> 1.0944002 | N43: cantidad de unidades | O43: =O16 -> 246 | P43: =V16 -> 231 | Q43: =P43-O43 -> -15 | R43: =Q43/O43 -> -0.06097561 | S43: Menor cantidad de unidades 246 a 231 por menor demanda
A44: 34 | B44: CR | C44: CASTRO CR | D44: LOS LAGOS | E44: CASTRO | F44: Austral | G44: Compra de la matriz energética | H44: Kwh | I44: 19116 | J44: SEN | K44: =+I44*VLOOKUP(J44,'Factores Emisión EDGE'!$K$228:$L$230,2,FALSE)/1000 -> 5.7462696 | L44: =(I44*0.055028169)/1000 -> 1.0519185 | N44: kwh/unidad | O44: =O37/O43 -> 22347.354 | P44: =P37/P43 -> 21285.762 | Q44: =P44-O44 -> -1061.5915 | R44: =Q44/O44 -> -0.047504128 | S44: Menor consumo por instalacion luces led
A45: 35 | B45: FRANQUICIA | C45: APUMANQUE DOS | D45: METROPOLITANA DE SANTIAGO | E45: LAS CONDES | F45: RM | G45: Compra de la matriz energética | H45: Kwh | I45: 18264 | J45: SEN | K45: =+I45*VLOOKUP(J45,'Factores Emisión EDGE'!$K$228:$L$230,2,FALSE)/1000 -> 5.4901584 | L45: =(I45*0.055028169)/1000 -> 1.0050345 | N45: kwh/CD | O45: =O37/O11 -> 183248.3 | P45: =P37/V11 -> 175607.54 | Q45: =P45-O45 -> -7640.7626 | R45: =Q45/O45 -> -0.041696226 | S45: Menor consumo por instalacion luces led
A46: 36 | B46: OFICINA PROPIA | C46: BRASIL | D46: METROPOLITANA DE SANTIAGO | E46: SANTIAGO CENTRO | F46: RM | G46: Compra de la matriz energética | H46: Kwh | I46: 17678.43 | J46: SEN | K46: =+I46*VLOOKUP(J46,'Factores Emisión EDGE'!$K$228:$L$230,2,FALSE)/1000 -> 5.3141361 | L46: =(I46*0.055028169)/1000 -> 0.97281163 | N46: kwh/oficina+franquicia | O46: =O37/(O14+O15) -> 28933.942 | P46: =P37/(V14+V15) -> 26868.913 | Q46: =P46-O46 -> -2065.0293 | R46: =Q46/O46 -> -0.071370478 | S46: Menor consumo por instalacion luces led
A47: 37 | B47: OFICINA PROPIA | C47: BILBAO | D47: METROPOLITANA DE SANTIAGO | E47: PROVIDENCIA | F47: RM | G47: Compra de la matriz energética | H47: Kwh | I47: 17640 | J47: SEN | K47: =+I47*VLOOKUP(J47,'Factores Emisión EDGE'!$K$228:$L$230,2,FALSE)/1000 -> 5.302584 | L47: =(I47*0.055028169)/1000 -> 0.9706969 | N47: Emisiones tCO2 | O47: =Q16+R16 -> 1894 | P47: =X16+Y16 -> 1343.7763 | Q47: =P47-O47 -> -550.22371 | R47: =Q47/O47 -> -0.29050882 | S47: 1) Mejora de factor de emisión de matriz energetica nacional de un -23% (-18%) 2) Menor consumo electrico por instalaciones LED y menor cantidad de unidades (-11%) 3) Aumento de consumo ERNC respecto del total (+1%)
A48: 38 | B48: OFICINA PROPIA | C48: ANTOFAGASTA BAQUEDANO | D48: ANTOFAGASTA | E48: ANTOFAGASTA | F48: NORTE | G48: Compra de la matriz energética | H48: Kwh | I48: 17488.364 | J48: SEN | K48: =+I48*VLOOKUP(J48,'Factores Emisión EDGE'!$K$228:$L$230,2,FALSE)/1000 -> 5.2570021 | L48: =(I48*0.055028169)/1000 -> 0.96235263 | N48: Emisión por pieza kgco2/pieza | O48: =(Q16+R16)*1000/O4 -> 0.057492981 | P48: =(X16+Y16)*1000/O5 -> 0.070333297 | Q48: =P48-O48 -> 0.012840316 | R48: =Q48/O48 -> 0.22333711 | S48: Reduccion de emisiones totales (-29%) no es proporcional a la baja de demanda (-42%) por consumo fijo en instalaciones. Intensidad energetica por pieza aumenta +54%, sin embargo la mejora del factor de emisión contribuye a reducir -32%
A49: 39 | B49: FRANQUICIA | C49: ALAMEDA LIBERTADOR B OHIGGINS | D49: METROPOLITANA DE SANTIAGO | E49: SANTIAGO CENTRO | F49: RM | G49: Compra de la matriz energética | H49: Kwh | I49: 17160 | J49: SEN | K49: =+I49*VLOOKUP(J49,'Factores Emisión EDGE'!$K$228:$L$230,2,FALSE)/1000 -> 5.158296 | L49: =(I49*0.055028169)/1000 -> 0.94428338
A50: 40 | B50: CR | C50: LINARES CR | D50: MAULE | E50: LINARES | F50: Centro Sur | G50: Compra de la matriz energética | H50: Kwh | I50: 17119 | J50: SEN | K50: =+I50*VLOOKUP(J50,'Factores Emisión EDGE'!$K$228:$L$230,2,FALSE)/1000 -> 5.1459714 | L50: =(I50*0.055028169)/1000 -> 0.94202723
A51: 41 | B51: CO | C51: CO SANTIAGO CENTRO | D51: METROPOLITANA DE SANTIAGO | E51: SANTIAGO CENTRO | F51: Rm | G51: Compra de la matriz energética | H51: Kwh | I51: 16746.41 | J51: SEN | K51: =+I51*VLOOKUP(J51,'Factores Emisión EDGE'!$K$228:$L$230,2,FALSE)/1000 -> 5.0339708 | L51: =(I51*0.055028169)/1000 -> 0.92152428 | R51: =R37*O47 -> -199.97448
A52: 42 | B52: CD | C52: ARICA EXPRESS | D52: ARICA Y PARINACOTA | E52: ARICA | F52: Norte | G52: Compra de la matriz energética | H52: Kwh | I52: 16461 | J52: SEN | K52: =+I52*VLOOKUP(J52,'Factores Emisión EDGE'!$K$228:$L$230,2,FALSE)/1000 -> 4.9481766 | L52: =(I52*0.055028169)/1000 -> 0.90581869
A53: 43 | B53: CD | C53: SAN FERNANDO EXPRESS | D53: LIBERTADOR GRAL BERNARDO O HIGGINS | E53: SAN FERNANDO | F53: Centro Sur | G53: Compra de la matriz energética | H53: Kwh | I53: 16159 | J53: SEN | K53: =+I53*VLOOKUP(J53,'Factores Emisión EDGE'!$K$228:$L$230,2,FALSE)/1000 -> 4.8573954 | L53: =(I53*0.055028169)/1000 -> 0.88920018
A54: 44 | B54: OFICINA PROPIA | C54: ANTOFAGASTA ARAUCO | D54: ANTOFAGASTA | E54: ANTOFAGASTA | F54: NORTE | G54: Compra de la matriz energética | H54: Kwh | I54: 15647.717 | J54: SEN | K54: =+I54*VLOOKUP(J54,'Factores Emisión EDGE'!$K$228:$L$230,2,FALSE)/1000 -> 4.7037037 | L54: =(I54*0.055028169)/1000 -> 0.86106521
A55: 45 | B55: OFICINA PROPIA | C55: CHILLAN CINCO DE ABRIL | D55: NUBLE | E55: CHILLAN | F55: C- SUR | G55: Compra de la matriz energética | H55: Kwh | I55: 15548 | J55: SEN | K55: =+I55*VLOOKUP(J55,'Factores Emisión EDGE'!$K$228:$L$230,2,FALSE)/1000 -> 4.6737288 | L55: =(I55*0.055028169)/1000 -> 0.85557797
A56: 46 | B56: FRANQUICIA | C56: QUILLOTA RENE CORTAZAR | D56: VALPARAISO | E56: QUILPUE | F56: Centro Norte | G56: Compra de la matriz energética | H56: Kwh | I56: 15535 | J56: SEN | K56: =+I56*VLOOKUP(J56,'Factores Emisión EDGE'!$K$228:$L$230,2,FALSE)/1000 -> 4.669821 | L56: =(I56*0.055028169)/1000 -> 0.85486261
A57: 47 | B57: OFICINA PROPIA | C57: PUERTO MONTT CENTRO | D57: LOS LAGOS | E57: PUERTO MONTT | F57: AUSTRAL | G57: Compra de la matriz energética | H57: Kwh | I57: 15384 | J57: SEN | K57: =+I57*VLOOKUP(J57,'Factores Emisión EDGE'!$K$228:$L$230,2,FALSE)/1000 -> 4.6244304 | L57: =(I57*0.055028169)/1000 -> 0.84655335
A58: 48 | B58: CR | C58: LAS CONDES CR | D58: METROPOLITANA DE SANTIAGO | E58: LAS CONDES | F58: Rm | G58: Compra de la matriz energética | H58: Kwh | I58: 15165.3 | J58: SEN | K58: =+I58*VLOOKUP(J58,'Factores Emisión EDGE'!$K$228:$L$230,2,FALSE)/1000 -> 4.5586892 | L58: =(I58*0.055028169)/1000 -> 0.83451869
A59: 49 | B59: CD | C59: PUNTA ARENAS EXPRESS | D59: MAGALLANES Y LA ANTARTICA CHILENA | E59: PUNTA ARENAS | F59: Austral | G59: Compra de la matriz energética | H59: Kwh | I59: 15159 | J59: SEM | K59: =+I59*VLOOKUP(J59,'Factores Emisión EDGE'!$K$228:$L$230,2,FALSE)/1000 -> 8.9861289 | L59: =(I59*0.055028169)/1000 -> 0.83417201
A60: 50 | B60: FRANQUICIA | C60: CURICO CENTRO | D60: MAULE | E60: CURICO | F60: C- SUR | G60: Compra de la matriz energética | H60: Kwh | I60: 15024 | J60: SEN | K60: =+I60*VLOOKUP(J60,'Factores Emisión EDGE'!$K$228:$L$230,2,FALSE)/1000 -> 4.5162144 | L60: =(I60*0.055028169)/1000 -> 0.82674321
A61: 51 | B61: CD | C61: QUILLOTA EXPRESS | D61: VALPARAISO | E61: QUILLOTA | F61: Centro Norte | G61: Compra de la matriz energética | H61: Kwh | I61: 14911.53 | J61: SEN | K61: =+I61*VLOOKUP(J61,'Factores Emisión EDGE'!$K$228:$L$230,2,FALSE)/1000 -> 4.4824059 | L61: =(I61*0.055028169)/1000 -> 0.82055419
A62: 52 | B62: CO | C62: CO HUECHURABA | D62: METROPOLITANA DE SANTIAGO | E62: HUECHURABA | F62: Rm | G62: Compra de la matriz energética | H62: Kwh | I62: 14738.04 | J62: SEN | K62: =+I62*VLOOKUP(J62,'Factores Emisión EDGE'!$K$228:$L$230,2,FALSE)/1000 -> 4.4302548 | L62: =(I62*0.055028169)/1000 -> 0.81100736
A63: 53 | B63: FRANQUICIA | C63: PUERTO MONTT IBAÑEZ DOS | D63: LOS LAGOS | E63: PUERTO MONTT | F63: AUSTRAL | G63: Compra de la matriz energética | H63: Kwh | I63: 14668.364 | J63: SEN | K63: =+I63*VLOOKUP(J63,'Factores Emisión EDGE'!$K$228:$L$230,2,FALSE)/1000 -> 4.4093101 | L63: =(I63*0.055028169)/1000 -> 0.80717319
... A112: 102 | B112: CR | C112: SAN BERNARDO CR | D112: METROPOLITANA DE SANTIAGO | E112: SAN BERNARDO | F112: Rm | G112: Compra de la matriz energética | H112: Kwh | I112: 8554 | J112: SEN | K112: =+I112*VLOOKUP(J112,'Factores Emisión EDGE'!$K$228:$L$230,2,FALSE)/1000 -> 2.5713324 | L112: =(I112*0.055028169)/1000 -> 0.47071096
A113: 103 | B113: OFICINA PROPIA | C113: SANTIAGO VICUNA MACKENNA | D113: METROPOLITANA DE SANTIAGO | E113: SANTIAGO CENTRO | F113: RM | G113: Compra de la matriz energética | H113: Kwh | I113: 8422.19 | J113: SEN | K113: =+I113*VLOOKUP(J113,'Factores Emisión EDGE'!$K$228:$L$230,2,FALSE)/1000 -> 2.5317103 | L113: =(I113*0.055028169)/1000 -> 0.46345769 | N113: Fuente | O113: Categorías | P113: Considerada | Q113: Demanda 2022 | R113: Cantidad | S113: Unidad | T113: Tipo | U113: Conversión a kWh
A114: 104 | B114: FRANQUICIA | C114: CONCEPCION OHIGGINS | D114: BIOBIO | E114: CONCEPCION | F114: SUR | G114: Compra de la matriz energética | H114: Kwh | I114: 8360 | J114: SEN | K114: =+I114*VLOOKUP(J114,'Factores Emisión EDGE'!$K$228:$L$230,2,FALSE)/1000 -> 2.513016 | L114: =(I114*0.055028169)/1000 -> 0.46003549 | N114: Combustible | O114: Distribución propia (furgones) | P114: SI | Q114: 19105834 | R114: 456447 | S114: Lts | T114: Diesel | U114: 4409278
A115: 105 | B115: CD | C115: TALCA EXPRESS | D115: MAULE | E115: TALCA | F115: Centro Sur | G115: Compra de la matriz energética | H115: Kwh | I115: 8317.0909 | J115: SEN | K115: =+I115*VLOOKUP(J115,'Factores Emisión EDGE'!$K$228:$L$230,2,FALSE)/1000 -> 2.5001175 | L115: =(I115*0.055028169)/1000 -> 0.45767428 | N115: Combustible | O115: Distribución propia (motos) | P115: SI | R115: 42804 | S115: Lts | T115: Diesel | U115: 413487
A116: 106 | B116: OFICINA PROPIA | C116: VIÑA DEL MAR SIMON BOLIVAR | D116: VALPARAISO | E116: VINA DEL MAR | F116: C- NORTE | G116: Compra de la matriz energética | H116: Kwh | I116: 8304.48 | J116: SEN | K116: =+I116*VLOOKUP(J116,'Factores Emisión EDGE'!$K$228:$L$230,2,FALSE)/1000 -> 2.4963267 | L116: =(I116*0.055028169)/1000 -> 0.45698033 | N116: Combustible | O116: Distribución propia (VEs) | P116: SI | R116: 147209 | S116: kWh | T116: Electricidad | U116: 147209
A117: 107 | B117: FRANQUICIA | C117: LOS DOMINICOS | D117: METROPOLITANA DE SANTIAGO | E117: LAS CONDES | F117: RM | G117: Compra de la matriz energética | H117: Kwh | I117: 8242.5204 | J117: SEN | K117: =+I117*VLOOKUP(J117,'Factores Emisión EDGE'!$K$228:$L$230,2,FALSE)/1000 -> 2.4777016 | L117: =(I117*0.055028169)/1000 -> 0.4535708 | N117: Combustible | O117: Distribución externa | P117: NO | R117: 1920607 | S117: Lts | T117: Diesel | U117: -
A118: 108 | B118: CD | C118: LA SERENA EXPRESS | D118: COQUIMBO | E118: LA SERENA | F118: Centro Norte | G118: Compra de la matriz energética | H118: Kwh | I118: 8033 | J118: SEN | K118: =+I118*VLOOKUP(J118,'Factores Emisión EDGE'!$K$228:$L$230,2,FALSE)/1000 -> 2.4147198 | L118: =(I118*0.055028169)/1000 -> 0.44204128 | N118: Combustible | O118: Transporte troncal propio | P118: SI | R118: 452116 | S118: Lts | T118: Diesel | U118: 4367441
A119: 109 | B119: FRANQUICIA | C119: RAMON PICARTE | D119: LOS RIOS | E119: VALDIVIA | F119: SUR | G119: Compra de la matriz energética | H119: Kwh | I119: 7987.6364 | J119: SEN | K119: =+I119*VLOOKUP(J119,'Factores Emisión EDGE'!$K$228:$L$230,2,FALSE)/1000 -> 2.4010835 | L119: =(I119*0.055028169)/1000 -> 0.439545 | N119: Combustible | O119: Transporte troncal externo | P119: No | R119: 1064449 | S119: Lts | T119: Diesel | U119: -
A120: 110 | B120: OFICINA PROPIA | C120: ALTO HOSPICIO | D120: TARAPACA | E120: ALTO HOSPICIO | F120: NORTE | G120: Compra de la matriz energética | H120: Kwh | I120: 7971 | J120: SEN | K120: =+I120*VLOOKUP(J120,'Factores Emisión EDGE'!$K$228:$L$230,2,FALSE)/1000 -> 2.3960826 | L120: =(I120*0.055028169)/1000 -> 0.43862954 | N120: Consumo electrico | O120: Compra de electricidad | P120: SI | R120: 4917011 | S120: kWh | T120: Diesel | U120: 4917011
A121: 111 | B121: OFICINA PROPIA | C121: CALAMA MALL | D121: ANTOFAGASTA | E121: CALAMA | F121: NORTE | G121: Compra de la matriz energética | H121: Kwh | I121: 7880.1366 | J121: SEN | K121: =+I121*VLOOKUP(J121,'Factores Emisión EDGE'!$K$228:$L$230,2,FALSE)/1000 -> 2.3687691 | L121: =(I121*0.055028169)/1000 -> 0.43362949 | N121: Combustible | O121: Fuentes fijas generadores | P121: SI | R121: 4199 | S121: Lts | T121: Diesel | U121: 40562
A122: 112 | B122: FRANQUICIA | C122: BANDERA | D122: METROPOLITANA DE SANTIAGO | E122: SANTIAGO CENTRO | F122: RM | G122: Compra de la matriz energética | H122: Kwh | I122: 7638.81 | J122: SEN | K122: =+I122*VLOOKUP(J122,'Factores Emisión EDGE'!$K$228:$L$230,2,FALSE)/1000 -> 2.2962263 | L122: =(I122*0.055028169)/1000 -> 0.42034973 | N122: Combustible | O122: Fuentes fijas calefacción | P122: SI | R122: 12 | S122: Lts | T122: Gas Natural | U122: 129
A123: 113 | B123: FRANQUICIA | C123: TALAGANTE | D123: METROPOLITANA DE SANTIAGO | E123: TALAGANTE | F123: RM | G123: Compra de la matriz energética | H123: Kwh | I123: 7608 | J123: SEN | K123: =+I123*VLOOKUP(J123,'Factores Emisión EDGE'!$K$228:$L$230,2,FALSE)/1000 -> 2.2869648 | L123: =(I123*0.055028169)/1000 -> 0.41865431 | R123: 9004854 | S123: GRI | V123: Comentario
A124: 114 | B124: OFICINA PROPIA | C124: NUCLEO OCHAGAVIA | D124: METROPOLITANA DE SANTIAGO | E124: PEDRO AGUIRRE CERDA | F124: RM | G124: Compra de la matriz energética | H124: Kwh | I124: 7517.4193 | J124: SEN | K124: =+I124*VLOOKUP(J124,'Factores Emisión EDGE'!$K$228:$L$230,2,FALSE)/1000 -> 2.2597363 | L124: =(I124*0.055028169)/1000 -> 0.41366982 | S124: 302-1 | T124: Total | U124: 14295117 | V124: De acuerdo a la definición del indicador, solo consideramos la energía consumida por el transporte propio, las instalaciones propias o controladas por la empresa y el consumo de combustible de las fuentes fijas
A125: 115 | B125: FRANQUICIA | C125: IRARRAZAVAL | D125: METROPOLITANA DE SANTIAGO | E125: NUNOA | F125: RM | G125: Compra de la matriz energética | H125: Kwh | I125: 7393.87 | J125: SEN | K125: =+I125*VLOOKUP(J125,'Factores Emisión EDGE'!$K$228:$L$230,2,FALSE)/1000 -> 2.2225973 | L125: =(I125*0.055028169)/1000 -> 0.40687113 | N125: Conversiones | S125: 302-3 | T125: Intensidad energetica | U125: 0.7
A126: 116 | B126: FRANQUICIA | C126: SAN FERNANDO | D126: LIBERTADOR GRAL BERNARDO O HIGGINS | E126: SAN FERNANDO | F126: C- SUR | G126: Compra de la matriz energética | H126: Kwh | I126: 7380 | J126: SEN | K126: =+I126*VLOOKUP(J126,'Factores Emisión EDGE'!$K$228:$L$230,2,FALSE)/1000 -> 2.218428 | L126: =(I126*0.055028169)/1000 -> 0.40610789 | N126: kWh | O126: kcal | S126: N/A | T126: Consumo electrico | U126: 4917011
A127: 117 | B127: FRANQUICIA | C127: TALCAHUANO DOS | D127: BIOBIO | E127: TALCAHUANO | F127: SUR | G127: Compra de la matriz energética | H127: Kwh | I127: 7281 | J127: SEN | K127: =+I127*VLOOKUP(J127,'Factores Emisión EDGE'!$K$228:$L$230,2,FALSE)/1000 -> 2.1886686 | L127: =(I127*0.055028169)/1000 -> 0.4006601 | N127: 0.00116222 | O127: 1 | S127: N/A | T127: Cosnumo electrico ERNC | U127: 1425271
A128: 118 | B128: FRANQUICIA | C128: ARICA VEINTIUNO DE MAYO | D128: ARICA Y PARINACOTA | E128: ARICA | F128: NORTE | G128: Compra de la matriz energética | H128: Kwh | I128: 7268 | J128: SEN | K128: =+I128*VLOOKUP(J128,'Factores Emisión EDGE'!$K$228:$L$230,2,FALSE)/1000 -> 2.1847608 | L128: =(I128*0.055028169)/1000 -> 0.39994473 | N128: 1 | O128: 860 | P128: Enel X | S128: 302-4 | T128: % ERNC Consumo | U128: 0.29
A129: 119 | B129: OFICINA PROPIA | C129: CALAMA ABAROA | D129: ANTOFAGASTA | E129: CALAMA | F129: NORTE | G129: Compra de la matriz energética | H129: Kwh | I129: 7163 | J129: SEN | K129: =+I129*VLOOKUP(J129,'Factores Emisión EDGE'!$K$228:$L$230,2,FALSE)/1000 -> 2.1531978 | L129: =(I129*0.055028169)/1000 -> 0.39416677 | N129: Diesel (1 lt) | O129: kWh | S129: N/A | T129: Consumo combustible | U129: 9378106
A130: 120 | B130: FRANQUICIA | C130: MACUL CAMINO AGRICOLA | D130: METROPOLITANA DE SANTIAGO | E130: MACUL | F130: RM | G130: Compra de la matriz energética | H130: Kwh | I130: 6983.42 | J130: SEN | K130: =+I130*VLOOKUP(J130,'Factores Emisión EDGE'!$K$228:$L$230,2,FALSE)/1000 -> 2.0992161 | L130: =(I130*0.055028169)/1000 -> 0.38428482 | N130: 1 | O130: 9.66 | P130: Enel X | S130: N/A | T130: % ERNC combustible | U130: 0.02
A131: 121 | B131: FRANQUICIA | C131: VIVACETA | D131: METROPOLITANA DE SANTIAGO | E131: INDEPENDENCIA | F131: RM | G131: Compra de la matriz energética | H131: Kwh | I131: 6900.84 | J131: SEN | K131: =+I131*VLOOKUP(J131,'Factores Emisión EDGE'!$K$228:$L$230,2,FALSE)/1000 -> 2.0743925 | L131: =(I131*0.055028169)/1000 -> 0.37974059 | N131: Gas (1 m3) | O131: kWh
A132: 122 | B132: OFICINA PROPIA | C132: VILLARRICA | D132: ARAUCANIA | E132: VILLARRICA | F132: SUR | G132: Compra de la matriz energética | H132: Kwh | I132: 6816 | J132: SEN | K132: =+I132*VLOOKUP(J132,'Factores Emisión EDGE'!$K$228:$L$230,2,FALSE)/1000 -> 2.0488896 | L132: =(I132*0.055028169)/1000 -> 0.375072 | N132: 1 | O132: 10.86 | P132: http://old.acee.cl/576/articles-59153_doc_pdf.pdf
A133: 123 | B133: OFICINA PROPIA | C133: FLEMING | D133: METROPOLITANA DE SANTIAGO | E133: LAS CONDES | F133: RM | G133: Compra de la matriz energética | H133: Kwh | I133: 6706.7792 | J133: SEN | K133: =+I133*VLOOKUP(J133,'Factores Emisión EDGE'!$K$228:$L$230,2,FALSE)/1000 -> 2.0160578 | L133: =(I133*0.055028169)/1000 -> 0.36906178
A134: 124 | B134: FRANQUICIA | C134: MALL PLAZA SUR | D134: METROPOLITANA DE SANTIAGO | E134: SAN BERNARDO | F134: RM | G134: Compra de la matriz energética | H134: Kwh | I134: 6650.8686 | J134: SEN | K134: =+I134*VLOOKUP(J134,'Factores Emisión EDGE'!$K$228:$L$230,2,FALSE)/1000 -> 1.9992511 | L134: =(I134*0.055028169)/1000 -> 0.36598512
A135: 125 | B135: FRANQUICIA | C135: PEDRO FONTOVA | D135: METROPOLITANA DE SANTIAGO | E135: HUECHURABA | F135: RM | G135: Compra de la matriz energética | H135: Kwh | I135: 6624 | J135: SEN | K135: =+I135*VLOOKUP(J135,'Factores Emisión EDGE'!$K$228:$L$230,2,FALSE)/1000 -> 1.9911744 | L135: =(I135*0.055028169)/1000 -> 0.36450659
A136: 126 | B136: FRANQUICIA | C136: CONCEPCION MAIPU DOS | D136: BIOBIO | E136: CONCEPCION | F136: SUR | G136: Compra de la matriz energética | H136: Kwh | I136: 6609 | J136: SEN | K136: =+I136*VLOOKUP(J136,'Factores Emisión EDGE'!$K$228:$L$230,2,FALSE)/1000 -> 1.9866654 | L136: =(I136*0.055028169)/1000 -> 0.36368117
A137: 127 | B137: OFICINA PROPIA | C137: PUCON | D137: ARAUCANIA | E137: PUCON | F137: SUR | G137: Compra de la matriz energética | H137: Kwh | I137: 6598 | J137: SEN | K137: =+I137*VLOOKUP(J137,'Factores Emisión EDGE'!$K$228:$L$230,2,FALSE)/1000 -> 1.9833588 | L137: =(I137*0.055028169)/1000 -> 0.36307586
A138: 128 | B138: FRANQUICIA | C138: TEMUCO AV ALEMANIA | D138: ARAUCANIA | E138: TEMUCO | F138: SUR | G138: Compra de la matriz energética | H138: Kwh | I138: 6577 | J138: SEN | K138: =+I138*VLOOKUP(J138,'Factores Emisión EDGE'!$K$228:$L$230,2,FALSE)/1000 -> 1.9770462 | L138: =(I138*0.055028169)/1000 -> 0.36192027
A139: 129 | B139: FRANQUICIA | C139: CIUDAD EMPRESARIAL DOS | D139: METROPOLITANA DE SANTIAGO | E139: HUECHURABA | F139: RM | G139: Compra de la matriz energética | H139: Kwh | I139: 6492 | J139: SEN | K139: =+I139*VLOOKUP(J139,'Factores Emisión EDGE'!$K$228:$L$230,2,FALSE)/1000 -> 1.9514952 | L139: =(I139*0.055028169)/1000 -> 0.35724287
A140: 130 | B140: FRANQUICIA | C140: VALLENAR | D140: ATACAMA | E140: VALLENAR | F140: NORTE | G140: Compra de la matriz energética | H140: Kwh | I140: 6360 | J140: SEN | K140: =+I140*VLOOKUP(J140,'Factores Emisión EDGE'!$K$228:$L$230,2,FALSE)/1000 -> 1.911816 | L140: =(I140*0.055028169)/1000 -> 0.34997915
A141: 131 | B141: FRANQUICIA | C141: AVENIDA PAJARITOS FR | D141: METROPOLITANA DE SANTIAGO | E141: MAIPU | F141: RM | G141: Compra de la matriz energética | H141: Kwh | I141: 6311.6882 | J141: SEN | K141: =+I141*VLOOKUP(J141,'Factores Emisión EDGE'!$K$228:$L$230,2,FALSE)/1000 -> 1.8972935 | L141: =(I141*0.055028169)/1000 -> 0.34732065
A142: 132 | B142: FRANQUICIA | C142: CONCEPCION ROTONDA GENERAL BONILLA | D142: BIOBIO | E142: CONCEPCION | F142: SUR | G142: Compra de la matriz energética | H142: Kwh | I142: 6214 | J142: SEN | K142: =+I142*VLOOKUP(J142,'Factores Emisión EDGE'!$K$228:$L$230,2,FALSE)/1000 -> 1.8679284 | L142: =(I142*0.055028169)/1000 -> 0.34194504
A143: 133 | B143: FRANQUICIA | C143: PLAZA EGAÑA | D143: METROPOLITANA DE SANTIAGO | E143: NUNOA | F143: RM | G143: Compra de la matriz energética | H143: Kwh | I143: 6080.07 | J143: SEN | K143: =+I143*VLOOKUP(J143,'Factores Emisión EDGE'!$K$228:$L$230,2,FALSE)/1000 -> 1.827669 | L143: =(I143*0.055028169)/1000 -> 0.33457512
A144: 134 | B144: OFICINA PROPIA | C144: RENCA | D144: METROPOLITANA DE SANTIAGO | E144: RENCA | F144: RM | G144: Compra de la matriz energética | H144: Kwh | I144: 6035.07 | J144: SEN | K144: =+I144*VLOOKUP(J144,'Factores Emisión EDGE'!$K$228:$L$230,2,FALSE)/1000 -> 1.814142 | L144: =(I144*0.055028169)/1000 -> 0.33209885
... A241: 231 | B241: OFICINA PROPIA | C241: PUERTO MONTT EL TEPUAL | D241: LOS LAGOS | E241: PUERTO MONTT | F241: AUSTRAL | G241: Compra de la matriz energética | H241: Kwh | I241: 7.1818182 | J241: SEN | K241: =+I241*VLOOKUP(J241,'Factores Emisión EDGE'!$K$228:$L$230,2,FALSE)/1000 -> 0.0021588545 | L241: =(I241*0.055028169)/1000 -> 0.0003952023

Sheet 8. Insumos y Empaque
A1: USO DE EMPAQUE
B3: Por favor llene la siguiente información sobre la compra de empaques para elementos despachados durante el año calendario 2021.
B6: TIPO DE RESPALDOS: | C6: Facturas, registros internos de compras, SAP u otros.
B8: Empaque y Fin de Vida / Insumos Operacionales 2022 | I8: Gasto en pesos | J8: Compra | K8: Fin de vida | L8: TOTAL
B9: Categoria de Emisión | C9: Cuenta Contable | D9: Tipo de empaque | E9: Producto | F9: Materialidad | G9: Q unidades | H9: Peso de materiales (ton) | I9: CLP | J9: ton CO2-e | K9: ton CO2-e | L9: ton CO2-e
B10: Empaque y fin de vida | C10: LINEA DE EMBALAJE CH | D10: INSUMO DE EMBALAJE | E10: Cajas | F10: Cartón | G10: 1064326 | H10: 227 | I10: 427031797 | J10: =+H10*(1.6%*(85%*'Factores Emisión EDGE'!L211+15%*'Factores Emisión EDGE'!L210)+((100%-1.6%)*'Factores Emisión EDGE'!L211)) -> 7.821705 | K10: =+((H10*5%*'Factores Emisión EDGE'!L157)+('8. Insumos y Empaque'!H10*95%*'Factores Emisión EDGE'!L130)) -> 400.85865 | L10: =K10+J10 -> 408.68036
B11: Empaque y fin de vida | C11: LINEA DE EMBALAJE CH | D11: INSUMO DE EMBALAJE | E11: Sobre | F11: Papel | G11: 860900 | H11: 29 | I11: 86258000 | J11: =+H11*VLOOKUP(F11,'Factores Emisión EDGE'!$K$204:$L$218,2,FALSE) -> 71.446421 | K11: =+H11*'Factores Emisión EDGE'!$L$129 -> 61.854465 | L11: =K11+J11 -> 133.30089
B12: Empaque y fin de vida | C12: MATERIALES GP | D12: INSUMO DE EMBALAJE | E12: Etiquetas | F12: Adhesivo | G12: 20639 | H12: 21 | I12: 52206036 | J12: =+H12*VLOOKUP(F12,'Factores Emisión EDGE'!$K$204:$L$218,2,FALSE) -> 61.463422 | K12: =+H12*'Factores Emisión EDGE'!$L$134 -> 42.345444 | L12: =K12+J12 -> 103.80887
B13: Empaque y fin de vida | C13: MATERIALES GP | D13: INSUMO DE EMBALAJE | E13: Cinta | F13: Adhesivo | G13: 188057 | H13: 16 | I13: 76453893 | J13: =+H13*VLOOKUP(F13,'Factores Emisión EDGE'!$K$204:$L$218,2,FALSE) -> 46.829274 | K13: =+H13*'Factores Emisión EDGE'!$L$134 -> 32.263195 | L13: =K13+J13 -> 79.092469
B14: Empaque y fin de vida | C14: MATERIALES GP | D14: INSUMO DE EMBALAJE | E14: Logo | F14: Adhesivo | G14: 1642 | H14: 1 | I14: 4869040 | J14: =+H14*VLOOKUP(F14,'Factores Emisión EDGE'!$K$204:$L$218,2,FALSE) -> 2.9268296 | K14: =+H14*'Factores Emisión EDGE'!$L$134 -> 2.0164497 | L14: =K14+J14 -> 4.9432793
B15: Empaque y fin de vida | C15: LINEA DE EMBALAJE CH | D15: INSUMO DE EMBALAJE | E15: Valija | F15: Cuero | G15: 30 | H15: 0.0234 | I15: 972540 | J15: =+H15*VLOOKUP(F15,'Factores Emisión EDGE'!$K$204:$L$218,2,FALSE) -> 0.0035594064 | K15: =+H15*'Factores Emisión EDGE'!$L$135 -> 0.0017517266 | L15: =K15+J15 -> 0.005311133
B16: Insumos Operacionales | C16: MATERIALES GP | D16: INSUMO OPERACIONAL | E16: Film | F16: PE baja densidad | G16: 92904 | H16: 149.196 | I16: 315902280 | J16: =+H16*VLOOKUP(F16,'Factores Emisión EDGE'!$K$204:$L$218,2,FALSE) -> 375.3547 | K16: 0 | L16: =K16+J16 -> 375.3547
B17: Insumos Operacionales | C17: MATERIALES GP | D17: INSUMO OPERACIONAL | E17: Bandeja | F17: PE alta densidad | G17: 18080 | H17: 66.5344 | I17: 147885120 | J17: =+H17*VLOOKUP(F17,'Factores Emisión EDGE'!$K$204:$L$218,2,FALSE) -> 154.56825 | K17: 0 | L17: =K17+J17 -> 154.56825
B18: Insumos Operacionales | C18: MATERIALES GP | D18: INSUMO OPERACIONAL | E18: Bolsa | F18: PE baja densidad | G18: 940245 | H18: 39.260843 | I18: 58093800 | J18: =+H18*VLOOKUP(F18,'Factores Emisión EDGE'!$K$204:$L$218,2,FALSE) -> 98.774376 | K18: 0 | L18: =K18+J18 -> 98.774376
B19: Insumos Operacionales | C19: MATERIALES GP | D19: INSUMO OPERACIONAL | E19: Pallet | F19: Madera | G19: 20354 | H19: 508.85 | I19: 89807310 | J19: =+H19*VLOOKUP(F19,'Factores Emisión EDGE'!$K$204:$L$218,2,FALSE) -> 77.401878 | K19: 0 | L19: =K19+J19 -> 77.401878
B20: Insumos Operacionales | C20: MATERIALES GP | D20: INSUMO OPERACIONAL | E20: Rollo | F20: Papel | G20: 69780 | H20: 21.6318 | I20: 75705180 | J20: =+H20*VLOOKUP(F20,'Factores Emisión EDGE'!$K$204:$L$218,2,FALSE) -> 53.29361 | K20: 0 | L20: =K20+J20 -> 53.29361
B21: Insumos Operacionales | C21: MATERIALES GP | D21: INSUMO OPERACIONAL | E21: Ventanilla | F21: Plástico | G21: 2345000 | H21: 6.21425 | I21: 26733000 | J21: =+H21*VLOOKUP(F21,'Factores Emisión EDGE'!$K$204:$L$218,2,FALSE) -> 15.534275 | K21: 0 | L21: =K21+J21 -> 15.534275
B22: Insumos Operacionales | C22: MATERIALES GP | D22: INSUMO OPERACIONAL | E22: Sello | F22: Plástico | G22: 878000 | H22: 4.39 | I22: 43248000 | J22: =+H22*VLOOKUP(F22,'Factores Emisión EDGE'!$K$204:$L$218,2,FALSE) -> 10.974046 | K22: 0 | L22: =K22+J22 -> 10.974046
B23: Insumos Operacionales | C23: MATERIALES GP | D23: INSUMO OPERACIONAL | E23: Cinta | F23: Adhesivo | G23: 5976 | H23: 0.47808 | I23: 3083616 | J23: =+H23*VLOOKUP(F23,'Factores Emisión EDGE'!$K$204:$L$218,2,FALSE) -> 1.3992587 | K23: 0 | L23: =K23+J23 -> 1.3992587
B24: Insumos Operacionales | C24: MATERIALES GP | D24: INSUMO OPERACIONAL | E24: Cajas | F24: Cartón | G24: 4100 | H24: 2.05 | I24: 3356500 | J24: =+H24*VLOOKUP(F24,'Factores Emisión EDGE'!$K$204:$L$218,2,FALSE) -> 1.2793524 | K24: 0 | L24: =K24+J24 -> 1.2793524
B25: Insumos Operacionales | C25: MATERIALES GP | D25: INSUMO OPERACIONAL | E25: Carpeta | F25: Papel | G25: 4000 | H25: 0.22 | I25: 2120000 | J25: =+H25*VLOOKUP(F25,'Factores Emisión EDGE'!$K$204:$L$218,2,FALSE) -> 0.54200733 | K25: 0 | L25: =K25+J25 -> 0.54200733
B26: Insumos Operacionales | C26: MATERIALES GP | D26: INSUMO OPERACIONAL | E26: Libreta | F26: Papel | G26: 200 | H26: 0.0515 | I26: 685000 | J26: =+H26*VLOOKUP(F26,'Factores Emisión EDGE'!$K$204:$L$218,2,FALSE) -> 0.12687899 | K26: 0 | L26: =K26+J26 -> 0.12687899
G27: Total | H27: =+SUM(H10:H26) -> 1092.9003 | I27: =+SUM(I10:I26) -> 1414411112 | J27: =+SUM(J10:J26) -> 979.73984 | K27: =+SUM(K10:K26) -> 539.33996 | L27: =K27+J27 -> 1519.0798
G28: Empaque y fin de vida | H28: =SUM(H10:H15) -> 294.0234 | I28: =SUM(I10:I15) -> 647791306 | J28: =+SUM(J10:J15) -> 190.49121 | K28: 539.38539 | L28: =K28+J28 -> 729.8766
G29: Insumo Operacional | H29: =SUM(H16:H26) -> 798.87687 | I29: =SUM(I16:I26) -> 766619806 | J29: =+SUM(J16:J26) -> 789.24863 | K29: 0 | L29: =J29 -> 789.24863
B31: Emisiones Cajas de Cartón con % Fibra Reciclada 2022
B32: Nombre del producto | C32: Peso (ton) | D32: Composición | E32: % Fibra reciclada | F32: % Fibra Virgen | G32: Factor reciclado uso | H32: Factor virgen uso | I32: Factor fin de vida | J32: CO2 compra | K32: CO2 fin de vida | L32: TOTAL
B33: Caja grande café | C33: 50.66256 | D33: 0.22362723 | E33: 1 | F33: 0 | G33: ='Factores Emisión EDGE'!$L$211 -> 0.033038364 | H33: ='Factores Emisión EDGE'!$L$210 -> 0.62407433 | I33: =95%*'Factores Emisión EDGE'!$L$130 -> 1.7658971 | J33: =((C33*E33*G33)+(C33*F33*H33)) -> 1.6738081 | K33: =C33*I33 -> 89.46487 | L33: =K33+J33 -> 91.138678
B34: Caja mediana autoarmable | C34: 49 | D34: 0.21381673 | E34: 1 | F34: 0 | G34: ='Factores Emisión EDGE'!$L$211 -> 0.033038364 | H34: ='Factores Emisión EDGE'!$L$210 -> 0.62407433 | I34: =95%*'Factores Emisión EDGE'!$L$130 -> 1.7658971 | J34: =((C34*E34*G34)+(C34*F34*H34)) -> 1.6188798 | K34: =C34*I34 -> 86.52896 | L34: =K34+J34 -> 88.14784
B35: Caja chica autoarmable | C35: 41.32 | D35: 0.18238867 | E35: 1 | F35: 0 | G35: ='Factores Emisión EDGE'!$L$211 -> 0.033038364 | H35: ='Factores Emisión EDGE'!$L$210 -> 0.62407433 | I35: =95%*'Factores Emisión EDGE'!$L$130 -> 1.7658971 | J35: =((C35*E35*G35)+(C35*F35*H35)) -> 1.3651452 | K35: =C35*I35 -> 72.96687 | L35: =K35+J35 -> 74.332015
B36: Caja multiproposito autoarmable | C36: 31.73 | D36: 0.1400579 | E36: 1 | F36: 0 | G36: ='Factores Emisión EDGE'!$L$211 -> 0.033038364 | H36: ='Factores Emisión EDGE'!$L$210 -> 0.62407433 | I36: =95%*'Factores Emisión EDGE'!$L$130 -> 1.7658971 | J36: =((C36*E36*G36)+(C36*F36*H36)) -> 1.0483073 | K36: =C36*I36 -> 56.031916 | L36: =K36+J36 -> 57.080224
B37: Caja sin cuna | C37: 29.195 | D37: 0.12886828 | E37: 1 | F37: 0 | G37: ='Factores Emisión EDGE'!$L$211 -> 0.033038364 | H37: ='Factores Emisión EDGE'!$L$210 -> 0.62407433 | I37: =95%*'Factores Emisión EDGE'!$L$130 -> 1.7658971 | J37: =((C37*E37*G37)+(C37*F37*H37)) -> 0.96455504 | K37: =C37*I37 -> 51.555367 | L37: =K37+J37 -> 52.519922
B38: Caja chica | C38: 21.568 | D38: 0.095202295 | E38: 1 | F38: 0 | G38: ='Factores Emisión EDGE'!$L$211 -> 0.033038364 | H38: ='Factores Emisión EDGE'!$L$210 -> 0.62407433 | I38: =95%*'Factores Emisión EDGE'!$L$130 -> 1.7658971 | J38: =((C38*E38*G38)+(C38*F38*H38)) -> 0.71257143 | K38: =C38*I38 -> 38.08687 | L38: =K38+J38 -> 38.799441
B39: Caja roja celular | C39: 3.6336 | D39: 0.016038903 | E39: 0.85 | F39: 0.15 | G39: ='Factores Emisión EDGE'!$L$211 -> 0.033038364 | H39: ='Factores Emisión EDGE'!$L$210 -> 0.62407433 | I39: =95%*'Factores Emisión EDGE'!$L$130 -> 1.7658971 | J39: =((C39*E39*G39)+(C39*F39*H39)) -> 0.44218644 | K39: =C39*I39 -> 6.4165639 | L39: =K39+J39 -> 6.8587503
C40: =SUM(C33:C39) -> 227.10916 | D40: =SUM(D33:D39) -> 1 | E40: - | F40: - | G40: - | H40: - | I40: Total | J40: =SUM(J33:J39) -> 7.8254533 | K40: =SUM(K33:K39) -> 401.05142 | L40: =SUM(L33:L39) -> 408.87687
B41: % de materiales reciclados | C41: =1-(C39*0.15/C40) -> 0.9976001
B42: % de materiales virgen | C42: =C39*F39/C40 -> 0.0023999032 | I42: Emisiones evitadas CO2 | J42: =-(C40*H33)-J40 -> -149.55845 | K42: ton CO2
I43: Emisiones evitadas del total | J43: =J42/(J42+L27) -> -0.10920491
B45: Empaque y Fin de Vida / Insumos Operacionales 2021 | I45: Gasto en pesos | J45: Compra | K45: Fin de vida | L45: TOTAL
B46: Categoria de Emisión | C46: Cuenta Contable | D46: Tipo de empaque | E46: Producto | F46: Materialidad | G46: Q unidades | H46: Peso de materiales (ton) | I46: CLP | J46: ton CO2-e | K46: ton CO2-e | L46: ton CO2-e
B47: Empaque y fin de vida | C47: LINEA DE EMBALAJE CH | D47: INSUMO DE EMBALAJE | E47: Cajas | F47: Cartón | G47: 3503246 | H47: 692.39 | I47: 779938633 | J47: =+H47*(1.6%*(85%*'Factores Emisión EDGE'!L211+15%*'Factores Emisión EDGE'!L210)+((100%-1.6%)*'Factores Emisión EDGE'!L211)) -> 23.857579 | K47: =+((H47*5%*'Factores Emisión EDGE'!L157)+('8. Insumos y Empaque'!H47*95%*'Factores Emisión EDGE'!L130)) -> 1222.6895 | L47: =K47+J47 -> 1246.5471
B48: Empaque y fin de vida | C48: LINEA DE EMBALAJE CH | D48: INSUMO DE EMBALAJE | E48: Sobre | F48: Papel | G48: 2126561 | H48: 78.79 | I48: 209686797 | J48: =+H48*VLOOKUP(F48,'Factores Emisión EDGE'!$K$204:$L$218,2,FALSE) -> 194.11254 | K48: =+((H48*5%*'Factores Emisión EDGE'!L157)+('8. Insumos y Empaque'!H48*95%*'Factores Emisión EDGE'!L129)) -> 159.64957 | L48: =K48+J48 -> 353.76211
B49: Empaque y fin de vida | C49: MATERIALES GP | D49: INSUMO DE EMBALAJE | E49: Etiquetas | F49: Adhesivo | G49: 57875 | H49: 47.97 | I49: 102600669 | J49: =+H49*VLOOKUP(F49,'Factores Emisión EDGE'!$K$204:$L$218,2,FALSE) -> 140.40002 | K49: =+H49*'Factores Emisión EDGE'!$L$134 -> 96.729092 | L49: =K49+J49 -> 237.12911
B50: Empaque y fin de vida | C50: MATERIALES GP | D50: INSUMO DE EMBALAJE | E50: Cinta | F50: Adhesivo | G50: 291713 | H50: 26.06 | I50: 106018404 | J50: =+H50*VLOOKUP(F50,'Factores Emisión EDGE'!$K$204:$L$218,2,FALSE) -> 76.273179 | K50: =+H50*'Factores Emisión EDGE'!$L$134 -> 52.548679 | L50: =K50+J50 -> 128.82186
B51: Empaque y fin de vida | C51: MATERIALES GP | D51: INSUMO DE EMBALAJE | E51: Logo | F51: Adhesivo | G51: 2662 | H51: 1.36 | I51: 4659666 | J51: =+H51*VLOOKUP(F51,'Factores Emisión EDGE'!$K$204:$L$218,2,FALSE) -> 3.9804883 | K51: =+H51*'Factores Emisión EDGE'!$L$134 -> 2.7423716 | L51: =K51+J51 -> 6.7228598
B52: Empaque y fin de vida | C52: LINEA DE EMBALAJE CH | D52: INSUMO DE EMBALAJE | E52: Valija | F52: Cuero | G52: 60 | H52: 0.05 | I52: 1920860 | J52: =+H52*VLOOKUP(F52,'Factores Emisión EDGE'!$K$204:$L$218,2,FALSE) -> 0.0076055692 | K52: =+H52*'Factores Emisión EDGE'!$L$135 -> 0.0037430057 | L52: =K52+J52 -> 0.011348575
B53: Insumos Operacionales | C53: MATERIALES GP | D53: INSUMO OPERACIONAL | E53: Film | F53: PE baja densidad | G53: 182278 | H53: 291.11 | I53: 483030494 | J53: =+H53*VLOOKUP(F53,'Factores Emisión EDGE'!$K$204:$L$218,2,FALSE) -> 732.38898 | K53: 0 | L53: =K53+J53 -> 732.38898
B54: Insumos Operacionales | C54: MATERIALES GP | D54: INSUMO OPERACIONAL | E54: Bandeja | F54: PE alta densidad | G54: 76655 | H54: 282.09 | I54: 502061472 | J54: =+H54*VLOOKUP(F54,'Factores Emisión EDGE'!$K$204:$L$218,2,FALSE) -> 655.33256 | K54: 0 | L54: =K54+J54 -> 655.33256
B55: Insumos Operacionales | C55: MATERIALES GP | D55: INSUMO OPERACIONAL | E55: Sello | F55: Plástico | G55: 840000 | H55: 227 | I55: 28620000 | J55: =+H55*VLOOKUP(F55,'Factores Emisión EDGE'!$K$204:$L$218,2,FALSE) -> 567.45068 | K55: 0 | L55: =K55+J55 -> 567.45068
B56: Insumos Operacionales | C56: MATERIALES GP | D56: INSUMO OPERACIONAL | E56: Bolsa | F56: PE baja densidad | G56: 1383290 | H56: 56.98 | I56: 75251840 | J56: =+H56*VLOOKUP(F56,'Factores Emisión EDGE'!$K$204:$L$218,2,FALSE) -> 143.35311 | K56: 0 | L56: =K56+J56 -> 143.35311
B57: Insumos Operacionales | C57: MATERIALES GP | D57: INSUMO OPERACIONAL | E57: Rollo | F57: Papel | G57: 110360 | H57: 34.21 | I57: 69320340 | J57: =+H57*VLOOKUP(F57,'Factores Emisión EDGE'!$K$204:$L$218,2,FALSE) -> 84.28214 | K57: 0 | L57: =K57+J57 -> 84.28214
B58: Insumos Operacionales | C58: MATERIALES GP | D58: INSUMO OPERACIONAL | E58: Pallet | F58: Madera | G58: 10411 | H58: 260.28 | I58: 40969410 | J58: =+H58*VLOOKUP(F58,'Factores Emisión EDGE'!$K$204:$L$218,2,FALSE) -> 39.591551 | K58: 0 | L58: =K58+J58 -> 39.591551
B59: Insumos Operacionales | C59: MATERIALES GP | D59: INSUMO OPERACIONAL | E59: Ventanilla | F59: Plástico | G59: 2609000 | H59: 7 | I59: 30264400 | J59: =+H59*VLOOKUP(F59,'Factores Emisión EDGE'!$K$204:$L$218,2,FALSE) -> 17.498479 | K59: 0 | L59: =K59+J59 -> 17.498479
B60: Insumos Operacionales | C60: MATERIALES GP | D60: INSUMO OPERACIONAL | E60: Cajas | F60: Cartón | G60: 15542 | H60: 10.9 | I60: 8458552 | J60: =+H60*VLOOKUP(F60,'Factores Emisión EDGE'!$K$204:$L$218,2,FALSE) -> 6.8024102 | K60: 0 | L60: =K60+J60 -> 6.8024102
B61: Insumos Operacionales | C61: MATERIALES GP | D61: INSUMO OPERACIONAL | E61: Libreta | F61: Papel | G61: 3200 | H61: 0.23 | I61: 1031000 | J61: =+H61*VLOOKUP(F61,'Factores Emisión EDGE'!$K$204:$L$218,2,FALSE) -> 0.56664403 | K61: 0 | L61: =K61+J61 -> 0.56664403
G62: Total | H62: =+SUM(H47:H61) -> 2016.42 | I62: =+SUM(I47:I61) -> 2443832537 | J62: =+SUM(J47:J61) -> 2685.898 | K62: =+SUM(K47:K61) -> 1534.363 | L62: =K62+J62 -> 4220.2609
G63: Empaque y fin de vida | H63: =SUM(H47:H52) -> 846.62 | I63: =SUM(I47:I52) -> 1204825029 | J63: =+SUM(J47:J52) -> 438.6314 | K63: =K62 -> 1534.363 | L63: =K63+J63 -> 1972.9944
G64: Insumo Operacional | H64: =SUM(H53:H61) -> 1169.8 | I64: =SUM(I53:I61) -> 1239007508 | J64: =+SUM(J53:J61) -> 2247.2665 | K64: - | L64: =J64 -> 2247.2665
B66: Emisiones Cajas de Cartón con % Fibra Reciclada 2021
B67: Nombre del producto | C67: Peso (ton) | D67: Composición | E67: % Fibra reciclada | F67: % Fibra Virgen | G67: Factor reciclado uso | H67: Factor virgen uso | I67: Factor fin de vida | J67: CO2 compra | K67: CO2 fin de vida | L67: TOTAL
B68: Caja grande café | C68: 127.5924 | D68: =C68/$C$79 -> 0.18427922 | E68: 1 | F68: 0 | G68: ='Factores Emisión EDGE'!$L$211 -> 0.033038364 | H68: ='Factores Emisión EDGE'!$L$210 -> 0.62407433 | I68: =95%*'Factores Emisión EDGE'!$L$130 -> 1.7658971 | J68: =((C68*E68*G68)+(C68*F68*H68)) -> 4.2154442 | K68: =C68*I68 -> 225.31505 | L68: =K68+J68 -> 229.5305
B69: Caja mediana autoarmable | C69: 129.0444 | D69: =C69/$C$79 -> 0.18637632 | E69: 1 | F69: 0 | G69: ='Factores Emisión EDGE'!$L$211 -> 0.033038364 | H69: ='Factores Emisión EDGE'!$L$210 -> 0.62407433 | I69: =95%*'Factores Emisión EDGE'!$L$130 -> 1.7658971 | J69: =((C69*E69*G69)+(C69*F69*H69)) -> 4.2634159 | K69: =C69*I69 -> 227.87914 | L69: =K69+J69 -> 232.14255
B70: Caja chica autoarmable | C70: 130.63 | D70: =C70/$C$79 -> 0.18866637 | E70: 1 | F70: 0 | G70: ='Factores Emisión EDGE'!$L$211 -> 0.033038364 | H70: ='Factores Emisión EDGE'!$L$210 -> 0.62407433 | I70: =95%*'Factores Emisión EDGE'!$L$130 -> 1.7658971 | J70: =((C70*E70*G70)+(C70*F70*H70)) -> 4.3158015 | K70: =C70*I70 -> 230.67914 | L70: =K70+J70 -> 234.99495
B71: Caja multiproposito autoarmable | C71: 83.931 | D71: =C71/$C$79 -> 0.12121991 | E71: 1 | F71: 0 | G71: ='Factores Emisión EDGE'!$L$211 -> 0.033038364 | H71: ='Factores Emisión EDGE'!$L$210 -> 0.62407433 | I71: =95%*'Factores Emisión EDGE'!$L$130 -> 1.7658971 | J71: =((C71*E71*G71)+(C71*F71*H71)) -> 2.7729429 | K71: =C71*I71 -> 148.21351 | L71: =K71+J71 -> 150.98646
